{"sections":[],"variants":[{"paths":["\/documentation\/openswiftui\/hstack\/view-implementations"],"traits":[{"interfaceLanguage":"swift"}]}],"kind":"article","identifier":{"interfaceLanguage":"swift","url":"doc:\/\/OpenSwiftUI\/documentation\/OpenSwiftUI\/HStack\/View-Implementations"},"schemaVersion":{"major":0,"patch":0,"minor":3},"hierarchy":{"paths":[["doc:\/\/OpenSwiftUI\/documentation\/OpenSwiftUI","doc:\/\/OpenSwiftUI\/documentation\/OpenSwiftUI\/HStack"]]},"topicSections":[{"title":"Instance Methods","identifiers":["doc:\/\/OpenSwiftUI\/documentation\/OpenSwiftUI\/HStack\/animation(_:)","doc:\/\/OpenSwiftUI\/documentation\/OpenSwiftUI\/HStack\/animation(_:body:)","doc:\/\/OpenSwiftUI\/documentation\/OpenSwiftUI\/HStack\/animation(_:value:)","doc:\/\/OpenSwiftUI\/documentation\/OpenSwiftUI\/HStack\/aspectRatio(_:contentMode:)-1l4w2","doc:\/\/OpenSwiftUI\/documentation\/OpenSwiftUI\/HStack\/aspectRatio(_:contentMode:)-744xo","doc:\/\/OpenSwiftUI\/documentation\/OpenSwiftUI\/HStack\/background(_:alignment:)","doc:\/\/OpenSwiftUI\/documentation\/OpenSwiftUI\/HStack\/background(alignment:content:)","doc:\/\/OpenSwiftUI\/documentation\/OpenSwiftUI\/HStack\/clipShape(_:style:)","doc:\/\/OpenSwiftUI\/documentation\/OpenSwiftUI\/HStack\/clipped(antialiased:)","doc:\/\/OpenSwiftUI\/documentation\/OpenSwiftUI\/HStack\/colorScheme(_:)","doc:\/\/OpenSwiftUI\/documentation\/OpenSwiftUI\/HStack\/controlSize(_:)","doc:\/\/OpenSwiftUI\/documentation\/OpenSwiftUI\/HStack\/cornerRadius(_:antialiased:)","doc:\/\/OpenSwiftUI\/documentation\/OpenSwiftUI\/HStack\/disabled(_:)-5vk9y","doc:\/\/OpenSwiftUI\/documentation\/OpenSwiftUI\/HStack\/disabled(_:)-6q0je","doc:\/\/OpenSwiftUI\/documentation\/OpenSwiftUI\/HStack\/dynamicTypeSize(_:)","doc:\/\/OpenSwiftUI\/documentation\/OpenSwiftUI\/HStack\/edgesIgnoringSafeArea(_:)","doc:\/\/OpenSwiftUI\/documentation\/OpenSwiftUI\/HStack\/environment(_:)","doc:\/\/OpenSwiftUI\/documentation\/OpenSwiftUI\/HStack\/environment(_:_:)","doc:\/\/OpenSwiftUI\/documentation\/OpenSwiftUI\/HStack\/environmentObject(_:)","doc:\/\/OpenSwiftUI\/documentation\/OpenSwiftUI\/HStack\/fixedSize()","doc:\/\/OpenSwiftUI\/documentation\/OpenSwiftUI\/HStack\/fixedSize(horizontal:vertical:)","doc:\/\/OpenSwiftUI\/documentation\/OpenSwiftUI\/HStack\/font(_:)","doc:\/\/OpenSwiftUI\/documentation\/OpenSwiftUI\/HStack\/foregroundStyle(_:)","doc:\/\/OpenSwiftUI\/documentation\/OpenSwiftUI\/HStack\/foregroundStyle(_:_:)","doc:\/\/OpenSwiftUI\/documentation\/OpenSwiftUI\/HStack\/foregroundStyle(_:_:_:)","doc:\/\/OpenSwiftUI\/documentation\/OpenSwiftUI\/HStack\/frame()","doc:\/\/OpenSwiftUI\/documentation\/OpenSwiftUI\/HStack\/frame(minWidth:idealWidth:maxWidth:minHeight:idealHeight:maxHeight:alignment:)","doc:\/\/OpenSwiftUI\/documentation\/OpenSwiftUI\/HStack\/frame(width:height:alignment:)","doc:\/\/OpenSwiftUI\/documentation\/OpenSwiftUI\/HStack\/geometryGroup()","doc:\/\/OpenSwiftUI\/documentation\/OpenSwiftUI\/HStack\/id(_:)","doc:\/\/OpenSwiftUI\/documentation\/OpenSwiftUI\/HStack\/ignoresSafeArea(_:edges:)","doc:\/\/OpenSwiftUI\/documentation\/OpenSwiftUI\/HStack\/layoutPriority(_:)","doc:\/\/OpenSwiftUI\/documentation\/OpenSwiftUI\/HStack\/layoutValue(key:value:)","doc:\/\/OpenSwiftUI\/documentation\/OpenSwiftUI\/HStack\/modifier(_:)","doc:\/\/OpenSwiftUI\/documentation\/OpenSwiftUI\/HStack\/offset(_:)","doc:\/\/OpenSwiftUI\/documentation\/OpenSwiftUI\/HStack\/offset(x:y:)","doc:\/\/OpenSwiftUI\/documentation\/OpenSwiftUI\/HStack\/onAppear(perform:)","doc:\/\/OpenSwiftUI\/documentation\/OpenSwiftUI\/HStack\/onChange(of:initial:_:)-40uio","doc:\/\/OpenSwiftUI\/documentation\/OpenSwiftUI\/HStack\/onChange(of:initial:_:)-5eup8","doc:\/\/OpenSwiftUI\/documentation\/OpenSwiftUI\/HStack\/onChange(of:perform:)","doc:\/\/OpenSwiftUI\/documentation\/OpenSwiftUI\/HStack\/onDisappear(perform:)","doc:\/\/OpenSwiftUI\/documentation\/OpenSwiftUI\/HStack\/overlay(_:alignment:)","doc:\/\/OpenSwiftUI\/documentation\/OpenSwiftUI\/HStack\/overlay(alignment:content:)","doc:\/\/OpenSwiftUI\/documentation\/OpenSwiftUI\/HStack\/padding(_:)-1v6zm","doc:\/\/OpenSwiftUI\/documentation\/OpenSwiftUI\/HStack\/padding(_:)-9lzq1","doc:\/\/OpenSwiftUI\/documentation\/OpenSwiftUI\/HStack\/padding(_:_:)","doc:\/\/OpenSwiftUI\/documentation\/OpenSwiftUI\/HStack\/preference(key:value:)","doc:\/\/OpenSwiftUI\/documentation\/OpenSwiftUI\/HStack\/rotation3DEffect(_:axis:anchor:anchorZ:perspective:)","doc:\/\/OpenSwiftUI\/documentation\/OpenSwiftUI\/HStack\/rotationEffect(_:anchor:)","doc:\/\/OpenSwiftUI\/documentation\/OpenSwiftUI\/HStack\/safeAreaInset(edge:alignment:spacing:content:)-21g","doc:\/\/OpenSwiftUI\/documentation\/OpenSwiftUI\/HStack\/safeAreaInset(edge:alignment:spacing:content:)-rses","doc:\/\/OpenSwiftUI\/documentation\/OpenSwiftUI\/HStack\/safeAreaPadding(_:)-3sho9","doc:\/\/OpenSwiftUI\/documentation\/OpenSwiftUI\/HStack\/safeAreaPadding(_:)-4swtm","doc:\/\/OpenSwiftUI\/documentation\/OpenSwiftUI\/HStack\/safeAreaPadding(_:_:)","doc:\/\/OpenSwiftUI\/documentation\/OpenSwiftUI\/HStack\/scaledToFill()","doc:\/\/OpenSwiftUI\/documentation\/OpenSwiftUI\/HStack\/scaledToFit()","doc:\/\/OpenSwiftUI\/documentation\/OpenSwiftUI\/HStack\/task(id:priority:_:)","doc:\/\/OpenSwiftUI\/documentation\/OpenSwiftUI\/HStack\/task(priority:_:)","doc:\/\/OpenSwiftUI\/documentation\/OpenSwiftUI\/HStack\/tint(_:)","doc:\/\/OpenSwiftUI\/documentation\/OpenSwiftUI\/HStack\/toggleStyle(_:)","doc:\/\/OpenSwiftUI\/documentation\/OpenSwiftUI\/HStack\/transaction(_:)","doc:\/\/OpenSwiftUI\/documentation\/OpenSwiftUI\/HStack\/transaction(_:body:)","doc:\/\/OpenSwiftUI\/documentation\/OpenSwiftUI\/HStack\/transaction(value:_:)","doc:\/\/OpenSwiftUI\/documentation\/OpenSwiftUI\/HStack\/transformEnvironment(_:transform:)","doc:\/\/OpenSwiftUI\/documentation\/OpenSwiftUI\/HStack\/transformPreference(_:_:)","doc:\/\/OpenSwiftUI\/documentation\/OpenSwiftUI\/HStack\/zIndex(_:)"],"anchor":"Instance-Methods","generated":true}],"metadata":{"modules":[{"name":"OpenSwiftUI"}],"title":"View Implementations","role":"collectionGroup","roleHeading":"API Collection"},"references":{"doc://OpenSwiftUI/documentation/OpenSwiftUI/HStack/onChange(of:initial:_:)-5eup8":{"title":"onChange(of:initial:_:)","type":"topic","kind":"symbol","abstract":[{"text":"Adds a modifier for this view that fires an action when a specific","type":"text"},{"text":" ","type":"text"},{"text":"value changes.","type":"text"}],"role":"symbol","fragments":[{"text":"func","kind":"keyword"},{"text":" ","kind":"text"},{"text":"onChange","kind":"identifier"},{"text":"<","kind":"text"},{"text":"V","kind":"genericParameter"},{"text":">(","kind":"text"},{"text":"of","kind":"externalParam"},{"text":": ","kind":"text"},{"text":"V","kind":"typeIdentifier"},{"text":", ","kind":"text"},{"text":"initial","kind":"externalParam"},{"text":": ","kind":"text"},{"text":"Bool","preciseIdentifier":"s:Sb","kind":"typeIdentifier"},{"text":", (","kind":"text"},{"text":"V","kind":"typeIdentifier"},{"text":", ","kind":"text"},{"text":"V","kind":"typeIdentifier"},{"text":") -> ","kind":"text"},{"text":"Void","preciseIdentifier":"s:s4Voida","kind":"typeIdentifier"},{"text":") -> ","kind":"text"},{"text":"some","kind":"keyword"},{"text":" ","kind":"text"},{"text":"View","preciseIdentifier":"s:15OpenSwiftUICore4ViewP","kind":"typeIdentifier"}],"url":"\/documentation\/openswiftui\/hstack\/onchange(of:initial:_:)-5eup8","identifier":"doc:\/\/OpenSwiftUI\/documentation\/OpenSwiftUI\/HStack\/onChange(of:initial:_:)-5eup8"},"doc://OpenSwiftUI/documentation/OpenSwiftUI/HStack/transaction(_:)":{"title":"transaction(_:)","abstract":[{"text":"Applies the given transaction mutation function to all animations used","type":"text"},{"text":" ","type":"text"},{"text":"within the view.","type":"text"}],"kind":"symbol","type":"topic","role":"symbol","fragments":[{"text":"func","kind":"keyword"},{"text":" ","kind":"text"},{"text":"transaction","kind":"identifier"},{"text":"((","kind":"text"},{"text":"inout","kind":"keyword"},{"text":" ","kind":"text"},{"text":"Transaction","preciseIdentifier":"s:15OpenSwiftUICore11TransactionV","kind":"typeIdentifier"},{"text":") -> ","kind":"text"},{"text":"Void","preciseIdentifier":"s:s4Voida","kind":"typeIdentifier"},{"text":") -> ","kind":"text"},{"text":"some","kind":"keyword"},{"text":" ","kind":"text"},{"text":"View","preciseIdentifier":"s:15OpenSwiftUICore4ViewP","kind":"typeIdentifier"}],"url":"\/documentation\/openswiftui\/hstack\/transaction(_:)","identifier":"doc:\/\/OpenSwiftUI\/documentation\/OpenSwiftUI\/HStack\/transaction(_:)"},"doc://OpenSwiftUI/documentation/OpenSwiftUI/HStack/environment(_:_:)":{"role":"symbol","title":"environment(_:_:)","abstract":[{"text":"Sets the environment value of the specified key path to the given value.","type":"text"}],"url":"\/documentation\/openswiftui\/hstack\/environment(_:_:)","type":"topic","identifier":"doc:\/\/OpenSwiftUI\/documentation\/OpenSwiftUI\/HStack\/environment(_:_:)","fragments":[{"text":"func","kind":"keyword"},{"text":" ","kind":"text"},{"text":"environment","kind":"identifier"},{"text":"<","kind":"text"},{"text":"V","kind":"genericParameter"},{"text":">(","kind":"text"},{"text":"WritableKeyPath","kind":"typeIdentifier","preciseIdentifier":"s:s15WritableKeyPathC"},{"text":"<","kind":"text"},{"text":"EnvironmentValues","kind":"typeIdentifier","preciseIdentifier":"s:15OpenSwiftUICore17EnvironmentValuesV"},{"text":", ","kind":"text"},{"text":"V","kind":"typeIdentifier"},{"text":">, ","kind":"text"},{"text":"V","kind":"typeIdentifier"},{"text":") -> ","kind":"text"},{"text":"some","kind":"keyword"},{"text":" ","kind":"text"},{"text":"View","kind":"typeIdentifier","preciseIdentifier":"s:15OpenSwiftUICore4ViewP"}],"kind":"symbol"},"doc://OpenSwiftUI/documentation/OpenSwiftUI/HStack/clipShape(_:style:)":{"url":"\/documentation\/openswiftui\/hstack\/clipshape(_:style:)","role":"symbol","type":"topic","identifier":"doc:\/\/OpenSwiftUI\/documentation\/OpenSwiftUI\/HStack\/clipShape(_:style:)","kind":"symbol","title":"clipShape(_:style:)","abstract":[{"text":"Sets a clipping shape for this view.","type":"text"}],"fragments":[{"kind":"keyword","text":"func"},{"kind":"text","text":" "},{"kind":"identifier","text":"clipShape"},{"kind":"text","text":"<"},{"kind":"genericParameter","text":"S"},{"kind":"text","text":">("},{"kind":"typeIdentifier","text":"S"},{"kind":"text","text":", "},{"kind":"externalParam","text":"style"},{"kind":"text","text":": "},{"kind":"typeIdentifier","preciseIdentifier":"s:15OpenSwiftUICore9FillStyleV","text":"FillStyle"},{"kind":"text","text":") -> "},{"kind":"keyword","text":"some"},{"kind":"text","text":" "},{"kind":"typeIdentifier","preciseIdentifier":"s:15OpenSwiftUICore4ViewP","text":"View"}]},"doc://OpenSwiftUI/documentation/OpenSwiftUI/HStack/layoutValue(key:value:)":{"role":"symbol","title":"layoutValue(key:value:)","type":"topic","identifier":"doc:\/\/OpenSwiftUI\/documentation\/OpenSwiftUI\/HStack\/layoutValue(key:value:)","kind":"symbol","url":"\/documentation\/openswiftui\/hstack\/layoutvalue(key:value:)","abstract":[{"text":"Associates a value with a custom layout property.","type":"text"}],"fragments":[{"text":"func","kind":"keyword"},{"text":" ","kind":"text"},{"text":"layoutValue","kind":"identifier"},{"text":"<","kind":"text"},{"text":"K","kind":"genericParameter"},{"text":">(","kind":"text"},{"text":"key","kind":"externalParam"},{"text":": ","kind":"text"},{"text":"K","kind":"typeIdentifier"},{"text":".Type, ","kind":"text"},{"text":"value","kind":"externalParam"},{"text":": ","kind":"text"},{"text":"K","kind":"typeIdentifier"},{"text":".","kind":"text"},{"text":"Value","kind":"typeIdentifier","preciseIdentifier":"s:15OpenSwiftUICore14LayoutValueKeyP0E0Qa"},{"text":") -> ","kind":"text"},{"text":"some","kind":"keyword"},{"text":" ","kind":"text"},{"text":"View","kind":"typeIdentifier","preciseIdentifier":"s:15OpenSwiftUICore4ViewP"}]},"doc://OpenSwiftUI/documentation/OpenSwiftUI/HStack/animation(_:)":{"type":"topic","fragments":[{"kind":"keyword","text":"func"},{"kind":"text","text":" "},{"kind":"identifier","text":"animation"},{"kind":"text","text":"("},{"preciseIdentifier":"s:15OpenSwiftUICore9AnimationV","kind":"typeIdentifier","text":"Animation"},{"kind":"text","text":"?) -> "},{"kind":"keyword","text":"some"},{"kind":"text","text":" "},{"preciseIdentifier":"s:15OpenSwiftUICore4ViewP","kind":"typeIdentifier","text":"View"}],"kind":"symbol","title":"animation(_:)","url":"\/documentation\/openswiftui\/hstack\/animation(_:)","identifier":"doc:\/\/OpenSwiftUI\/documentation\/OpenSwiftUI\/HStack\/animation(_:)","role":"symbol","deprecated":true,"abstract":[{"type":"text","text":"Applies the given animation to all animatable values within this view."}]},"doc://OpenSwiftUI/documentation/OpenSwiftUI/HStack/task(priority:_:)":{"title":"task(priority:_:)","identifier":"doc:\/\/OpenSwiftUI\/documentation\/OpenSwiftUI\/HStack\/task(priority:_:)","kind":"symbol","abstract":[{"text":"Adds an asynchronous task to perform before this view appears.","type":"text"}],"type":"topic","role":"symbol","url":"\/documentation\/openswiftui\/hstack\/task(priority:_:)","fragments":[{"text":"func","kind":"keyword"},{"text":" ","kind":"text"},{"text":"task","kind":"identifier"},{"text":"(","kind":"text"},{"text":"priority","kind":"externalParam"},{"text":": ","kind":"text"},{"text":"TaskPriority","kind":"typeIdentifier","preciseIdentifier":"s:ScP"},{"text":", () ","kind":"text"},{"text":"async","kind":"keyword"},{"text":" -> ","kind":"text"},{"text":"Void","kind":"typeIdentifier","preciseIdentifier":"s:s4Voida"},{"text":") -> ","kind":"text"},{"text":"some","kind":"keyword"},{"text":" ","kind":"text"},{"text":"View","kind":"typeIdentifier","preciseIdentifier":"s:15OpenSwiftUICore4ViewP"}]},"doc://OpenSwiftUI/documentation/OpenSwiftUI/HStack/clipped(antialiased:)":{"identifier":"doc:\/\/OpenSwiftUI\/documentation\/OpenSwiftUI\/HStack\/clipped(antialiased:)","url":"\/documentation\/openswiftui\/hstack\/clipped(antialiased:)","role":"symbol","abstract":[{"type":"text","text":"Clips this view to its bounding rectangular frame."}],"kind":"symbol","title":"clipped(antialiased:)","type":"topic","fragments":[{"text":"func","kind":"keyword"},{"text":" ","kind":"text"},{"text":"clipped","kind":"identifier"},{"text":"(","kind":"text"},{"text":"antialiased","kind":"externalParam"},{"text":": ","kind":"text"},{"text":"Bool","preciseIdentifier":"s:Sb","kind":"typeIdentifier"},{"text":") -> ","kind":"text"},{"text":"some","kind":"keyword"},{"text":" ","kind":"text"},{"text":"View","preciseIdentifier":"s:15OpenSwiftUICore4ViewP","kind":"typeIdentifier"}]},"doc://OpenSwiftUI/documentation/OpenSwiftUI/HStack/onAppear(perform:)":{"role":"symbol","title":"onAppear(perform:)","abstract":[{"text":"Adds an action to perform before this view appears.","type":"text"}],"url":"\/documentation\/openswiftui\/hstack\/onappear(perform:)","type":"topic","identifier":"doc:\/\/OpenSwiftUI\/documentation\/OpenSwiftUI\/HStack\/onAppear(perform:)","fragments":[{"text":"func","kind":"keyword"},{"text":" ","kind":"text"},{"text":"onAppear","kind":"identifier"},{"text":"(","kind":"text"},{"text":"perform","kind":"externalParam"},{"text":": (() -> ","kind":"text"},{"text":"Void","kind":"typeIdentifier","preciseIdentifier":"s:s4Voida"},{"text":")?) -> ","kind":"text"},{"text":"some","kind":"keyword"},{"text":" ","kind":"text"},{"text":"View","kind":"typeIdentifier","preciseIdentifier":"s:15OpenSwiftUICore4ViewP"}],"kind":"symbol"},"doc://OpenSwiftUI/documentation/OpenSwiftUI/HStack/controlSize(_:)":{"abstract":[{"type":"text","text":"Sets the size for controls within this view."}],"identifier":"doc:\/\/OpenSwiftUI\/documentation\/OpenSwiftUI\/HStack\/controlSize(_:)","type":"topic","url":"\/documentation\/openswiftui\/hstack\/controlsize(_:)","kind":"symbol","fragments":[{"text":"func","kind":"keyword"},{"text":" ","kind":"text"},{"text":"controlSize","kind":"identifier"},{"text":"(","kind":"text"},{"preciseIdentifier":"s:11OpenSwiftUI11ControlSizeO","text":"ControlSize","kind":"typeIdentifier"},{"text":") -> ","kind":"text"},{"text":"some","kind":"keyword"},{"text":" ","kind":"text"},{"preciseIdentifier":"s:15OpenSwiftUICore4ViewP","text":"View","kind":"typeIdentifier"}],"role":"symbol","title":"controlSize(_:)"},"doc://OpenSwiftUI/documentation/OpenSwiftUI/HStack":{"identifier":"doc:\/\/OpenSwiftUI\/documentation\/OpenSwiftUI\/HStack","kind":"symbol","role":"symbol","abstract":[{"text":"A view that arranges its subviews in a horizontal line.","type":"text"}],"fragments":[{"kind":"keyword","text":"struct"},{"kind":"text","text":" "},{"kind":"identifier","text":"HStack"}],"title":"HStack","navigatorTitle":[{"text":"HStack","kind":"identifier"}],"type":"topic","url":"\/documentation\/openswiftui\/hstack"},"doc://OpenSwiftUI/documentation/OpenSwiftUI/HStack/padding(_:)-9lzq1":{"abstract":[{"text":"Adds a specific padding amount to each edge of this view.","type":"text"}],"role":"symbol","fragments":[{"text":"func","kind":"keyword"},{"text":" ","kind":"text"},{"text":"padding","kind":"identifier"},{"text":"(","kind":"text"},{"text":"CGFloat","preciseIdentifier":"s:14CoreFoundation7CGFloatV","kind":"typeIdentifier"},{"text":") -> ","kind":"text"},{"text":"some","kind":"keyword"},{"text":" ","kind":"text"},{"text":"View","preciseIdentifier":"s:15OpenSwiftUICore4ViewP","kind":"typeIdentifier"}],"kind":"symbol","title":"padding(_:)","identifier":"doc:\/\/OpenSwiftUI\/documentation\/OpenSwiftUI\/HStack\/padding(_:)-9lzq1","type":"topic","url":"\/documentation\/openswiftui\/hstack\/padding(_:)-9lzq1"},"doc://OpenSwiftUI/documentation/OpenSwiftUI/HStack/task(id:priority:_:)":{"type":"topic","identifier":"doc:\/\/OpenSwiftUI\/documentation\/OpenSwiftUI\/HStack\/task(id:priority:_:)","title":"task(id:priority:_:)","url":"\/documentation\/openswiftui\/hstack\/task(id:priority:_:)","role":"symbol","kind":"symbol","abstract":[{"text":"Adds a task to perform before this view appears or when a specified","type":"text"},{"text":" ","type":"text"},{"text":"value changes.","type":"text"}],"fragments":[{"kind":"keyword","text":"func"},{"kind":"text","text":" "},{"kind":"identifier","text":"task"},{"kind":"text","text":"<"},{"kind":"genericParameter","text":"T"},{"kind":"text","text":">("},{"kind":"externalParam","text":"id"},{"kind":"text","text":": "},{"kind":"typeIdentifier","text":"T","preciseIdentifier":"s:15OpenSwiftUICore4ViewP0aB2UIE4task2id8priority_Qrqd___ScPyyYaYbctSQRd__lFQO1Tqd__mfp"},{"kind":"text","text":", "},{"kind":"externalParam","text":"priority"},{"kind":"text","text":": "},{"kind":"typeIdentifier","text":"TaskPriority","preciseIdentifier":"s:ScP"},{"kind":"text","text":", () "},{"kind":"keyword","text":"async"},{"kind":"text","text":" -> "},{"kind":"typeIdentifier","text":"Void","preciseIdentifier":"s:s4Voida"},{"kind":"text","text":") -> "},{"kind":"keyword","text":"some"},{"kind":"text","text":" "},{"kind":"typeIdentifier","text":"View","preciseIdentifier":"s:15OpenSwiftUICore4ViewP"}]},"doc://OpenSwiftUI/documentation/OpenSwiftUI/HStack/foregroundStyle(_:)":{"identifier":"doc:\/\/OpenSwiftUI\/documentation\/OpenSwiftUI\/HStack\/foregroundStyle(_:)","title":"foregroundStyle(_:)","abstract":[{"type":"text","text":"Sets a view’s foreground elements to use a given style."}],"type":"topic","kind":"symbol","fragments":[{"text":"func","kind":"keyword"},{"text":" ","kind":"text"},{"text":"foregroundStyle","kind":"identifier"},{"text":"<","kind":"text"},{"text":"S","kind":"genericParameter"},{"text":">(","kind":"text"},{"text":"S","kind":"typeIdentifier"},{"text":") -> ","kind":"text"},{"text":"some","kind":"keyword"},{"text":" ","kind":"text"},{"text":"View","kind":"typeIdentifier","preciseIdentifier":"s:15OpenSwiftUICore4ViewP"}],"url":"\/documentation\/openswiftui\/hstack\/foregroundstyle(_:)","role":"symbol"},"doc://OpenSwiftUI/documentation/OpenSwiftUI/HStack/geometryGroup()":{"role":"symbol","kind":"symbol","fragments":[{"text":"func","kind":"keyword"},{"text":" ","kind":"text"},{"text":"geometryGroup","kind":"identifier"},{"text":"() -> ","kind":"text"},{"text":"some","kind":"keyword"},{"text":" ","kind":"text"},{"text":"View","preciseIdentifier":"s:15OpenSwiftUICore4ViewP","kind":"typeIdentifier"}],"title":"geometryGroup()","type":"topic","abstract":[{"type":"text","text":"Isolates the geometry (e.g. position and size) of the view"},{"type":"text","text":" "},{"type":"text","text":"from its parent view."}],"identifier":"doc:\/\/OpenSwiftUI\/documentation\/OpenSwiftUI\/HStack\/geometryGroup()","url":"\/documentation\/openswiftui\/hstack\/geometrygroup()"},"doc://OpenSwiftUI/documentation/OpenSwiftUI/HStack/frame()":{"kind":"symbol","url":"\/documentation\/openswiftui\/hstack\/frame()","title":"frame()","fragments":[{"text":"func","kind":"keyword"},{"text":" ","kind":"text"},{"text":"frame","kind":"identifier"},{"text":"() -> ","kind":"text"},{"text":"some","kind":"keyword"},{"text":" ","kind":"text"},{"text":"View","preciseIdentifier":"s:15OpenSwiftUICore4ViewP","kind":"typeIdentifier"}],"abstract":[{"text":"Positions this view within an invisible frame.","type":"text"}],"role":"symbol","type":"topic","deprecated":true,"identifier":"doc:\/\/OpenSwiftUI\/documentation\/OpenSwiftUI\/HStack\/frame()"},"doc://OpenSwiftUI/documentation/OpenSwiftUI/HStack/overlay(alignment:content:)":{"abstract":[{"type":"text","text":"Layers the views that you specify in front of this view."}],"identifier":"doc:\/\/OpenSwiftUI\/documentation\/OpenSwiftUI\/HStack\/overlay(alignment:content:)","fragments":[{"text":"func","kind":"keyword"},{"text":" ","kind":"text"},{"text":"overlay","kind":"identifier"},{"text":"<","kind":"text"},{"text":"V","kind":"genericParameter"},{"text":">(","kind":"text"},{"text":"alignment","kind":"externalParam"},{"text":": ","kind":"text"},{"text":"Alignment","preciseIdentifier":"s:15OpenSwiftUICore9AlignmentV","kind":"typeIdentifier"},{"text":", ","kind":"text"},{"text":"content","kind":"externalParam"},{"kind":"text","text":": () -> "},{"kind":"typeIdentifier","text":"V"},{"kind":"text","text":") -> "},{"kind":"keyword","text":"some"},{"kind":"text","text":" "},{"kind":"typeIdentifier","text":"View","preciseIdentifier":"s:15OpenSwiftUICore4ViewP"}],"type":"topic","url":"\/documentation\/openswiftui\/hstack\/overlay(alignment:content:)","title":"overlay(alignment:content:)","kind":"symbol","role":"symbol"},"doc://OpenSwiftUI/documentation/OpenSwiftUI/HStack/scaledToFill()":{"kind":"symbol","title":"scaledToFill()","url":"\/documentation\/openswiftui\/hstack\/scaledtofill()","identifier":"doc:\/\/OpenSwiftUI\/documentation\/OpenSwiftUI\/HStack\/scaledToFill()","role":"symbol","type":"topic","fragments":[{"kind":"keyword","text":"func"},{"kind":"text","text":" "},{"kind":"identifier","text":"scaledToFill"},{"kind":"text","text":"() -> "},{"kind":"keyword","text":"some"},{"kind":"text","text":" "},{"kind":"typeIdentifier","preciseIdentifier":"s:15OpenSwiftUICore4ViewP","text":"View"}],"abstract":[{"type":"text","text":"Scales this view to fill its parent."}]},"doc://OpenSwiftUI/documentation/OpenSwiftUI/HStack/zIndex(_:)":{"identifier":"doc:\/\/OpenSwiftUI\/documentation\/OpenSwiftUI\/HStack\/zIndex(_:)","title":"zIndex(_:)","role":"symbol","kind":"symbol","fragments":[{"kind":"keyword","text":"func"},{"kind":"text","text":" "},{"kind":"identifier","text":"zIndex"},{"kind":"text","text":"("},{"kind":"typeIdentifier","text":"Double","preciseIdentifier":"s:Sd"},{"kind":"text","text":") -> "},{"kind":"keyword","text":"some"},{"kind":"text","text":" "},{"kind":"typeIdentifier","text":"View","preciseIdentifier":"s:15OpenSwiftUICore4ViewP"}],"abstract":[{"type":"text","text":"Controls the display order of overlapping views."}],"url":"\/documentation\/openswiftui\/hstack\/zindex(_:)","type":"topic"},"doc://OpenSwiftUI/documentation/OpenSwiftUI/HStack/safeAreaInset(edge:alignment:spacing:content:)-rses":{"kind":"symbol","url":"\/documentation\/openswiftui\/hstack\/safeareainset(edge:alignment:spacing:content:)-rses","title":"safeAreaInset(edge:alignment:spacing:content:)","identifier":"doc:\/\/OpenSwiftUI\/documentation\/OpenSwiftUI\/HStack\/safeAreaInset(edge:alignment:spacing:content:)-rses","abstract":[{"type":"text","text":"Shows the specified content beside the modified view."}],"role":"symbol","fragments":[{"kind":"keyword","text":"func"},{"kind":"text","text":" "},{"kind":"identifier","text":"safeAreaInset"},{"kind":"text","text":"<"},{"kind":"genericParameter","text":"V"},{"kind":"text","text":">("},{"kind":"externalParam","text":"edge"},{"kind":"text","text":": "},{"kind":"typeIdentifier","text":"HorizontalEdge","preciseIdentifier":"s:15OpenSwiftUICore14HorizontalEdgeO"},{"kind":"text","text":", "},{"kind":"externalParam","text":"alignment"},{"kind":"text","text":": "},{"kind":"typeIdentifier","text":"VerticalAlignment","preciseIdentifier":"s:15OpenSwiftUICore17VerticalAlignmentV"},{"kind":"text","text":", "},{"kind":"externalParam","text":"spacing"},{"kind":"text","text":": "},{"kind":"typeIdentifier","text":"CGFloat","preciseIdentifier":"s:14CoreFoundation7CGFloatV"},{"kind":"text","text":"?, "},{"kind":"externalParam","text":"content"},{"kind":"text","text":": () -> "},{"kind":"typeIdentifier","text":"V"},{"kind":"text","text":") -> "},{"kind":"keyword","text":"some"},{"kind":"text","text":" "},{"kind":"typeIdentifier","text":"View","preciseIdentifier":"s:15OpenSwiftUICore4ViewP"}],"type":"topic"},"doc://OpenSwiftUI/documentation/OpenSwiftUI/HStack/onChange(of:initial:_:)-40uio":{"identifier":"doc:\/\/OpenSwiftUI\/documentation\/OpenSwiftUI\/HStack\/onChange(of:initial:_:)-40uio","abstract":[{"type":"text","text":"Adds a modifier for this view that fires an action when a specific"},{"type":"text","text":" "},{"type":"text","text":"value changes."}],"role":"symbol","type":"topic","title":"onChange(of:initial:_:)","kind":"symbol","fragments":[{"kind":"keyword","text":"func"},{"kind":"text","text":" "},{"kind":"identifier","text":"onChange"},{"kind":"text","text":"<"},{"kind":"genericParameter","text":"V"},{"kind":"text","text":">("},{"kind":"externalParam","text":"of"},{"kind":"text","text":": "},{"kind":"typeIdentifier","text":"V"},{"kind":"text","text":", "},{"kind":"externalParam","text":"initial"},{"kind":"text","text":": "},{"kind":"typeIdentifier","text":"Bool","preciseIdentifier":"s:Sb"},{"kind":"text","text":", () -> "},{"kind":"typeIdentifier","text":"Void","preciseIdentifier":"s:s4Voida"},{"kind":"text","text":") -> "},{"kind":"keyword","text":"some"},{"kind":"text","text":" "},{"kind":"typeIdentifier","text":"View","preciseIdentifier":"s:15OpenSwiftUICore4ViewP"}],"url":"\/documentation\/openswiftui\/hstack\/onchange(of:initial:_:)-40uio"},"doc://OpenSwiftUI/documentation/OpenSwiftUI/HStack/toggleStyle(_:)":{"fragments":[{"kind":"keyword","text":"func"},{"kind":"text","text":" "},{"kind":"identifier","text":"toggleStyle"},{"kind":"text","text":"<"},{"kind":"genericParameter","text":"S"},{"kind":"text","text":">("},{"kind":"typeIdentifier","text":"S","preciseIdentifier":"s:15OpenSwiftUICore4ViewP0aB2UIE11toggleStyleyQrqd__AD06ToggleG0Rd__lFQO1Sqd__mfp"},{"kind":"text","text":") -> "},{"kind":"keyword","text":"some"},{"kind":"text","text":" "},{"kind":"typeIdentifier","text":"View","preciseIdentifier":"s:15OpenSwiftUICore4ViewP"}],"role":"symbol","title":"toggleStyle(_:)","abstract":[{"text":"Sets the style for toggles in a view hierarchy.","type":"text"}],"kind":"symbol","type":"topic","identifier":"doc:\/\/OpenSwiftUI\/documentation\/OpenSwiftUI\/HStack\/toggleStyle(_:)","url":"\/documentation\/openswiftui\/hstack\/togglestyle(_:)"},"doc://OpenSwiftUI/documentation/OpenSwiftUI/HStack/aspectRatio(_:contentMode:)-744xo":{"kind":"symbol","role":"symbol","fragments":[{"kind":"keyword","text":"func"},{"kind":"text","text":" "},{"kind":"identifier","text":"aspectRatio"},{"kind":"text","text":"("},{"preciseIdentifier":"c:@S@CGSize","kind":"typeIdentifier","text":"CGSize"},{"kind":"text","text":", "},{"kind":"externalParam","text":"contentMode"},{"kind":"text","text":": "},{"preciseIdentifier":"s:15OpenSwiftUICore11ContentModeO","kind":"typeIdentifier","text":"ContentMode"},{"kind":"text","text":") -> "},{"kind":"keyword","text":"some"},{"kind":"text","text":" "},{"preciseIdentifier":"s:15OpenSwiftUICore4ViewP","kind":"typeIdentifier","text":"View"}],"abstract":[{"text":"Constrains this view’s dimensions to the aspect ratio of the given size.","type":"text"}],"identifier":"doc:\/\/OpenSwiftUI\/documentation\/OpenSwiftUI\/HStack\/aspectRatio(_:contentMode:)-744xo","url":"\/documentation\/openswiftui\/hstack\/aspectratio(_:contentmode:)-744xo","type":"topic","title":"aspectRatio(_:contentMode:)"},"doc://OpenSwiftUI/documentation/OpenSwiftUI/HStack/transformPreference(_:_:)":{"type":"topic","identifier":"doc:\/\/OpenSwiftUI\/documentation\/OpenSwiftUI\/HStack\/transformPreference(_:_:)","role":"symbol","fragments":[{"text":"func","kind":"keyword"},{"text":" ","kind":"text"},{"text":"transformPreference","kind":"identifier"},{"text":"<","kind":"text"},{"text":"K","kind":"genericParameter"},{"text":">(","kind":"text"},{"text":"K","kind":"typeIdentifier"},{"text":".Type, (","kind":"text"},{"text":"inout","kind":"keyword"},{"text":" ","kind":"text"},{"text":"K","kind":"typeIdentifier"},{"text":".","kind":"text"},{"preciseIdentifier":"s:15OpenSwiftUICore13PreferenceKeyP5ValueQa","text":"Value","kind":"typeIdentifier"},{"kind":"text","text":") -> "},{"kind":"typeIdentifier","text":"Void","preciseIdentifier":"s:s4Voida"},{"kind":"text","text":") -> "},{"kind":"keyword","text":"some"},{"kind":"text","text":" "},{"kind":"typeIdentifier","text":"View","preciseIdentifier":"s:15OpenSwiftUICore4ViewP"}],"kind":"symbol","abstract":[],"url":"\/documentation\/openswiftui\/hstack\/transformpreference(_:_:)","title":"transformPreference(_:_:)"},"doc://OpenSwiftUI/documentation/OpenSwiftUI/HStack/disabled(_:)-6q0je":{"role":"symbol","identifier":"doc:\/\/OpenSwiftUI\/documentation\/OpenSwiftUI\/HStack\/disabled(_:)-6q0je","kind":"symbol","abstract":[{"type":"text","text":"Adds a condition that controls whether users can interact with this"},{"type":"text","text":" "},{"type":"text","text":"view."}],"url":"\/documentation\/openswiftui\/hstack\/disabled(_:)-6q0je","title":"disabled(_:)","type":"topic","fragments":[{"kind":"keyword","text":"func"},{"kind":"text","text":" "},{"kind":"identifier","text":"disabled"},{"kind":"text","text":"("},{"preciseIdentifier":"s:Sb","kind":"typeIdentifier","text":"Bool"},{"kind":"text","text":") -> "},{"kind":"keyword","text":"some"},{"kind":"text","text":" "},{"preciseIdentifier":"s:15OpenSwiftUICore4ViewP","kind":"typeIdentifier","text":"View"}]},"doc://OpenSwiftUI/documentation/OpenSwiftUI/HStack/background(_:alignment:)":{"deprecated":true,"kind":"symbol","url":"\/documentation\/openswiftui\/hstack\/background(_:alignment:)","title":"background(_:alignment:)","identifier":"doc:\/\/OpenSwiftUI\/documentation\/OpenSwiftUI\/HStack\/background(_:alignment:)","abstract":[{"type":"text","text":"Layers the given view behind this view."}],"role":"symbol","fragments":[{"kind":"keyword","text":"func"},{"kind":"text","text":" "},{"kind":"identifier","text":"background"},{"kind":"text","text":"<"},{"kind":"genericParameter","text":"Background"},{"kind":"text","text":">("},{"kind":"typeIdentifier","text":"Background"},{"kind":"text","text":", "},{"kind":"externalParam","text":"alignment"},{"kind":"text","text":": "},{"kind":"typeIdentifier","text":"Alignment","preciseIdentifier":"s:15OpenSwiftUICore9AlignmentV"},{"kind":"text","text":") -> "},{"kind":"keyword","text":"some"},{"kind":"text","text":" "},{"kind":"typeIdentifier","text":"View","preciseIdentifier":"s:15OpenSwiftUICore4ViewP"}],"type":"topic"},"doc://OpenSwiftUI/documentation/OpenSwiftUI/HStack/fixedSize(horizontal:vertical:)":{"identifier":"doc:\/\/OpenSwiftUI\/documentation\/OpenSwiftUI\/HStack\/fixedSize(horizontal:vertical:)","fragments":[{"kind":"keyword","text":"func"},{"kind":"text","text":" "},{"kind":"identifier","text":"fixedSize"},{"kind":"text","text":"("},{"kind":"externalParam","text":"horizontal"},{"kind":"text","text":": "},{"kind":"typeIdentifier","text":"Bool","preciseIdentifier":"s:Sb"},{"kind":"text","text":", "},{"text":"vertical","kind":"externalParam"},{"text":": ","kind":"text"},{"text":"Bool","preciseIdentifier":"s:Sb","kind":"typeIdentifier"},{"text":") -> ","kind":"text"},{"text":"some","kind":"keyword"},{"text":" ","kind":"text"},{"text":"View","preciseIdentifier":"s:15OpenSwiftUICore4ViewP","kind":"typeIdentifier"}],"role":"symbol","abstract":[{"type":"text","text":"Fixes this view at its ideal size in the specified dimensions."}],"type":"topic","kind":"symbol","url":"\/documentation\/openswiftui\/hstack\/fixedsize(horizontal:vertical:)","title":"fixedSize(horizontal:vertical:)"},"doc://OpenSwiftUI/documentation/OpenSwiftUI/HStack/safeAreaPadding(_:)-4swtm":{"url":"\/documentation\/openswiftui\/hstack\/safeareapadding(_:)-4swtm","identifier":"doc:\/\/OpenSwiftUI\/documentation\/OpenSwiftUI\/HStack\/safeAreaPadding(_:)-4swtm","role":"symbol","kind":"symbol","abstract":[{"type":"text","text":"Adds the provided insets into the safe area of this view."}],"title":"safeAreaPadding(_:)","fragments":[{"text":"func","kind":"keyword"},{"text":" ","kind":"text"},{"text":"safeAreaPadding","kind":"identifier"},{"text":"(","kind":"text"},{"preciseIdentifier":"s:15OpenSwiftUICore10EdgeInsetsV","text":"EdgeInsets","kind":"typeIdentifier"},{"text":") -> ","kind":"text"},{"text":"some","kind":"keyword"},{"text":" ","kind":"text"},{"preciseIdentifier":"s:15OpenSwiftUICore4ViewP","text":"View","kind":"typeIdentifier"}],"type":"topic"},"doc://OpenSwiftUI/documentation/OpenSwiftUI/HStack/padding(_:_:)":{"role":"symbol","kind":"symbol","type":"topic","title":"padding(_:_:)","identifier":"doc:\/\/OpenSwiftUI\/documentation\/OpenSwiftUI\/HStack\/padding(_:_:)","url":"\/documentation\/openswiftui\/hstack\/padding(_:_:)","fragments":[{"text":"func","kind":"keyword"},{"text":" ","kind":"text"},{"text":"padding","kind":"identifier"},{"text":"(","kind":"text"},{"text":"Edge","preciseIdentifier":"s:15OpenSwiftUICore4EdgeO","kind":"typeIdentifier"},{"text":".","kind":"text"},{"text":"Set","preciseIdentifier":"s:15OpenSwiftUICore4EdgeO3SetV","kind":"typeIdentifier"},{"text":", ","kind":"text"},{"text":"CGFloat","preciseIdentifier":"s:14CoreFoundation7CGFloatV","kind":"typeIdentifier"},{"text":"?) -> ","kind":"text"},{"text":"some","kind":"keyword"},{"kind":"text","text":" "},{"kind":"typeIdentifier","preciseIdentifier":"s:15OpenSwiftUICore4ViewP","text":"View"}],"abstract":[{"type":"text","text":"Adds an equal padding amount to specific edges of this view."}]},"doc://OpenSwiftUI/documentation/OpenSwiftUI/HStack/transaction(value:_:)":{"kind":"symbol","abstract":[{"text":"Applies the given transaction mutation function to all animations used","type":"text"},{"text":" ","type":"text"},{"text":"within the view.","type":"text"}],"identifier":"doc:\/\/OpenSwiftUI\/documentation\/OpenSwiftUI\/HStack\/transaction(value:_:)","role":"symbol","type":"topic","fragments":[{"kind":"keyword","text":"func"},{"kind":"text","text":" "},{"kind":"identifier","text":"transaction"},{"kind":"text","text":"("},{"kind":"externalParam","text":"value"},{"kind":"text","text":": "},{"kind":"keyword","text":"some"},{"kind":"text","text":" "},{"kind":"typeIdentifier","preciseIdentifier":"s:SQ","text":"Equatable"},{"kind":"text","text":", ("},{"kind":"keyword","text":"inout"},{"kind":"text","text":" "},{"kind":"typeIdentifier","preciseIdentifier":"s:15OpenSwiftUICore11TransactionV","text":"Transaction"},{"kind":"text","text":") -> "},{"kind":"typeIdentifier","preciseIdentifier":"s:s4Voida","text":"Void"},{"kind":"text","text":") -> "},{"kind":"keyword","text":"some"},{"kind":"text","text":" "},{"kind":"typeIdentifier","preciseIdentifier":"s:15OpenSwiftUICore4ViewP","text":"View"}],"url":"\/documentation\/openswiftui\/hstack\/transaction(value:_:)","title":"transaction(value:_:)"},"doc://OpenSwiftUI/documentation/OpenSwiftUI/HStack/onChange(of:perform:)":{"url":"\/documentation\/openswiftui\/hstack\/onchange(of:perform:)","title":"onChange(of:perform:)","role":"symbol","identifier":"doc:\/\/OpenSwiftUI\/documentation\/OpenSwiftUI\/HStack\/onChange(of:perform:)","kind":"symbol","type":"topic","fragments":[{"kind":"keyword","text":"func"},{"kind":"text","text":" "},{"kind":"identifier","text":"onChange"},{"kind":"text","text":"<"},{"kind":"genericParameter","text":"V"},{"kind":"text","text":">("},{"kind":"externalParam","text":"of"},{"kind":"text","text":": "},{"kind":"typeIdentifier","text":"V"},{"kind":"text","text":", "},{"kind":"externalParam","text":"perform"},{"kind":"text","text":": ("},{"kind":"typeIdentifier","text":"V"},{"kind":"text","text":") -> "},{"kind":"typeIdentifier","preciseIdentifier":"s:s4Voida","text":"Void"},{"kind":"text","text":") -> "},{"kind":"keyword","text":"some"},{"kind":"text","text":" "},{"kind":"typeIdentifier","preciseIdentifier":"s:15OpenSwiftUICore4ViewP","text":"View"}],"abstract":[{"type":"text","text":"Performs an action when a specified value changes."}],"deprecated":true},"doc://OpenSwiftUI/documentation/OpenSwiftUI/HStack/edgesIgnoringSafeArea(_:)":{"type":"topic","abstract":[{"type":"text","text":"Changes the view’s proposed area to extend outside the screen’s safe"},{"type":"text","text":" "},{"type":"text","text":"areas."}],"url":"\/documentation\/openswiftui\/hstack\/edgesignoringsafearea(_:)","title":"edgesIgnoringSafeArea(_:)","identifier":"doc:\/\/OpenSwiftUI\/documentation\/OpenSwiftUI\/HStack\/edgesIgnoringSafeArea(_:)","fragments":[{"kind":"keyword","text":"func"},{"kind":"text","text":" "},{"kind":"identifier","text":"edgesIgnoringSafeArea"},{"kind":"text","text":"("},{"kind":"typeIdentifier","preciseIdentifier":"s:15OpenSwiftUICore4EdgeO","text":"Edge"},{"kind":"text","text":"."},{"kind":"typeIdentifier","preciseIdentifier":"s:15OpenSwiftUICore4EdgeO3SetV","text":"Set"},{"kind":"text","text":") -> "},{"kind":"keyword","text":"some"},{"kind":"text","text":" "},{"kind":"typeIdentifier","preciseIdentifier":"s:15OpenSwiftUICore4ViewP","text":"View"}],"deprecated":true,"role":"symbol","kind":"symbol"},"doc://OpenSwiftUI/documentation/OpenSwiftUI/HStack/safeAreaPadding(_:_:)":{"fragments":[{"kind":"keyword","text":"func"},{"kind":"text","text":" "},{"kind":"identifier","text":"safeAreaPadding"},{"kind":"text","text":"("},{"preciseIdentifier":"s:15OpenSwiftUICore4EdgeO","kind":"typeIdentifier","text":"Edge"},{"kind":"text","text":"."},{"preciseIdentifier":"s:15OpenSwiftUICore4EdgeO3SetV","kind":"typeIdentifier","text":"Set"},{"kind":"text","text":", "},{"preciseIdentifier":"s:14CoreFoundation7CGFloatV","kind":"typeIdentifier","text":"CGFloat"},{"kind":"text","text":"?) -> "},{"kind":"keyword","text":"some"},{"kind":"text","text":" "},{"preciseIdentifier":"s:15OpenSwiftUICore4ViewP","kind":"typeIdentifier","text":"View"}],"abstract":[{"type":"text","text":"Adds the provided insets into the safe area of this view."}],"kind":"symbol","role":"symbol","identifier":"doc:\/\/OpenSwiftUI\/documentation\/OpenSwiftUI\/HStack\/safeAreaPadding(_:_:)","type":"topic","title":"safeAreaPadding(_:_:)","url":"\/documentation\/openswiftui\/hstack\/safeareapadding(_:_:)"},"doc://OpenSwiftUI/documentation/OpenSwiftUI/HStack/transaction(_:body:)":{"fragments":[{"kind":"keyword","text":"func"},{"kind":"text","text":" "},{"kind":"identifier","text":"transaction"},{"kind":"text","text":"<"},{"kind":"genericParameter","text":"V"},{"kind":"text","text":">(("},{"kind":"keyword","text":"inout"},{"kind":"text","text":" "},{"kind":"typeIdentifier","preciseIdentifier":"s:15OpenSwiftUICore11TransactionV","text":"Transaction"},{"kind":"text","text":") -> "},{"kind":"typeIdentifier","preciseIdentifier":"s:s4Voida","text":"Void"},{"kind":"text","text":", "},{"kind":"externalParam","text":"body"},{"kind":"text","text":": ("},{"kind":"typeIdentifier","preciseIdentifier":"s:15OpenSwiftUICore22PlaceholderContentViewV","text":"PlaceholderContentView"},{"kind":"text","text":"<"},{"kind":"typeIdentifier","text":"Self"},{"kind":"text","text":">) -> "},{"kind":"typeIdentifier","text":"V"},{"kind":"text","text":") -> "},{"kind":"keyword","text":"some"},{"kind":"text","text":" "},{"kind":"typeIdentifier","preciseIdentifier":"s:15OpenSwiftUICore4ViewP","text":"View"}],"identifier":"doc:\/\/OpenSwiftUI\/documentation\/OpenSwiftUI\/HStack\/transaction(_:body:)","kind":"symbol","type":"topic","abstract":[{"text":"Applies the given transaction mutation function to all animations used","type":"text"},{"text":" ","type":"text"},{"text":"within the ","type":"text"},{"code":"body","type":"codeVoice"},{"type":"text","text":" closure."}],"role":"symbol","url":"\/documentation\/openswiftui\/hstack\/transaction(_:body:)","title":"transaction(_:body:)"},"doc://OpenSwiftUI/documentation/OpenSwiftUI/HStack/overlay(_:alignment:)":{"url":"\/documentation\/openswiftui\/hstack\/overlay(_:alignment:)","deprecated":true,"type":"topic","title":"overlay(_:alignment:)","identifier":"doc:\/\/OpenSwiftUI\/documentation\/OpenSwiftUI\/HStack\/overlay(_:alignment:)","abstract":[{"type":"text","text":"Layers a secondary view in front of this view."}],"role":"symbol","kind":"symbol","fragments":[{"kind":"keyword","text":"func"},{"kind":"text","text":" "},{"text":"overlay","kind":"identifier"},{"text":"<","kind":"text"},{"text":"Overlay","kind":"genericParameter"},{"text":">(","kind":"text"},{"text":"Overlay","kind":"typeIdentifier"},{"text":", ","kind":"text"},{"text":"alignment","kind":"externalParam"},{"text":": ","kind":"text"},{"text":"Alignment","kind":"typeIdentifier","preciseIdentifier":"s:15OpenSwiftUICore9AlignmentV"},{"text":") -> ","kind":"text"},{"text":"some","kind":"keyword"},{"text":" ","kind":"text"},{"preciseIdentifier":"s:15OpenSwiftUICore4ViewP","text":"View","kind":"typeIdentifier"}]},"doc://OpenSwiftUI/documentation/OpenSwiftUI/HStack/preference(key:value:)":{"type":"topic","kind":"symbol","title":"preference(key:value:)","identifier":"doc:\/\/OpenSwiftUI\/documentation\/OpenSwiftUI\/HStack\/preference(key:value:)","url":"\/documentation\/openswiftui\/hstack\/preference(key:value:)","abstract":[{"type":"text","text":"Sets a value for the given preference."}],"fragments":[{"kind":"keyword","text":"func"},{"kind":"text","text":" "},{"kind":"identifier","text":"preference"},{"kind":"text","text":"<"},{"kind":"genericParameter","text":"K"},{"kind":"text","text":">("},{"kind":"externalParam","text":"key"},{"kind":"text","text":": "},{"kind":"typeIdentifier","text":"K"},{"kind":"text","text":".Type, "},{"kind":"externalParam","text":"value"},{"kind":"text","text":": "},{"kind":"typeIdentifier","text":"K"},{"kind":"text","text":"."},{"kind":"typeIdentifier","text":"Value","preciseIdentifier":"s:15OpenSwiftUICore13PreferenceKeyP5ValueQa"},{"kind":"text","text":") -> "},{"kind":"keyword","text":"some"},{"kind":"text","text":" "},{"kind":"typeIdentifier","text":"View","preciseIdentifier":"s:15OpenSwiftUICore4ViewP"}],"role":"symbol"},"doc://OpenSwiftUI/documentation/OpenSwiftUI/HStack/offset(x:y:)":{"title":"offset(x:y:)","type":"topic","abstract":[{"text":"Offset this view by the specified horizontal and vertical distances.","type":"text"}],"role":"symbol","kind":"symbol","fragments":[{"kind":"keyword","text":"func"},{"kind":"text","text":" "},{"kind":"identifier","text":"offset"},{"kind":"text","text":"("},{"kind":"externalParam","text":"x"},{"kind":"text","text":": "},{"preciseIdentifier":"s:14CoreFoundation7CGFloatV","kind":"typeIdentifier","text":"CGFloat"},{"kind":"text","text":", "},{"kind":"externalParam","text":"y"},{"kind":"text","text":": "},{"preciseIdentifier":"s:14CoreFoundation7CGFloatV","kind":"typeIdentifier","text":"CGFloat"},{"kind":"text","text":") -> "},{"kind":"keyword","text":"some"},{"kind":"text","text":" "},{"preciseIdentifier":"s:15OpenSwiftUICore4ViewP","kind":"typeIdentifier","text":"View"}],"url":"\/documentation\/openswiftui\/hstack\/offset(x:y:)","identifier":"doc:\/\/OpenSwiftUI\/documentation\/OpenSwiftUI\/HStack\/offset(x:y:)"},"doc://OpenSwiftUI/documentation/OpenSwiftUI/HStack/font(_:)":{"abstract":[],"role":"symbol","title":"font(_:)","fragments":[{"text":"func","kind":"keyword"},{"text":" ","kind":"text"},{"text":"font","kind":"identifier"},{"text":"(","kind":"text"},{"preciseIdentifier":"s:15OpenSwiftUICore4FontV","text":"Font","kind":"typeIdentifier"},{"text":"?) -> ","kind":"text"},{"text":"some","kind":"keyword"},{"text":" ","kind":"text"},{"preciseIdentifier":"s:15OpenSwiftUICore4ViewP","text":"View","kind":"typeIdentifier"}],"kind":"symbol","type":"topic","identifier":"doc:\/\/OpenSwiftUI\/documentation\/OpenSwiftUI\/HStack\/font(_:)","url":"\/documentation\/openswiftui\/hstack\/font(_:)"},"doc://OpenSwiftUI/documentation/OpenSwiftUI/HStack/frame(width:height:alignment:)":{"url":"\/documentation\/openswiftui\/hstack\/frame(width:height:alignment:)","title":"frame(width:height:alignment:)","type":"topic","identifier":"doc:\/\/OpenSwiftUI\/documentation\/OpenSwiftUI\/HStack\/frame(width:height:alignment:)","kind":"symbol","abstract":[{"type":"text","text":"Positions this view within an invisible frame with the specified size."}],"fragments":[{"kind":"keyword","text":"func"},{"kind":"text","text":" "},{"kind":"identifier","text":"frame"},{"kind":"text","text":"("},{"kind":"externalParam","text":"width"},{"kind":"text","text":": "},{"preciseIdentifier":"s:14CoreFoundation7CGFloatV","kind":"typeIdentifier","text":"CGFloat"},{"kind":"text","text":"?, "},{"kind":"externalParam","text":"height"},{"kind":"text","text":": "},{"preciseIdentifier":"s:14CoreFoundation7CGFloatV","kind":"typeIdentifier","text":"CGFloat"},{"kind":"text","text":"?, "},{"kind":"externalParam","text":"alignment"},{"kind":"text","text":": "},{"preciseIdentifier":"s:15OpenSwiftUICore9AlignmentV","kind":"typeIdentifier","text":"Alignment"},{"kind":"text","text":") -> "},{"kind":"keyword","text":"some"},{"kind":"text","text":" "},{"preciseIdentifier":"s:15OpenSwiftUICore4ViewP","kind":"typeIdentifier","text":"View"}],"role":"symbol"},"doc://OpenSwiftUI/documentation/OpenSwiftUI/HStack/ignoresSafeArea(_:edges:)":{"role":"symbol","fragments":[{"kind":"keyword","text":"func"},{"kind":"text","text":" "},{"kind":"identifier","text":"ignoresSafeArea"},{"kind":"text","text":"("},{"kind":"typeIdentifier","text":"SafeAreaRegions","preciseIdentifier":"s:15OpenSwiftUICore15SafeAreaRegionsV"},{"kind":"text","text":", "},{"kind":"externalParam","text":"edges"},{"kind":"text","text":": "},{"kind":"typeIdentifier","text":"Edge","preciseIdentifier":"s:15OpenSwiftUICore4EdgeO"},{"kind":"text","text":"."},{"kind":"typeIdentifier","text":"Set","preciseIdentifier":"s:15OpenSwiftUICore4EdgeO3SetV"},{"kind":"text","text":") -> "},{"kind":"keyword","text":"some"},{"kind":"text","text":" "},{"kind":"typeIdentifier","text":"View","preciseIdentifier":"s:15OpenSwiftUICore4ViewP"}],"identifier":"doc:\/\/OpenSwiftUI\/documentation\/OpenSwiftUI\/HStack\/ignoresSafeArea(_:edges:)","abstract":[{"text":"Expands the safe area of a view.","type":"text"}],"url":"\/documentation\/openswiftui\/hstack\/ignoressafearea(_:edges:)","title":"ignoresSafeArea(_:edges:)","type":"topic","kind":"symbol"},"doc://OpenSwiftUI/documentation/OpenSwiftUI/HStack/aspectRatio(_:contentMode:)-1l4w2":{"abstract":[{"type":"text","text":"Constrains this view’s dimensions to the specified aspect ratio."}],"role":"symbol","identifier":"doc:\/\/OpenSwiftUI\/documentation\/OpenSwiftUI\/HStack\/aspectRatio(_:contentMode:)-1l4w2","type":"topic","kind":"symbol","title":"aspectRatio(_:contentMode:)","fragments":[{"text":"func","kind":"keyword"},{"text":" ","kind":"text"},{"text":"aspectRatio","kind":"identifier"},{"text":"(","kind":"text"},{"text":"CGFloat","kind":"typeIdentifier","preciseIdentifier":"s:14CoreFoundation7CGFloatV"},{"text":"?, ","kind":"text"},{"text":"contentMode","kind":"externalParam"},{"text":": ","kind":"text"},{"text":"ContentMode","kind":"typeIdentifier","preciseIdentifier":"s:15OpenSwiftUICore11ContentModeO"},{"text":") -> ","kind":"text"},{"text":"some","kind":"keyword"},{"text":" ","kind":"text"},{"text":"View","kind":"typeIdentifier","preciseIdentifier":"s:15OpenSwiftUICore4ViewP"}],"url":"\/documentation\/openswiftui\/hstack\/aspectratio(_:contentmode:)-1l4w2"},"doc://OpenSwiftUI/documentation/OpenSwiftUI/HStack/disabled(_:)-5vk9y":{"kind":"symbol","abstract":[{"text":"Adds a condition that controls whether users can interact with this","type":"text"},{"text":" ","type":"text"},{"text":"view.","type":"text"}],"title":"disabled(_:)","url":"\/documentation\/openswiftui\/hstack\/disabled(_:)-5vk9y","role":"symbol","fragments":[{"text":"func","kind":"keyword"},{"text":" ","kind":"text"},{"text":"disabled","kind":"identifier"},{"text":"(","kind":"text"},{"text":"Bool","kind":"typeIdentifier","preciseIdentifier":"s:Sb"},{"text":") -> ","kind":"text"},{"text":"some","kind":"keyword"},{"text":" ","kind":"text"},{"text":"View","kind":"typeIdentifier","preciseIdentifier":"s:15OpenSwiftUICore4ViewP"}],"type":"topic","identifier":"doc:\/\/OpenSwiftUI\/documentation\/OpenSwiftUI\/HStack\/disabled(_:)-5vk9y"},"doc://OpenSwiftUI/documentation/OpenSwiftUI/HStack/fixedSize()":{"url":"\/documentation\/openswiftui\/hstack\/fixedsize()","type":"topic","role":"symbol","abstract":[{"text":"Fixes this view at its ideal size.","type":"text"}],"kind":"symbol","fragments":[{"text":"func","kind":"keyword"},{"text":" ","kind":"text"},{"text":"fixedSize","kind":"identifier"},{"text":"() -> ","kind":"text"},{"text":"some","kind":"keyword"},{"text":" ","kind":"text"},{"text":"View","preciseIdentifier":"s:15OpenSwiftUICore4ViewP","kind":"typeIdentifier"}],"identifier":"doc:\/\/OpenSwiftUI\/documentation\/OpenSwiftUI\/HStack\/fixedSize()","title":"fixedSize()"},"doc://OpenSwiftUI/documentation/OpenSwiftUI/HStack/safeAreaInset(edge:alignment:spacing:content:)-21g":{"kind":"symbol","title":"safeAreaInset(edge:alignment:spacing:content:)","role":"symbol","identifier":"doc:\/\/OpenSwiftUI\/documentation\/OpenSwiftUI\/HStack\/safeAreaInset(edge:alignment:spacing:content:)-21g","abstract":[{"type":"text","text":"Shows the specified content above or below the modified view."}],"type":"topic","fragments":[{"kind":"keyword","text":"func"},{"kind":"text","text":" "},{"kind":"identifier","text":"safeAreaInset"},{"kind":"text","text":"<"},{"kind":"genericParameter","text":"V"},{"kind":"text","text":">("},{"kind":"externalParam","text":"edge"},{"kind":"text","text":": "},{"preciseIdentifier":"s:15OpenSwiftUICore12VerticalEdgeO","kind":"typeIdentifier","text":"VerticalEdge"},{"kind":"text","text":", "},{"kind":"externalParam","text":"alignment"},{"kind":"text","text":": "},{"preciseIdentifier":"s:15OpenSwiftUICore19HorizontalAlignmentV","kind":"typeIdentifier","text":"HorizontalAlignment"},{"kind":"text","text":", "},{"kind":"externalParam","text":"spacing"},{"kind":"text","text":": "},{"preciseIdentifier":"s:14CoreFoundation7CGFloatV","kind":"typeIdentifier","text":"CGFloat"},{"kind":"text","text":"?, "},{"kind":"externalParam","text":"content"},{"kind":"text","text":": () -> "},{"kind":"typeIdentifier","text":"V"},{"kind":"text","text":") -> "},{"kind":"keyword","text":"some"},{"kind":"text","text":" "},{"preciseIdentifier":"s:15OpenSwiftUICore4ViewP","kind":"typeIdentifier","text":"View"}],"url":"\/documentation\/openswiftui\/hstack\/safeareainset(edge:alignment:spacing:content:)-21g"},"doc://OpenSwiftUI/documentation/OpenSwiftUI/HStack/rotationEffect(_:anchor:)":{"fragments":[{"kind":"keyword","text":"func"},{"kind":"text","text":" "},{"kind":"identifier","text":"rotationEffect"},{"kind":"text","text":"("},{"preciseIdentifier":"s:15OpenSwiftUICore5AngleV","kind":"typeIdentifier","text":"Angle"},{"kind":"text","text":", "},{"kind":"externalParam","text":"anchor"},{"kind":"text","text":": "},{"preciseIdentifier":"s:15OpenSwiftUICore9UnitPointV","kind":"typeIdentifier","text":"UnitPoint"},{"kind":"text","text":") -> "},{"kind":"keyword","text":"some"},{"kind":"text","text":" "},{"preciseIdentifier":"s:15OpenSwiftUICore4ViewP","kind":"typeIdentifier","text":"View"}],"kind":"symbol","abstract":[{"type":"text","text":"Rotates a view’s rendered output in two dimensions around the specified"},{"type":"text","text":" "},{"type":"text","text":"point."}],"type":"topic","url":"\/documentation\/openswiftui\/hstack\/rotationeffect(_:anchor:)","identifier":"doc:\/\/OpenSwiftUI\/documentation\/OpenSwiftUI\/HStack\/rotationEffect(_:anchor:)","title":"rotationEffect(_:anchor:)","role":"symbol"},"doc://OpenSwiftUI/documentation/OpenSwiftUI/HStack/animation(_:value:)":{"identifier":"doc:\/\/OpenSwiftUI\/documentation\/OpenSwiftUI\/HStack\/animation(_:value:)","abstract":[],"role":"symbol","url":"\/documentation\/openswiftui\/hstack\/animation(_:value:)","kind":"symbol","type":"topic","title":"animation(_:value:)","fragments":[{"kind":"keyword","text":"func"},{"kind":"text","text":" "},{"kind":"identifier","text":"animation"},{"kind":"text","text":"<"},{"kind":"genericParameter","text":"V"},{"text":">(","kind":"text"},{"text":"Animation","preciseIdentifier":"s:15OpenSwiftUICore9AnimationV","kind":"typeIdentifier"},{"text":"?, ","kind":"text"},{"text":"value","kind":"externalParam"},{"text":": ","kind":"text"},{"text":"V","kind":"typeIdentifier"},{"text":") -> ","kind":"text"},{"text":"some","kind":"keyword"},{"text":" ","kind":"text"},{"text":"View","kind":"typeIdentifier","preciseIdentifier":"s:15OpenSwiftUICore4ViewP"}]},"doc://OpenSwiftUI/documentation/OpenSwiftUI/HStack/scaledToFit()":{"kind":"symbol","title":"scaledToFit()","role":"symbol","identifier":"doc:\/\/OpenSwiftUI\/documentation\/OpenSwiftUI\/HStack\/scaledToFit()","abstract":[{"type":"text","text":"Scales this view to fit its parent."}],"type":"topic","fragments":[{"kind":"keyword","text":"func"},{"kind":"text","text":" "},{"kind":"identifier","text":"scaledToFit"},{"kind":"text","text":"() -> "},{"kind":"keyword","text":"some"},{"kind":"text","text":" "},{"preciseIdentifier":"s:15OpenSwiftUICore4ViewP","kind":"typeIdentifier","text":"View"}],"url":"\/documentation\/openswiftui\/hstack\/scaledtofit()"},"doc://OpenSwiftUI/documentation/OpenSwiftUI/HStack/environment(_:)":{"kind":"symbol","fragments":[{"kind":"keyword","text":"func"},{"kind":"text","text":" "},{"kind":"identifier","text":"environment"},{"kind":"text","text":"<"},{"kind":"genericParameter","text":"T"},{"kind":"text","text":">("},{"kind":"typeIdentifier","text":"T"},{"kind":"text","text":"?) -> "},{"kind":"keyword","text":"some"},{"kind":"text","text":" "},{"preciseIdentifier":"s:15OpenSwiftUICore4ViewP","kind":"typeIdentifier","text":"View"}],"title":"environment(_:)","type":"topic","abstract":[{"type":"text","text":"Places an observable object in the view’s environment."}],"identifier":"doc:\/\/OpenSwiftUI\/documentation\/OpenSwiftUI\/HStack\/environment(_:)","role":"symbol","url":"\/documentation\/openswiftui\/hstack\/environment(_:)"},"doc://OpenSwiftUI/documentation/OpenSwiftUI/HStack/colorScheme(_:)":{"role":"symbol","fragments":[{"kind":"keyword","text":"func"},{"kind":"text","text":" "},{"kind":"identifier","text":"colorScheme"},{"kind":"text","text":"("},{"kind":"typeIdentifier","text":"ColorScheme","preciseIdentifier":"s:15OpenSwiftUICore11ColorSchemeO"},{"kind":"text","text":") -> "},{"kind":"keyword","text":"some"},{"kind":"text","text":" "},{"kind":"typeIdentifier","text":"View","preciseIdentifier":"s:15OpenSwiftUICore4ViewP"}],"type":"topic","url":"\/documentation\/openswiftui\/hstack\/colorscheme(_:)","kind":"symbol","identifier":"doc:\/\/OpenSwiftUI\/documentation\/OpenSwiftUI\/HStack\/colorScheme(_:)","title":"colorScheme(_:)","abstract":[{"type":"text","text":"Sets this view’s color scheme."}]},"doc://OpenSwiftUI/documentation/OpenSwiftUI/HStack/safeAreaPadding(_:)-3sho9":{"title":"safeAreaPadding(_:)","url":"\/documentation\/openswiftui\/hstack\/safeareapadding(_:)-3sho9","identifier":"doc:\/\/OpenSwiftUI\/documentation\/OpenSwiftUI\/HStack\/safeAreaPadding(_:)-3sho9","fragments":[{"kind":"keyword","text":"func"},{"kind":"text","text":" "},{"kind":"identifier","text":"safeAreaPadding"},{"kind":"text","text":"("},{"preciseIdentifier":"s:14CoreFoundation7CGFloatV","kind":"typeIdentifier","text":"CGFloat"},{"kind":"text","text":") -> "},{"kind":"keyword","text":"some"},{"kind":"text","text":" "},{"preciseIdentifier":"s:15OpenSwiftUICore4ViewP","kind":"typeIdentifier","text":"View"}],"abstract":[{"text":"Adds the provided insets into the safe area of this view.","type":"text"}],"type":"topic","kind":"symbol","role":"symbol"},"doc://OpenSwiftUI/documentation/OpenSwiftUI/HStack/frame(minWidth:idealWidth:maxWidth:minHeight:idealHeight:maxHeight:alignment:)":{"role":"symbol","kind":"symbol","fragments":[{"text":"func","kind":"keyword"},{"text":" ","kind":"text"},{"text":"frame","kind":"identifier"},{"text":"(","kind":"text"},{"text":"minWidth","kind":"externalParam"},{"text":": ","kind":"text"},{"text":"CGFloat","preciseIdentifier":"s:14CoreFoundation7CGFloatV","kind":"typeIdentifier"},{"text":"?, ","kind":"text"},{"text":"idealWidth","kind":"externalParam"},{"text":": ","kind":"text"},{"text":"CGFloat","preciseIdentifier":"s:14CoreFoundation7CGFloatV","kind":"typeIdentifier"},{"text":"?, ","kind":"text"},{"text":"maxWidth","kind":"externalParam"},{"text":": ","kind":"text"},{"text":"CGFloat","preciseIdentifier":"s:14CoreFoundation7CGFloatV","kind":"typeIdentifier"},{"text":"?, ","kind":"text"},{"text":"minHeight","kind":"externalParam"},{"text":": ","kind":"text"},{"text":"CGFloat","preciseIdentifier":"s:14CoreFoundation7CGFloatV","kind":"typeIdentifier"},{"text":"?, ","kind":"text"},{"text":"idealHeight","kind":"externalParam"},{"text":": ","kind":"text"},{"text":"CGFloat","preciseIdentifier":"s:14CoreFoundation7CGFloatV","kind":"typeIdentifier"},{"text":"?, ","kind":"text"},{"text":"maxHeight","kind":"externalParam"},{"text":": ","kind":"text"},{"text":"CGFloat","preciseIdentifier":"s:14CoreFoundation7CGFloatV","kind":"typeIdentifier"},{"text":"?, ","kind":"text"},{"text":"alignment","kind":"externalParam"},{"text":": ","kind":"text"},{"text":"Alignment","preciseIdentifier":"s:15OpenSwiftUICore9AlignmentV","kind":"typeIdentifier"},{"text":") -> ","kind":"text"},{"text":"some","kind":"keyword"},{"text":" ","kind":"text"},{"text":"View","preciseIdentifier":"s:15OpenSwiftUICore4ViewP","kind":"typeIdentifier"}],"title":"frame(minWidth:idealWidth:maxWidth:minHeight:idealHeight:maxHeight:alignment:)","abstract":[{"text":"Positions this view within an invisible frame having the specified size","type":"text"},{"text":" ","type":"text"},{"text":"constraints.","type":"text"}],"identifier":"doc:\/\/OpenSwiftUI\/documentation\/OpenSwiftUI\/HStack\/frame(minWidth:idealWidth:maxWidth:minHeight:idealHeight:maxHeight:alignment:)","url":"\/documentation\/openswiftui\/hstack\/frame(minwidth:idealwidth:maxwidth:minheight:idealheight:maxheight:alignment:)","type":"topic"},"doc://OpenSwiftUI/documentation/OpenSwiftUI":{"kind":"symbol","identifier":"doc:\/\/OpenSwiftUI\/documentation\/OpenSwiftUI","abstract":[{"type":"text","text":"Declare the user interface and behavior for your app on every platform."}],"url":"\/documentation\/openswiftui","type":"topic","title":"OpenSwiftUI","role":"collection"},"doc://OpenSwiftUI/documentation/OpenSwiftUI/HStack/foregroundStyle(_:_:)":{"title":"foregroundStyle(_:_:)","role":"symbol","fragments":[{"text":"func","kind":"keyword"},{"text":" ","kind":"text"},{"text":"foregroundStyle","kind":"identifier"},{"text":"<","kind":"text"},{"text":"S1","kind":"genericParameter"},{"text":", ","kind":"text"},{"text":"S2","kind":"genericParameter"},{"text":">(","kind":"text"},{"text":"S1","kind":"typeIdentifier"},{"text":", ","kind":"text"},{"text":"S2","kind":"typeIdentifier"},{"text":") -> ","kind":"text"},{"text":"some","kind":"keyword"},{"text":" ","kind":"text"},{"text":"View","kind":"typeIdentifier","preciseIdentifier":"s:15OpenSwiftUICore4ViewP"}],"url":"\/documentation\/openswiftui\/hstack\/foregroundstyle(_:_:)","abstract":[{"text":"Sets the primary and secondary levels of the foreground","type":"text"},{"text":" ","type":"text"},{"text":"style in the child view.","type":"text"}],"type":"topic","identifier":"doc:\/\/OpenSwiftUI\/documentation\/OpenSwiftUI\/HStack\/foregroundStyle(_:_:)","kind":"symbol"},"doc://OpenSwiftUI/documentation/OpenSwiftUI/HStack/layoutPriority(_:)":{"identifier":"doc:\/\/OpenSwiftUI\/documentation\/OpenSwiftUI\/HStack\/layoutPriority(_:)","url":"\/documentation\/openswiftui\/hstack\/layoutpriority(_:)","kind":"symbol","type":"topic","title":"layoutPriority(_:)","abstract":[{"text":"Sets the priority by which a parent layout should apportion space to","type":"text"},{"text":" ","type":"text"},{"text":"this child.","type":"text"}],"role":"symbol","fragments":[{"kind":"keyword","text":"func"},{"kind":"text","text":" "},{"kind":"identifier","text":"layoutPriority"},{"kind":"text","text":"("},{"kind":"typeIdentifier","text":"Double","preciseIdentifier":"s:Sd"},{"kind":"text","text":") -> "},{"kind":"keyword","text":"some"},{"kind":"text","text":" "},{"kind":"typeIdentifier","text":"View","preciseIdentifier":"s:15OpenSwiftUICore4ViewP"}]},"doc://OpenSwiftUI/documentation/OpenSwiftUI/HStack/modifier(_:)":{"type":"topic","fragments":[{"text":"func","kind":"keyword"},{"text":" ","kind":"text"},{"text":"modifier","kind":"identifier"},{"text":"<","kind":"text"},{"text":"T","kind":"genericParameter"},{"text":">(","kind":"text"},{"text":"T","kind":"typeIdentifier"},{"text":") -> ","kind":"text"},{"text":"ModifiedContent","preciseIdentifier":"s:15OpenSwiftUICore15ModifiedContentV","kind":"typeIdentifier"},{"text":"<","kind":"text"},{"text":"Self","kind":"typeIdentifier"},{"text":", ","kind":"text"},{"text":"T","kind":"typeIdentifier"},{"text":">","kind":"text"}],"kind":"symbol","role":"symbol","title":"modifier(_:)","abstract":[{"text":"Applies a modifier to a view and returns a new view.","type":"text"}],"url":"\/documentation\/openswiftui\/hstack\/modifier(_:)","identifier":"doc:\/\/OpenSwiftUI\/documentation\/OpenSwiftUI\/HStack\/modifier(_:)"},"doc://OpenSwiftUI/documentation/OpenSwiftUI/HStack/environmentObject(_:)":{"abstract":[{"text":"Supplies an observable object to a view’s hierarchy.","type":"text"}],"type":"topic","kind":"symbol","identifier":"doc:\/\/OpenSwiftUI\/documentation\/OpenSwiftUI\/HStack\/environmentObject(_:)","url":"\/documentation\/openswiftui\/hstack\/environmentobject(_:)","title":"environmentObject(_:)","role":"symbol","fragments":[{"kind":"keyword","text":"func"},{"kind":"text","text":" "},{"kind":"identifier","text":"environmentObject"},{"kind":"text","text":"<"},{"kind":"genericParameter","text":"T"},{"kind":"text","text":">("},{"kind":"typeIdentifier","text":"T"},{"kind":"text","text":") -> "},{"kind":"keyword","text":"some"},{"kind":"text","text":" "},{"kind":"typeIdentifier","text":"View","preciseIdentifier":"s:15OpenSwiftUICore4ViewP"}]},"doc://OpenSwiftUI/documentation/OpenSwiftUI/HStack/offset(_:)":{"abstract":[{"type":"text","text":"Offset this view by the horizontal and vertical amount specified in the"},{"type":"text","text":" "},{"type":"text","text":"offset parameter."}],"fragments":[{"text":"func","kind":"keyword"},{"text":" ","kind":"text"},{"text":"offset","kind":"identifier"},{"text":"(","kind":"text"},{"text":"CGSize","kind":"typeIdentifier","preciseIdentifier":"c:@S@CGSize"},{"text":") -> ","kind":"text"},{"text":"some","kind":"keyword"},{"text":" ","kind":"text"},{"text":"View","kind":"typeIdentifier","preciseIdentifier":"s:15OpenSwiftUICore4ViewP"}],"title":"offset(_:)","kind":"symbol","type":"topic","identifier":"doc:\/\/OpenSwiftUI\/documentation\/OpenSwiftUI\/HStack\/offset(_:)","url":"\/documentation\/openswiftui\/hstack\/offset(_:)","role":"symbol"},"doc://OpenSwiftUI/documentation/OpenSwiftUI/HStack/dynamicTypeSize(_:)":{"abstract":[{"type":"text","text":"Sets the Dynamic Type size within the view to the given value."}],"identifier":"doc:\/\/OpenSwiftUI\/documentation\/OpenSwiftUI\/HStack\/dynamicTypeSize(_:)","title":"dynamicTypeSize(_:)","kind":"symbol","url":"\/documentation\/openswiftui\/hstack\/dynamictypesize(_:)","role":"symbol","type":"topic","fragments":[{"text":"func","kind":"keyword"},{"text":" ","kind":"text"},{"text":"dynamicTypeSize","kind":"identifier"},{"text":"(","kind":"text"},{"text":"DynamicTypeSize","kind":"typeIdentifier","preciseIdentifier":"s:15OpenSwiftUICore15DynamicTypeSizeO"},{"text":") -> ","kind":"text"},{"text":"some","kind":"keyword"},{"text":" ","kind":"text"},{"text":"View","kind":"typeIdentifier","preciseIdentifier":"s:15OpenSwiftUICore4ViewP"}]},"doc://OpenSwiftUI/documentation/OpenSwiftUI/HStack/onDisappear(perform:)":{"fragments":[{"text":"func","kind":"keyword"},{"text":" ","kind":"text"},{"text":"onDisappear","kind":"identifier"},{"text":"(","kind":"text"},{"text":"perform","kind":"externalParam"},{"text":": (() -> ","kind":"text"},{"preciseIdentifier":"s:s4Voida","text":"Void","kind":"typeIdentifier"},{"text":")?) -> ","kind":"text"},{"text":"some","kind":"keyword"},{"text":" ","kind":"text"},{"preciseIdentifier":"s:15OpenSwiftUICore4ViewP","text":"View","kind":"typeIdentifier"}],"url":"\/documentation\/openswiftui\/hstack\/ondisappear(perform:)","abstract":[{"type":"text","text":"Adds an action to perform after this view disappears."}],"title":"onDisappear(perform:)","type":"topic","kind":"symbol","role":"symbol","identifier":"doc:\/\/OpenSwiftUI\/documentation\/OpenSwiftUI\/HStack\/onDisappear(perform:)"},"doc://OpenSwiftUI/documentation/OpenSwiftUI/HStack/rotation3DEffect(_:axis:anchor:anchorZ:perspective:)":{"abstract":[{"text":"Renders a view’s content as if it’s rotated in three dimensions around","type":"text"},{"text":" ","type":"text"},{"text":"the specified axis.","type":"text"}],"kind":"symbol","identifier":"doc:\/\/OpenSwiftUI\/documentation\/OpenSwiftUI\/HStack\/rotation3DEffect(_:axis:anchor:anchorZ:perspective:)","type":"topic","role":"symbol","fragments":[{"text":"func","kind":"keyword"},{"text":" ","kind":"text"},{"text":"rotation3DEffect","kind":"identifier"},{"text":"(","kind":"text"},{"text":"Angle","kind":"typeIdentifier","preciseIdentifier":"s:15OpenSwiftUICore5AngleV"},{"text":", ","kind":"text"},{"text":"axis","kind":"externalParam"},{"text":": (x","kind":"text"},{"text":": ","kind":"text"},{"text":"CGFloat","kind":"typeIdentifier","preciseIdentifier":"s:14CoreFoundation7CGFloatV"},{"text":", y","kind":"text"},{"text":": ","kind":"text"},{"text":"CGFloat","kind":"typeIdentifier","preciseIdentifier":"s:14CoreFoundation7CGFloatV"},{"text":", z","kind":"text"},{"text":": ","kind":"text"},{"text":"CGFloat","kind":"typeIdentifier","preciseIdentifier":"s:14CoreFoundation7CGFloatV"},{"text":"), ","kind":"text"},{"text":"anchor","kind":"externalParam"},{"text":": ","kind":"text"},{"text":"UnitPoint","kind":"typeIdentifier","preciseIdentifier":"s:15OpenSwiftUICore9UnitPointV"},{"text":", ","kind":"text"},{"text":"anchorZ","kind":"externalParam"},{"text":": ","kind":"text"},{"text":"CGFloat","kind":"typeIdentifier","preciseIdentifier":"s:14CoreFoundation7CGFloatV"},{"text":", ","kind":"text"},{"text":"perspective","kind":"externalParam"},{"text":": ","kind":"text"},{"text":"CGFloat","kind":"typeIdentifier","preciseIdentifier":"s:14CoreFoundation7CGFloatV"},{"text":") -> ","kind":"text"},{"text":"some","kind":"keyword"},{"text":" ","kind":"text"},{"text":"View","kind":"typeIdentifier","preciseIdentifier":"s:15OpenSwiftUICore4ViewP"}],"url":"\/documentation\/openswiftui\/hstack\/rotation3deffect(_:axis:anchor:anchorz:perspective:)","title":"rotation3DEffect(_:axis:anchor:anchorZ:perspective:)"},"doc://OpenSwiftUI/documentation/OpenSwiftUI/HStack/transformEnvironment(_:transform:)":{"abstract":[{"type":"text","text":"Transforms the environment value of the specified key path with the"},{"type":"text","text":" "},{"type":"text","text":"given function."}],"identifier":"doc:\/\/OpenSwiftUI\/documentation\/OpenSwiftUI\/HStack\/transformEnvironment(_:transform:)","fragments":[{"text":"func","kind":"keyword"},{"text":" ","kind":"text"},{"text":"transformEnvironment","kind":"identifier"},{"text":"<","kind":"text"},{"text":"V","kind":"genericParameter"},{"text":">(","kind":"text"},{"preciseIdentifier":"s:s15WritableKeyPathC","text":"WritableKeyPath","kind":"typeIdentifier"},{"text":"<","kind":"text"},{"preciseIdentifier":"s:15OpenSwiftUICore17EnvironmentValuesV","text":"EnvironmentValues","kind":"typeIdentifier"},{"text":", ","kind":"text"},{"text":"V","kind":"typeIdentifier"},{"text":">, ","kind":"text"},{"text":"transform","kind":"externalParam"},{"text":": (","kind":"text"},{"text":"inout","kind":"keyword"},{"text":" ","kind":"text"},{"text":"V","kind":"typeIdentifier"},{"text":") -> ","kind":"text"},{"preciseIdentifier":"s:s4Voida","text":"Void","kind":"typeIdentifier"},{"text":") -> ","kind":"text"},{"text":"some","kind":"keyword"},{"text":" ","kind":"text"},{"preciseIdentifier":"s:15OpenSwiftUICore4ViewP","text":"View","kind":"typeIdentifier"}],"url":"\/documentation\/openswiftui\/hstack\/transformenvironment(_:transform:)","role":"symbol","kind":"symbol","title":"transformEnvironment(_:transform:)","type":"topic"},"doc://OpenSwiftUI/documentation/OpenSwiftUI/HStack/animation(_:body:)":{"type":"topic","abstract":[{"text":"Applies the given animation to all animatable values within the ","type":"text"},{"code":"body","type":"codeVoice"},{"text":" ","type":"text"},{"text":"closure.","type":"text"}],"identifier":"doc:\/\/OpenSwiftUI\/documentation\/OpenSwiftUI\/HStack\/animation(_:body:)","kind":"symbol","title":"animation(_:body:)","role":"symbol","url":"\/documentation\/openswiftui\/hstack\/animation(_:body:)","fragments":[{"kind":"keyword","text":"func"},{"kind":"text","text":" "},{"kind":"identifier","text":"animation"},{"kind":"text","text":"<"},{"kind":"genericParameter","text":"V"},{"kind":"text","text":">("},{"preciseIdentifier":"s:15OpenSwiftUICore9AnimationV","kind":"typeIdentifier","text":"Animation"},{"kind":"text","text":"?, "},{"kind":"externalParam","text":"body"},{"kind":"text","text":": ("},{"preciseIdentifier":"s:15OpenSwiftUICore22PlaceholderContentViewV","kind":"typeIdentifier","text":"PlaceholderContentView"},{"kind":"text","text":"<"},{"kind":"typeIdentifier","text":"Self"},{"kind":"text","text":">) -> "},{"kind":"typeIdentifier","text":"V"},{"kind":"text","text":") -> "},{"kind":"keyword","text":"some"},{"kind":"text","text":" "},{"preciseIdentifier":"s:15OpenSwiftUICore4ViewP","kind":"typeIdentifier","text":"View"}]},"doc://OpenSwiftUI/documentation/OpenSwiftUI/HStack/background(alignment:content:)":{"fragments":[{"text":"func","kind":"keyword"},{"text":" ","kind":"text"},{"text":"background","kind":"identifier"},{"text":"<","kind":"text"},{"text":"V","kind":"genericParameter"},{"text":">(","kind":"text"},{"text":"alignment","kind":"externalParam"},{"text":": ","kind":"text"},{"text":"Alignment","kind":"typeIdentifier","preciseIdentifier":"s:15OpenSwiftUICore9AlignmentV"},{"text":", ","kind":"text"},{"text":"content","kind":"externalParam"},{"text":": () -> ","kind":"text"},{"text":"V","kind":"typeIdentifier"},{"text":") -> ","kind":"text"},{"text":"some","kind":"keyword"},{"text":" ","kind":"text"},{"text":"View","kind":"typeIdentifier","preciseIdentifier":"s:15OpenSwiftUICore4ViewP"}],"kind":"symbol","type":"topic","abstract":[{"text":"Layers the views that you specify behind this view.","type":"text"}],"url":"\/documentation\/openswiftui\/hstack\/background(alignment:content:)","identifier":"doc:\/\/OpenSwiftUI\/documentation\/OpenSwiftUI\/HStack\/background(alignment:content:)","title":"background(alignment:content:)","role":"symbol"},"doc://OpenSwiftUI/documentation/OpenSwiftUI/HStack/cornerRadius(_:antialiased:)":{"identifier":"doc:\/\/OpenSwiftUI\/documentation\/OpenSwiftUI\/HStack\/cornerRadius(_:antialiased:)","title":"cornerRadius(_:antialiased:)","url":"\/documentation\/openswiftui\/hstack\/cornerradius(_:antialiased:)","kind":"symbol","type":"topic","abstract":[{"type":"text","text":"Clips this view to its bounding frame, with the specified corner radius."}],"role":"symbol","fragments":[{"kind":"keyword","text":"func"},{"kind":"text","text":" "},{"kind":"identifier","text":"cornerRadius"},{"kind":"text","text":"("},{"preciseIdentifier":"s:14CoreFoundation7CGFloatV","kind":"typeIdentifier","text":"CGFloat"},{"kind":"text","text":", "},{"kind":"externalParam","text":"antialiased"},{"kind":"text","text":": "},{"preciseIdentifier":"s:Sb","kind":"typeIdentifier","text":"Bool"},{"kind":"text","text":") -> "},{"kind":"keyword","text":"some"},{"kind":"text","text":" "},{"preciseIdentifier":"s:15OpenSwiftUICore4ViewP","kind":"typeIdentifier","text":"View"}],"deprecated":true},"doc://OpenSwiftUI/documentation/OpenSwiftUI/HStack/tint(_:)":{"abstract":[{"type":"text","text":"Sets the tint color within this view."}],"role":"symbol","title":"tint(_:)","kind":"symbol","type":"topic","url":"\/documentation\/openswiftui\/hstack\/tint(_:)","identifier":"doc:\/\/OpenSwiftUI\/documentation\/OpenSwiftUI\/HStack\/tint(_:)","fragments":[{"text":"func","kind":"keyword"},{"text":" ","kind":"text"},{"text":"tint","kind":"identifier"},{"text":"(","kind":"text"},{"text":"Color","kind":"typeIdentifier","preciseIdentifier":"s:15OpenSwiftUICore5ColorV"},{"text":"?) -> ","kind":"text"},{"text":"some","kind":"keyword"},{"text":" ","kind":"text"},{"text":"View","kind":"typeIdentifier","preciseIdentifier":"s:15OpenSwiftUICore4ViewP"}]},"doc://OpenSwiftUI/documentation/OpenSwiftUI/HStack/padding(_:)-1v6zm":{"role":"symbol","title":"padding(_:)","kind":"symbol","abstract":[{"type":"text","text":"Adds a different padding amount to each edge of this view."}],"type":"topic","fragments":[{"text":"func","kind":"keyword"},{"text":" ","kind":"text"},{"text":"padding","kind":"identifier"},{"text":"(","kind":"text"},{"preciseIdentifier":"s:15OpenSwiftUICore10EdgeInsetsV","text":"EdgeInsets","kind":"typeIdentifier"},{"text":") -> ","kind":"text"},{"text":"some","kind":"keyword"},{"text":" ","kind":"text"},{"preciseIdentifier":"s:15OpenSwiftUICore4ViewP","text":"View","kind":"typeIdentifier"}],"url":"\/documentation\/openswiftui\/hstack\/padding(_:)-1v6zm","identifier":"doc:\/\/OpenSwiftUI\/documentation\/OpenSwiftUI\/HStack\/padding(_:)-1v6zm"},"doc://OpenSwiftUI/documentation/OpenSwiftUI/HStack/foregroundStyle(_:_:_:)":{"abstract":[{"text":"Sets the primary, secondary, and tertiary levels of","type":"text"},{"text":" ","type":"text"},{"text":"the foreground style.","type":"text"}],"url":"\/documentation\/openswiftui\/hstack\/foregroundstyle(_:_:_:)","role":"symbol","fragments":[{"text":"func","kind":"keyword"},{"text":" ","kind":"text"},{"text":"foregroundStyle","kind":"identifier"},{"text":"<","kind":"text"},{"text":"S1","kind":"genericParameter"},{"text":", ","kind":"text"},{"text":"S2","kind":"genericParameter"},{"text":", ","kind":"text"},{"text":"S3","kind":"genericParameter"},{"text":">(","kind":"text"},{"text":"S1","kind":"typeIdentifier"},{"text":", ","kind":"text"},{"text":"S2","kind":"typeIdentifier"},{"text":", ","kind":"text"},{"text":"S3","kind":"typeIdentifier"},{"text":") -> ","kind":"text"},{"text":"some","kind":"keyword"},{"text":" ","kind":"text"},{"text":"View","kind":"typeIdentifier","preciseIdentifier":"s:15OpenSwiftUICore4ViewP"}],"type":"topic","title":"foregroundStyle(_:_:_:)","identifier":"doc:\/\/OpenSwiftUI\/documentation\/OpenSwiftUI\/HStack\/foregroundStyle(_:_:_:)","kind":"symbol"},"doc://OpenSwiftUI/documentation/OpenSwiftUI/HStack/id(_:)":{"kind":"symbol","identifier":"doc:\/\/OpenSwiftUI\/documentation\/OpenSwiftUI\/HStack\/id(_:)","title":"id(_:)","type":"topic","fragments":[{"text":"func","kind":"keyword"},{"text":" ","kind":"text"},{"text":"id","kind":"identifier"},{"text":"<","kind":"text"},{"text":"ID","kind":"genericParameter"},{"text":">(","kind":"text"},{"text":"ID","kind":"typeIdentifier"},{"text":") -> ","kind":"text"},{"text":"some","kind":"keyword"},{"text":" ","kind":"text"},{"text":"View","kind":"typeIdentifier","preciseIdentifier":"s:15OpenSwiftUICore4ViewP"}],"url":"\/documentation\/openswiftui\/hstack\/id(_:)","abstract":[{"type":"text","text":"Binds a view’s identity to the given proxy value."}],"role":"symbol"}}}