{"hierarchy":{"paths":[["doc:\/\/OpenSwiftUI\/documentation\/OpenSwiftUI","doc:\/\/OpenSwiftUI\/documentation\/OpenSwiftUI\/TimelineView"]]},"identifier":{"url":"doc:\/\/OpenSwiftUI\/documentation\/OpenSwiftUI\/TimelineView\/transaction(value:_:)","interfaceLanguage":"swift"},"primaryContentSections":[{"declarations":[{"tokens":[{"text":"nonisolated","kind":"attribute"},{"text":" ","kind":"text"},{"text":"func","kind":"keyword"},{"text":" ","kind":"text"},{"text":"transaction","kind":"identifier"},{"text":"(","kind":"text"},{"text":"value","kind":"externalParam"},{"text":": ","kind":"text"},{"text":"some","kind":"keyword"},{"text":" ","kind":"text"},{"preciseIdentifier":"s:SQ","text":"Equatable","kind":"typeIdentifier"},{"text":", ","kind":"text"},{"text":"_","kind":"externalParam"},{"text":" ","kind":"text"},{"text":"transform","kind":"internalParam"},{"text":": ","kind":"text"},{"text":"@escaping","kind":"keyword"},{"text":" (","kind":"text"},{"text":"inout","kind":"keyword"},{"text":" ","kind":"text"},{"identifier":"doc:\/\/OpenSwiftUI\/documentation\/OpenSwiftUI\/Transaction","preciseIdentifier":"s:15OpenSwiftUICore11TransactionV","text":"Transaction","kind":"typeIdentifier"},{"text":") -> ","kind":"text"},{"preciseIdentifier":"s:s4Voida","text":"Void","kind":"typeIdentifier"},{"text":") -> ","kind":"text"},{"text":"some","kind":"keyword"},{"text":" ","kind":"text"},{"identifier":"doc:\/\/OpenSwiftUI\/documentation\/OpenSwiftUI\/View","preciseIdentifier":"s:15OpenSwiftUICore4ViewP","text":"View","kind":"typeIdentifier"},{"text":"\n","kind":"text"}],"languages":["swift"],"platforms":["macOS"]}],"kind":"declarations"},{"parameters":[{"name":"value","content":[{"type":"paragraph","inlineContent":[{"text":"A value to monitor for changes.","type":"text"}]}]},{"name":"transform","content":[{"type":"paragraph","inlineContent":[{"type":"text","text":"The transformation to apply to transactions"},{"type":"text","text":" "},{"type":"text","text":"within this view."}]}]}],"kind":"parameters"},{"kind":"content","content":[{"type":"heading","anchor":"return-value","level":2,"text":"Return Value"},{"type":"paragraph","inlineContent":[{"text":"A view that wraps this view and applies a transformation to","type":"text"},{"text":" ","type":"text"},{"text":"all transactions used within the view whenever ","type":"text"},{"code":"value","type":"codeVoice"},{"text":" changes.","type":"text"}]}]},{"kind":"content","content":[{"type":"heading","text":"Discussion","level":2,"anchor":"discussion"},{"type":"paragraph","inlineContent":[{"type":"text","text":"Use this modifier to change or replace the animation used in a view."},{"type":"text","text":" "},{"type":"text","text":"Consider three identical views controlled by a"},{"type":"text","text":" "},{"type":"text","text":"button that changes all three simultaneously:"}]},{"type":"unorderedList","items":[{"content":[{"inlineContent":[{"text":"The first view animates rotating the “Rotation” ","type":"text"},{"type":"reference","identifier":"doc:\/\/OpenSwiftUI\/documentation\/OpenSwiftUI\/Text","isActive":true},{"text":" view by 360","type":"text"},{"text":" ","type":"text"},{"text":"degrees.","type":"text"}],"type":"paragraph"}]},{"content":[{"inlineContent":[{"type":"text","text":"The second uses the "},{"type":"codeVoice","code":"transaction(_:)"},{"type":"text","text":" modifier to change the"},{"type":"text","text":" "},{"type":"text","text":"animation by adding a delay to the start of the animation"},{"type":"text","text":" "},{"type":"text","text":"by two seconds and then increases the rotational speed of the"},{"type":"text","text":" "},{"type":"text","text":"“Rotation\\nModified” "},{"type":"reference","identifier":"doc:\/\/OpenSwiftUI\/documentation\/OpenSwiftUI\/Text","isActive":true},{"type":"text","text":" view animation by a factor of 2."}],"type":"paragraph"}]},{"content":[{"inlineContent":[{"type":"text","text":"The third uses the "},{"type":"codeVoice","code":"transaction(_:)"},{"type":"text","text":" modifier to disable animations"},{"type":"text","text":" "},{"type":"text","text":"affecting the “Animation\\nReplaced” "},{"type":"reference","isActive":true,"identifier":"doc:\/\/OpenSwiftUI\/documentation\/OpenSwiftUI\/Text"},{"type":"text","text":" view."}],"type":"paragraph"}]}]},{"type":"paragraph","inlineContent":[{"text":"The following code implements these animations:","type":"text"}]},{"syntax":"swift","type":"codeListing","code":["struct TransactionExample: View {","    @State var flag = false","","    var body: some View {","        VStack(spacing: 50) {","            HStack(spacing: 30) {","                Text(\"Rotation\")","                    .rotationEffect(Angle(degrees: flag ? 360 : 0))","","                Text(\"Rotation\\nModified\")","                    .rotationEffect(Angle(degrees: flag ? 360 : 0))","                    .transaction(value: flag) { t in","                        t.animation =","                            t.animation?.delay(2.0).speed(2)","                    }","","                Text(\"Animation\\nReplaced\")","                    .rotationEffect(Angle(degrees: flag ? 360 : 0))","                    .transaction(value: flag) { t in","                        t.disableAnimations = true","                    }","            }","","            Button(\"Animate\") {","                withAnimation(.easeIn(duration: 2.0)) {","                    flag.toggle()","                }","            }","        }","    }","}"]}]}],"abstract":[{"text":"Applies the given transaction mutation function to all animations used","type":"text"},{"text":" ","type":"text"},{"text":"within the view.","type":"text"}],"variants":[{"paths":["\/documentation\/openswiftui\/timelineview\/transaction(value:_:)"],"traits":[{"interfaceLanguage":"swift"}]}],"metadata":{"extendedModule":"OpenSwiftUICore","roleHeading":"Instance Method","modules":[{"name":"OpenSwiftUI","relatedModules":["OpenSwiftUICore"]}],"title":"transaction(value:_:)","symbolKind":"method","fragments":[{"text":"func","kind":"keyword"},{"text":" ","kind":"text"},{"text":"transaction","kind":"identifier"},{"text":"(","kind":"text"},{"text":"value","kind":"externalParam"},{"text":": ","kind":"text"},{"text":"some","kind":"keyword"},{"text":" ","kind":"text"},{"text":"Equatable","kind":"typeIdentifier","preciseIdentifier":"s:SQ"},{"text":", (","kind":"text"},{"text":"inout","kind":"keyword"},{"text":" ","kind":"text"},{"text":"Transaction","kind":"typeIdentifier","preciseIdentifier":"s:15OpenSwiftUICore11TransactionV"},{"text":") -> ","kind":"text"},{"text":"Void","kind":"typeIdentifier","preciseIdentifier":"s:s4Voida"},{"text":") -> ","kind":"text"},{"text":"some","kind":"keyword"},{"text":" ","kind":"text"},{"text":"View","kind":"typeIdentifier","preciseIdentifier":"s:15OpenSwiftUICore4ViewP"}],"platforms":[{"name":"iOS","deprecated":false,"unavailable":false,"beta":false,"introducedAt":"13.0"},{"name":"macOS","deprecated":false,"unavailable":false,"beta":false,"introducedAt":"10.15"},{"name":"tvOS","deprecated":false,"unavailable":false,"beta":false,"introducedAt":"13.0"},{"name":"visionOS","deprecated":false,"unavailable":false,"beta":false,"introducedAt":"1.0"},{"name":"watchOS","deprecated":false,"unavailable":false,"beta":false,"introducedAt":"6.0"}],"remoteSource":{"url":"https:\/\/github.com\/OpenSwiftUIProject\/OpenSwiftUI\/blob\/main\/Sources\/OpenSwiftUICore\/Animation\/Transaction\/TransactionModifier.swift#L149","fileName":"TransactionModifier.swift"},"role":"symbol","externalID":"s:15OpenSwiftUICore4ViewPAAE11transaction5value_Qrqd___yAA11TransactionVzctSQRd__lF::SYNTHESIZED::s:11OpenSwiftUI12TimelineViewV"},"kind":"symbol","sections":[],"schemaVersion":{"major":0,"minor":3,"patch":0},"references":{"doc://OpenSwiftUI/documentation/OpenSwiftUI":{"identifier":"doc:\/\/OpenSwiftUI\/documentation\/OpenSwiftUI","url":"\/documentation\/openswiftui","role":"collection","type":"topic","kind":"symbol","abstract":[{"type":"text","text":"Declare the user interface and behavior for your app on every platform."}],"title":"OpenSwiftUI"},"doc://OpenSwiftUI/documentation/OpenSwiftUI/TimelineView/transaction(value:_:)":{"url":"\/documentation\/openswiftui\/timelineview\/transaction(value:_:)","identifier":"doc:\/\/OpenSwiftUI\/documentation\/OpenSwiftUI\/TimelineView\/transaction(value:_:)","type":"topic","kind":"symbol","title":"transaction(value:_:)","fragments":[{"text":"func","kind":"keyword"},{"text":" ","kind":"text"},{"text":"transaction","kind":"identifier"},{"text":"(","kind":"text"},{"text":"value","kind":"externalParam"},{"text":": ","kind":"text"},{"text":"some","kind":"keyword"},{"text":" ","kind":"text"},{"text":"Equatable","kind":"typeIdentifier","preciseIdentifier":"s:SQ"},{"text":", (","kind":"text"},{"text":"inout","kind":"keyword"},{"text":" ","kind":"text"},{"text":"Transaction","kind":"typeIdentifier","preciseIdentifier":"s:15OpenSwiftUICore11TransactionV"},{"text":") -> ","kind":"text"},{"text":"Void","kind":"typeIdentifier","preciseIdentifier":"s:s4Voida"},{"text":") -> ","kind":"text"},{"text":"some","kind":"keyword"},{"text":" ","kind":"text"},{"text":"View","kind":"typeIdentifier","preciseIdentifier":"s:15OpenSwiftUICore4ViewP"}],"abstract":[{"text":"Applies the given transaction mutation function to all animations used","type":"text"},{"text":" ","type":"text"},{"text":"within the view.","type":"text"}],"role":"symbol"},"doc://OpenSwiftUI/documentation/OpenSwiftUI/Transaction":{"fragments":[{"text":"struct","kind":"keyword"},{"text":" ","kind":"text"},{"text":"Transaction","kind":"identifier"}],"url":"\/documentation\/openswiftui\/transaction","identifier":"doc:\/\/OpenSwiftUI\/documentation\/OpenSwiftUI\/Transaction","role":"symbol","navigatorTitle":[{"text":"Transaction","kind":"identifier"}],"title":"Transaction","kind":"symbol","abstract":[{"type":"text","text":"The context of the current state-processing update."}],"type":"topic"},"doc://OpenSwiftUI/documentation/OpenSwiftUI/TimelineView":{"navigatorTitle":[{"kind":"identifier","text":"TimelineView"}],"abstract":[{"type":"text","text":"A view that updates according to a schedule that you provide."}],"role":"symbol","kind":"symbol","fragments":[{"kind":"keyword","text":"struct"},{"kind":"text","text":" "},{"kind":"identifier","text":"TimelineView"}],"title":"TimelineView","identifier":"doc:\/\/OpenSwiftUI\/documentation\/OpenSwiftUI\/TimelineView","type":"topic","url":"\/documentation\/openswiftui\/timelineview"},"doc://OpenSwiftUI/documentation/OpenSwiftUI/View":{"url":"\/documentation\/openswiftui\/view","abstract":[{"type":"text","text":"A type that represents part of your app’s user interface and provides"},{"type":"text","text":" "},{"type":"text","text":"modifiers that you use to configure views."}],"role":"symbol","identifier":"doc:\/\/OpenSwiftUI\/documentation\/OpenSwiftUI\/View","title":"View","type":"topic","fragments":[{"text":"protocol","kind":"keyword"},{"text":" ","kind":"text"},{"text":"View","kind":"identifier"}],"navigatorTitle":[{"text":"View","kind":"identifier"}],"kind":"symbol"},"doc://OpenSwiftUI/documentation/OpenSwiftUI/Text":{"abstract":[],"role":"symbol","navigatorTitle":[{"text":"Text","kind":"identifier"}],"type":"topic","fragments":[{"text":"struct","kind":"keyword"},{"text":" ","kind":"text"},{"text":"Text","kind":"identifier"}],"url":"\/documentation\/openswiftui\/text","kind":"symbol","identifier":"doc:\/\/OpenSwiftUI\/documentation\/OpenSwiftUI\/Text","title":"Text"}}}