{"primaryContentSections":[{"kind":"declarations","declarations":[{"languages":["swift"],"tokens":[{"kind":"keyword","text":"static"},{"kind":"text","text":" "},{"kind":"keyword","text":"func"},{"kind":"text","text":" "},{"kind":"identifier","text":"buildBlock"},{"kind":"text","text":"<"},{"kind":"genericParameter","text":"C0"},{"kind":"text","text":", "},{"kind":"genericParameter","text":"C1"},{"kind":"text","text":", "},{"kind":"genericParameter","text":"C2"},{"kind":"text","text":", "},{"kind":"genericParameter","text":"C3"},{"kind":"text","text":", "},{"kind":"genericParameter","text":"C4"},{"kind":"text","text":">("},{"kind":"externalParam","text":"_"},{"kind":"text","text":" "},{"kind":"internalParam","text":"c0"},{"kind":"text","text":": "},{"kind":"typeIdentifier","text":"C0","preciseIdentifier":"s:11OpenSwiftUI15CommandsBuilderV10buildBlockyQrx_q_q0_q1_q2_tAA0D0RzAaER_AaER0_AaER1_AaER2_r3_lFZQO2C0xmfp"},{"kind":"text","text":", "},{"kind":"externalParam","text":"_"},{"kind":"text","text":" "},{"kind":"internalParam","text":"c1"},{"kind":"text","text":": "},{"kind":"typeIdentifier","text":"C1","preciseIdentifier":"s:11OpenSwiftUI15CommandsBuilderV10buildBlockyQrx_q_q0_q1_q2_tAA0D0RzAaER_AaER0_AaER1_AaER2_r3_lFZQO2C1q_mfp"},{"kind":"text","text":", "},{"kind":"externalParam","text":"_"},{"kind":"text","text":" "},{"kind":"internalParam","text":"c2"},{"kind":"text","text":": "},{"kind":"typeIdentifier","text":"C2","preciseIdentifier":"s:11OpenSwiftUI15CommandsBuilderV10buildBlockyQrx_q_q0_q1_q2_tAA0D0RzAaER_AaER0_AaER1_AaER2_r3_lFZQO2C2q0_mfp"},{"kind":"text","text":", "},{"kind":"externalParam","text":"_"},{"kind":"text","text":" "},{"kind":"internalParam","text":"c3"},{"kind":"text","text":": "},{"kind":"typeIdentifier","text":"C3","preciseIdentifier":"s:11OpenSwiftUI15CommandsBuilderV10buildBlockyQrx_q_q0_q1_q2_tAA0D0RzAaER_AaER0_AaER1_AaER2_r3_lFZQO2C3q1_mfp"},{"kind":"text","text":", "},{"kind":"externalParam","text":"_"},{"kind":"text","text":" "},{"kind":"internalParam","text":"c4"},{"kind":"text","text":": "},{"kind":"typeIdentifier","text":"C4","preciseIdentifier":"s:11OpenSwiftUI15CommandsBuilderV10buildBlockyQrx_q_q0_q1_q2_tAA0D0RzAaER_AaER0_AaER1_AaER2_r3_lFZQO2C4q2_mfp"},{"kind":"text","text":") -> "},{"kind":"keyword","text":"some"},{"kind":"text","text":" "},{"kind":"typeIdentifier","text":"Commands","preciseIdentifier":"s:11OpenSwiftUI8CommandsP","identifier":"doc:\/\/OpenSwiftUI\/documentation\/OpenSwiftUI\/Commands"},{"kind":"text","text":" "},{"kind":"keyword","text":"where"},{"kind":"text","text":" "},{"kind":"typeIdentifier","text":"C0"},{"kind":"text","text":" : "},{"kind":"typeIdentifier","text":"Commands","preciseIdentifier":"s:11OpenSwiftUI8CommandsP","identifier":"doc:\/\/OpenSwiftUI\/documentation\/OpenSwiftUI\/Commands"},{"kind":"text","text":", "},{"kind":"typeIdentifier","text":"C1"},{"kind":"text","text":" : "},{"kind":"typeIdentifier","text":"Commands","preciseIdentifier":"s:11OpenSwiftUI8CommandsP","identifier":"doc:\/\/OpenSwiftUI\/documentation\/OpenSwiftUI\/Commands"},{"kind":"text","text":", "},{"kind":"typeIdentifier","text":"C2"},{"kind":"text","text":" : "},{"kind":"typeIdentifier","text":"Commands","preciseIdentifier":"s:11OpenSwiftUI8CommandsP","identifier":"doc:\/\/OpenSwiftUI\/documentation\/OpenSwiftUI\/Commands"},{"kind":"text","text":", "},{"kind":"typeIdentifier","text":"C3"},{"kind":"text","text":" : "},{"kind":"typeIdentifier","text":"Commands","preciseIdentifier":"s:11OpenSwiftUI8CommandsP","identifier":"doc:\/\/OpenSwiftUI\/documentation\/OpenSwiftUI\/Commands"},{"kind":"text","text":", "},{"kind":"typeIdentifier","text":"C4"},{"kind":"text","text":" : "},{"kind":"typeIdentifier","text":"Commands","preciseIdentifier":"s:11OpenSwiftUI8CommandsP","identifier":"doc:\/\/OpenSwiftUI\/documentation\/OpenSwiftUI\/Commands"},{"kind":"text","text":"\n"}],"platforms":["macOS"]}]}],"sections":[],"hierarchy":{"paths":[["doc:\/\/OpenSwiftUI\/documentation\/OpenSwiftUI","doc:\/\/OpenSwiftUI\/documentation\/OpenSwiftUI\/CommandsBuilder"]]},"variants":[{"paths":["\/documentation\/openswiftui\/commandsbuilder\/buildblock(_:_:_:_:_:)"],"traits":[{"interfaceLanguage":"swift"}]}],"schemaVersion":{"minor":3,"major":0,"patch":0},"identifier":{"interfaceLanguage":"swift","url":"doc:\/\/OpenSwiftUI\/documentation\/OpenSwiftUI\/CommandsBuilder\/buildBlock(_:_:_:_:_:)"},"metadata":{"title":"buildBlock(_:_:_:_:_:)","symbolKind":"method","roleHeading":"Type Method","platforms":[{"deprecated":false,"beta":false,"name":"iOS","unavailable":false,"introducedAt":"13.0"},{"deprecated":false,"beta":false,"name":"macOS","unavailable":false,"introducedAt":"10.15"},{"deprecated":false,"beta":false,"name":"visionOS","unavailable":false,"introducedAt":"1.0"}],"externalID":"s:11OpenSwiftUI15CommandsBuilderV10buildBlockyQrx_q_q0_q1_q2_tAA0D0RzAaER_AaER0_AaER1_AaER2_r3_lFZ","fragments":[{"kind":"keyword","text":"static"},{"kind":"text","text":" "},{"kind":"keyword","text":"func"},{"kind":"text","text":" "},{"kind":"identifier","text":"buildBlock"},{"kind":"text","text":"<"},{"kind":"genericParameter","text":"C0"},{"kind":"text","text":", "},{"kind":"genericParameter","text":"C1"},{"kind":"text","text":", "},{"kind":"genericParameter","text":"C2"},{"kind":"text","text":", "},{"kind":"genericParameter","text":"C3"},{"kind":"text","text":", "},{"kind":"genericParameter","text":"C4"},{"kind":"text","text":">("},{"preciseIdentifier":"s:11OpenSwiftUI15CommandsBuilderV10buildBlockyQrx_q_q0_q1_q2_tAA0D0RzAaER_AaER0_AaER1_AaER2_r3_lFZQO2C0xmfp","kind":"typeIdentifier","text":"C0"},{"kind":"text","text":", "},{"preciseIdentifier":"s:11OpenSwiftUI15CommandsBuilderV10buildBlockyQrx_q_q0_q1_q2_tAA0D0RzAaER_AaER0_AaER1_AaER2_r3_lFZQO2C1q_mfp","kind":"typeIdentifier","text":"C1"},{"kind":"text","text":", "},{"preciseIdentifier":"s:11OpenSwiftUI15CommandsBuilderV10buildBlockyQrx_q_q0_q1_q2_tAA0D0RzAaER_AaER0_AaER1_AaER2_r3_lFZQO2C2q0_mfp","kind":"typeIdentifier","text":"C2"},{"kind":"text","text":", "},{"preciseIdentifier":"s:11OpenSwiftUI15CommandsBuilderV10buildBlockyQrx_q_q0_q1_q2_tAA0D0RzAaER_AaER0_AaER1_AaER2_r3_lFZQO2C3q1_mfp","kind":"typeIdentifier","text":"C3"},{"kind":"text","text":", "},{"preciseIdentifier":"s:11OpenSwiftUI15CommandsBuilderV10buildBlockyQrx_q_q0_q1_q2_tAA0D0RzAaER_AaER0_AaER1_AaER2_r3_lFZQO2C4q2_mfp","kind":"typeIdentifier","text":"C4"},{"kind":"text","text":") -> "},{"kind":"keyword","text":"some"},{"kind":"text","text":" "},{"preciseIdentifier":"s:11OpenSwiftUI8CommandsP","kind":"typeIdentifier","text":"Commands"}],"remoteSource":{"fileName":"TupleCommandContent.swift","url":"https:\/\/github.com\/OpenSwiftUIProject\/OpenSwiftUI\/blob\/main\/Sources\/OpenSwiftUI\/App\/Commands\/TupleCommandContent.swift#L169"},"modules":[{"name":"OpenSwiftUI"}],"extendedModule":"OpenSwiftUI","role":"symbol"},"kind":"symbol","references":{"doc://OpenSwiftUI/documentation/OpenSwiftUI/Commands":{"title":"Commands","url":"\/documentation\/openswiftui\/commands","kind":"symbol","navigatorTitle":[{"text":"Commands","kind":"identifier"}],"identifier":"doc:\/\/OpenSwiftUI\/documentation\/OpenSwiftUI\/Commands","type":"topic","role":"symbol","fragments":[{"text":"protocol","kind":"keyword"},{"text":" ","kind":"text"},{"text":"Commands","kind":"identifier"}],"abstract":[{"text":"Conforming types represent a group of related commands that can be exposed","type":"text"},{"text":" ","type":"text"},{"text":"to the user via the main menu on macOS and key commands on iOS.","type":"text"}]},"doc://OpenSwiftUI/documentation/OpenSwiftUI/CommandsBuilder/buildBlock(_:_:_:_:_:)":{"abstract":[],"url":"\/documentation\/openswiftui\/commandsbuilder\/buildblock(_:_:_:_:_:)","fragments":[{"text":"static","kind":"keyword"},{"text":" ","kind":"text"},{"text":"func","kind":"keyword"},{"text":" ","kind":"text"},{"text":"buildBlock","kind":"identifier"},{"text":"<","kind":"text"},{"text":"C0","kind":"genericParameter"},{"text":", ","kind":"text"},{"text":"C1","kind":"genericParameter"},{"text":", ","kind":"text"},{"text":"C2","kind":"genericParameter"},{"text":", ","kind":"text"},{"text":"C3","kind":"genericParameter"},{"text":", ","kind":"text"},{"text":"C4","kind":"genericParameter"},{"text":">(","kind":"text"},{"preciseIdentifier":"s:11OpenSwiftUI15CommandsBuilderV10buildBlockyQrx_q_q0_q1_q2_tAA0D0RzAaER_AaER0_AaER1_AaER2_r3_lFZQO2C0xmfp","text":"C0","kind":"typeIdentifier"},{"text":", ","kind":"text"},{"preciseIdentifier":"s:11OpenSwiftUI15CommandsBuilderV10buildBlockyQrx_q_q0_q1_q2_tAA0D0RzAaER_AaER0_AaER1_AaER2_r3_lFZQO2C1q_mfp","text":"C1","kind":"typeIdentifier"},{"text":", ","kind":"text"},{"preciseIdentifier":"s:11OpenSwiftUI15CommandsBuilderV10buildBlockyQrx_q_q0_q1_q2_tAA0D0RzAaER_AaER0_AaER1_AaER2_r3_lFZQO2C2q0_mfp","text":"C2","kind":"typeIdentifier"},{"text":", ","kind":"text"},{"preciseIdentifier":"s:11OpenSwiftUI15CommandsBuilderV10buildBlockyQrx_q_q0_q1_q2_tAA0D0RzAaER_AaER0_AaER1_AaER2_r3_lFZQO2C3q1_mfp","text":"C3","kind":"typeIdentifier"},{"text":", ","kind":"text"},{"preciseIdentifier":"s:11OpenSwiftUI15CommandsBuilderV10buildBlockyQrx_q_q0_q1_q2_tAA0D0RzAaER_AaER0_AaER1_AaER2_r3_lFZQO2C4q2_mfp","text":"C4","kind":"typeIdentifier"},{"text":") -> ","kind":"text"},{"text":"some","kind":"keyword"},{"text":" ","kind":"text"},{"preciseIdentifier":"s:11OpenSwiftUI8CommandsP","text":"Commands","kind":"typeIdentifier"}],"kind":"symbol","identifier":"doc:\/\/OpenSwiftUI\/documentation\/OpenSwiftUI\/CommandsBuilder\/buildBlock(_:_:_:_:_:)","title":"buildBlock(_:_:_:_:_:)","type":"topic","role":"symbol"},"doc://OpenSwiftUI/documentation/OpenSwiftUI":{"type":"topic","identifier":"doc:\/\/OpenSwiftUI\/documentation\/OpenSwiftUI","url":"\/documentation\/openswiftui","title":"OpenSwiftUI","kind":"symbol","role":"collection","abstract":[{"type":"text","text":"Declare the user interface and behavior for your app on every platform."}]},"doc://OpenSwiftUI/documentation/OpenSwiftUI/CommandsBuilder":{"kind":"symbol","identifier":"doc:\/\/OpenSwiftUI\/documentation\/OpenSwiftUI\/CommandsBuilder","abstract":[{"type":"text","text":"Constructs command sets from multi-expression closures. Like "},{"type":"codeVoice","code":"ViewBuilder"},{"type":"text","text":","},{"type":"text","text":" "},{"type":"text","text":"it supports up to ten expressions in the closure body."}],"title":"CommandsBuilder","role":"symbol","fragments":[{"kind":"keyword","text":"struct"},{"kind":"text","text":" "},{"kind":"identifier","text":"CommandsBuilder"}],"navigatorTitle":[{"kind":"identifier","text":"CommandsBuilder"}],"url":"\/documentation\/openswiftui\/commandsbuilder","type":"topic"}}}