{"topicSections":[{"identifiers":["doc:\/\/OpenSwiftUI\/documentation\/OpenSwiftUI\/Ellipse\/animation(_:)","doc:\/\/OpenSwiftUI\/documentation\/OpenSwiftUI\/Ellipse\/animation(_:body:)","doc:\/\/OpenSwiftUI\/documentation\/OpenSwiftUI\/Ellipse\/animation(_:value:)","doc:\/\/OpenSwiftUI\/documentation\/OpenSwiftUI\/Ellipse\/aspectRatio(_:contentMode:)-2er13","doc:\/\/OpenSwiftUI\/documentation\/OpenSwiftUI\/Ellipse\/aspectRatio(_:contentMode:)-6bbu5","doc:\/\/OpenSwiftUI\/documentation\/OpenSwiftUI\/Ellipse\/background(_:alignment:)","doc:\/\/OpenSwiftUI\/documentation\/OpenSwiftUI\/Ellipse\/background(alignment:content:)","doc:\/\/OpenSwiftUI\/documentation\/OpenSwiftUI\/Ellipse\/clipShape(_:style:)","doc:\/\/OpenSwiftUI\/documentation\/OpenSwiftUI\/Ellipse\/clipped(antialiased:)","doc:\/\/OpenSwiftUI\/documentation\/OpenSwiftUI\/Ellipse\/colorScheme(_:)","doc:\/\/OpenSwiftUI\/documentation\/OpenSwiftUI\/Ellipse\/controlSize(_:)","doc:\/\/OpenSwiftUI\/documentation\/OpenSwiftUI\/Ellipse\/cornerRadius(_:antialiased:)","doc:\/\/OpenSwiftUI\/documentation\/OpenSwiftUI\/Ellipse\/disabled(_:)-4hz7c","doc:\/\/OpenSwiftUI\/documentation\/OpenSwiftUI\/Ellipse\/disabled(_:)-6fkwb","doc:\/\/OpenSwiftUI\/documentation\/OpenSwiftUI\/Ellipse\/dynamicTypeSize(_:)","doc:\/\/OpenSwiftUI\/documentation\/OpenSwiftUI\/Ellipse\/edgesIgnoringSafeArea(_:)","doc:\/\/OpenSwiftUI\/documentation\/OpenSwiftUI\/Ellipse\/environment(_:)","doc:\/\/OpenSwiftUI\/documentation\/OpenSwiftUI\/Ellipse\/environment(_:_:)","doc:\/\/OpenSwiftUI\/documentation\/OpenSwiftUI\/Ellipse\/environmentObject(_:)","doc:\/\/OpenSwiftUI\/documentation\/OpenSwiftUI\/Ellipse\/fixedSize()","doc:\/\/OpenSwiftUI\/documentation\/OpenSwiftUI\/Ellipse\/fixedSize(horizontal:vertical:)","doc:\/\/OpenSwiftUI\/documentation\/OpenSwiftUI\/Ellipse\/font(_:)","doc:\/\/OpenSwiftUI\/documentation\/OpenSwiftUI\/Ellipse\/foregroundStyle(_:)","doc:\/\/OpenSwiftUI\/documentation\/OpenSwiftUI\/Ellipse\/foregroundStyle(_:_:)","doc:\/\/OpenSwiftUI\/documentation\/OpenSwiftUI\/Ellipse\/foregroundStyle(_:_:_:)","doc:\/\/OpenSwiftUI\/documentation\/OpenSwiftUI\/Ellipse\/frame()","doc:\/\/OpenSwiftUI\/documentation\/OpenSwiftUI\/Ellipse\/frame(minWidth:idealWidth:maxWidth:minHeight:idealHeight:maxHeight:alignment:)","doc:\/\/OpenSwiftUI\/documentation\/OpenSwiftUI\/Ellipse\/frame(width:height:alignment:)","doc:\/\/OpenSwiftUI\/documentation\/OpenSwiftUI\/Ellipse\/geometryGroup()","doc:\/\/OpenSwiftUI\/documentation\/OpenSwiftUI\/Ellipse\/id(_:)","doc:\/\/OpenSwiftUI\/documentation\/OpenSwiftUI\/Ellipse\/ignoresSafeArea(_:edges:)","doc:\/\/OpenSwiftUI\/documentation\/OpenSwiftUI\/Ellipse\/layoutPriority(_:)","doc:\/\/OpenSwiftUI\/documentation\/OpenSwiftUI\/Ellipse\/layoutValue(key:value:)","doc:\/\/OpenSwiftUI\/documentation\/OpenSwiftUI\/Ellipse\/modifier(_:)","doc:\/\/OpenSwiftUI\/documentation\/OpenSwiftUI\/Ellipse\/offset(_:)","doc:\/\/OpenSwiftUI\/documentation\/OpenSwiftUI\/Ellipse\/offset(x:y:)","doc:\/\/OpenSwiftUI\/documentation\/OpenSwiftUI\/Ellipse\/onAppear(perform:)","doc:\/\/OpenSwiftUI\/documentation\/OpenSwiftUI\/Ellipse\/onChange(of:initial:_:)-6gyuv","doc:\/\/OpenSwiftUI\/documentation\/OpenSwiftUI\/Ellipse\/onChange(of:initial:_:)-8yyep","doc:\/\/OpenSwiftUI\/documentation\/OpenSwiftUI\/Ellipse\/onChange(of:perform:)","doc:\/\/OpenSwiftUI\/documentation\/OpenSwiftUI\/Ellipse\/onDisappear(perform:)","doc:\/\/OpenSwiftUI\/documentation\/OpenSwiftUI\/Ellipse\/overlay(_:alignment:)","doc:\/\/OpenSwiftUI\/documentation\/OpenSwiftUI\/Ellipse\/overlay(alignment:content:)","doc:\/\/OpenSwiftUI\/documentation\/OpenSwiftUI\/Ellipse\/padding(_:)-2db3t","doc:\/\/OpenSwiftUI\/documentation\/OpenSwiftUI\/Ellipse\/padding(_:)-7p0vd","doc:\/\/OpenSwiftUI\/documentation\/OpenSwiftUI\/Ellipse\/padding(_:_:)","doc:\/\/OpenSwiftUI\/documentation\/OpenSwiftUI\/Ellipse\/preference(key:value:)","doc:\/\/OpenSwiftUI\/documentation\/OpenSwiftUI\/Ellipse\/rotation3DEffect(_:axis:anchor:anchorZ:perspective:)","doc:\/\/OpenSwiftUI\/documentation\/OpenSwiftUI\/Ellipse\/rotationEffect(_:anchor:)","doc:\/\/OpenSwiftUI\/documentation\/OpenSwiftUI\/Ellipse\/safeAreaInset(edge:alignment:spacing:content:)-58523","doc:\/\/OpenSwiftUI\/documentation\/OpenSwiftUI\/Ellipse\/safeAreaInset(edge:alignment:spacing:content:)-5nnzo","doc:\/\/OpenSwiftUI\/documentation\/OpenSwiftUI\/Ellipse\/safeAreaPadding(_:)-5nk70","doc:\/\/OpenSwiftUI\/documentation\/OpenSwiftUI\/Ellipse\/safeAreaPadding(_:)-ex73","doc:\/\/OpenSwiftUI\/documentation\/OpenSwiftUI\/Ellipse\/safeAreaPadding(_:_:)","doc:\/\/OpenSwiftUI\/documentation\/OpenSwiftUI\/Ellipse\/scaledToFill()","doc:\/\/OpenSwiftUI\/documentation\/OpenSwiftUI\/Ellipse\/scaledToFit()","doc:\/\/OpenSwiftUI\/documentation\/OpenSwiftUI\/Ellipse\/task(id:priority:_:)","doc:\/\/OpenSwiftUI\/documentation\/OpenSwiftUI\/Ellipse\/task(priority:_:)","doc:\/\/OpenSwiftUI\/documentation\/OpenSwiftUI\/Ellipse\/tint(_:)","doc:\/\/OpenSwiftUI\/documentation\/OpenSwiftUI\/Ellipse\/toggleStyle(_:)","doc:\/\/OpenSwiftUI\/documentation\/OpenSwiftUI\/Ellipse\/transaction(_:)","doc:\/\/OpenSwiftUI\/documentation\/OpenSwiftUI\/Ellipse\/transaction(_:body:)","doc:\/\/OpenSwiftUI\/documentation\/OpenSwiftUI\/Ellipse\/transaction(value:_:)","doc:\/\/OpenSwiftUI\/documentation\/OpenSwiftUI\/Ellipse\/transformEnvironment(_:transform:)","doc:\/\/OpenSwiftUI\/documentation\/OpenSwiftUI\/Ellipse\/transformPreference(_:_:)","doc:\/\/OpenSwiftUI\/documentation\/OpenSwiftUI\/Ellipse\/zIndex(_:)"],"anchor":"Instance-Methods","title":"Instance Methods","generated":true}],"identifier":{"url":"doc:\/\/OpenSwiftUI\/documentation\/OpenSwiftUI\/Ellipse\/View-Implementations","interfaceLanguage":"swift"},"sections":[],"kind":"article","schemaVersion":{"major":0,"patch":0,"minor":3},"variants":[{"paths":["\/documentation\/openswiftui\/ellipse\/view-implementations"],"traits":[{"interfaceLanguage":"swift"}]}],"hierarchy":{"paths":[["doc:\/\/OpenSwiftUI\/documentation\/OpenSwiftUI","doc:\/\/OpenSwiftUI\/documentation\/OpenSwiftUI\/Ellipse"]]},"metadata":{"role":"collectionGroup","roleHeading":"API Collection","title":"View Implementations","modules":[{"name":"OpenSwiftUI"}]},"references":{"doc://OpenSwiftUI/documentation/OpenSwiftUI/Ellipse/edgesIgnoringSafeArea(_:)":{"kind":"symbol","url":"\/documentation\/openswiftui\/ellipse\/edgesignoringsafearea(_:)","title":"edgesIgnoringSafeArea(_:)","deprecated":true,"role":"symbol","abstract":[{"text":"Changes the view’s proposed area to extend outside the screen’s safe","type":"text"},{"text":" ","type":"text"},{"text":"areas.","type":"text"}],"identifier":"doc:\/\/OpenSwiftUI\/documentation\/OpenSwiftUI\/Ellipse\/edgesIgnoringSafeArea(_:)","fragments":[{"text":"func","kind":"keyword"},{"text":" ","kind":"text"},{"text":"edgesIgnoringSafeArea","kind":"identifier"},{"text":"(","kind":"text"},{"preciseIdentifier":"s:15OpenSwiftUICore4EdgeO","text":"Edge","kind":"typeIdentifier"},{"text":".","kind":"text"},{"preciseIdentifier":"s:15OpenSwiftUICore4EdgeO3SetV","text":"Set","kind":"typeIdentifier"},{"text":") -> ","kind":"text"},{"text":"some","kind":"keyword"},{"text":" ","kind":"text"},{"preciseIdentifier":"s:15OpenSwiftUICore4ViewP","text":"View","kind":"typeIdentifier"}],"type":"topic"},"doc://OpenSwiftUI/documentation/OpenSwiftUI/Ellipse/aspectRatio(_:contentMode:)-6bbu5":{"url":"\/documentation\/openswiftui\/ellipse\/aspectratio(_:contentmode:)-6bbu5","fragments":[{"kind":"keyword","text":"func"},{"kind":"text","text":" "},{"kind":"identifier","text":"aspectRatio"},{"kind":"text","text":"("},{"preciseIdentifier":"s:14CoreFoundation7CGFloatV","kind":"typeIdentifier","text":"CGFloat"},{"kind":"text","text":"?, "},{"kind":"externalParam","text":"contentMode"},{"kind":"text","text":": "},{"preciseIdentifier":"s:15OpenSwiftUICore11ContentModeO","kind":"typeIdentifier","text":"ContentMode"},{"kind":"text","text":") -> "},{"kind":"keyword","text":"some"},{"kind":"text","text":" "},{"preciseIdentifier":"s:15OpenSwiftUICore4ViewP","kind":"typeIdentifier","text":"View"}],"identifier":"doc:\/\/OpenSwiftUI\/documentation\/OpenSwiftUI\/Ellipse\/aspectRatio(_:contentMode:)-6bbu5","kind":"symbol","role":"symbol","title":"aspectRatio(_:contentMode:)","type":"topic","abstract":[{"type":"text","text":"Constrains this view’s dimensions to the specified aspect ratio."}]},"doc://OpenSwiftUI/documentation/OpenSwiftUI/Ellipse/safeAreaPadding(_:)-ex73":{"url":"\/documentation\/openswiftui\/ellipse\/safeareapadding(_:)-ex73","fragments":[{"text":"func","kind":"keyword"},{"text":" ","kind":"text"},{"text":"safeAreaPadding","kind":"identifier"},{"text":"(","kind":"text"},{"text":"CGFloat","kind":"typeIdentifier","preciseIdentifier":"s:14CoreFoundation7CGFloatV"},{"text":") -> ","kind":"text"},{"text":"some","kind":"keyword"},{"text":" ","kind":"text"},{"text":"View","kind":"typeIdentifier","preciseIdentifier":"s:15OpenSwiftUICore4ViewP"}],"identifier":"doc:\/\/OpenSwiftUI\/documentation\/OpenSwiftUI\/Ellipse\/safeAreaPadding(_:)-ex73","kind":"symbol","type":"topic","abstract":[{"text":"Adds the provided insets into the safe area of this view.","type":"text"}],"role":"symbol","title":"safeAreaPadding(_:)"},"doc://OpenSwiftUI/documentation/OpenSwiftUI/Ellipse/safeAreaPadding(_:_:)":{"type":"topic","kind":"symbol","abstract":[{"text":"Adds the provided insets into the safe area of this view.","type":"text"}],"identifier":"doc:\/\/OpenSwiftUI\/documentation\/OpenSwiftUI\/Ellipse\/safeAreaPadding(_:_:)","url":"\/documentation\/openswiftui\/ellipse\/safeareapadding(_:_:)","title":"safeAreaPadding(_:_:)","fragments":[{"text":"func","kind":"keyword"},{"text":" ","kind":"text"},{"text":"safeAreaPadding","kind":"identifier"},{"text":"(","kind":"text"},{"preciseIdentifier":"s:15OpenSwiftUICore4EdgeO","text":"Edge","kind":"typeIdentifier"},{"text":".","kind":"text"},{"preciseIdentifier":"s:15OpenSwiftUICore4EdgeO3SetV","text":"Set","kind":"typeIdentifier"},{"text":", ","kind":"text"},{"preciseIdentifier":"s:14CoreFoundation7CGFloatV","text":"CGFloat","kind":"typeIdentifier"},{"text":"?) -> ","kind":"text"},{"text":"some","kind":"keyword"},{"text":" ","kind":"text"},{"preciseIdentifier":"s:15OpenSwiftUICore4ViewP","text":"View","kind":"typeIdentifier"}],"role":"symbol"},"doc://OpenSwiftUI/documentation/OpenSwiftUI/Ellipse/foregroundStyle(_:)":{"fragments":[{"kind":"keyword","text":"func"},{"kind":"text","text":" "},{"kind":"identifier","text":"foregroundStyle"},{"kind":"text","text":"<"},{"kind":"genericParameter","text":"S"},{"kind":"text","text":">("},{"kind":"typeIdentifier","text":"S"},{"kind":"text","text":") -> "},{"kind":"keyword","text":"some"},{"kind":"text","text":" "},{"kind":"typeIdentifier","preciseIdentifier":"s:15OpenSwiftUICore4ViewP","text":"View"}],"identifier":"doc:\/\/OpenSwiftUI\/documentation\/OpenSwiftUI\/Ellipse\/foregroundStyle(_:)","url":"\/documentation\/openswiftui\/ellipse\/foregroundstyle(_:)","kind":"symbol","abstract":[{"type":"text","text":"Sets a view’s foreground elements to use a given style."}],"type":"topic","role":"symbol","title":"foregroundStyle(_:)"},"doc://OpenSwiftUI/documentation/OpenSwiftUI/Ellipse/offset(x:y:)":{"fragments":[{"text":"func","kind":"keyword"},{"text":" ","kind":"text"},{"text":"offset","kind":"identifier"},{"text":"(","kind":"text"},{"text":"x","kind":"externalParam"},{"text":": ","kind":"text"},{"preciseIdentifier":"s:14CoreFoundation7CGFloatV","text":"CGFloat","kind":"typeIdentifier"},{"text":", ","kind":"text"},{"text":"y","kind":"externalParam"},{"text":": ","kind":"text"},{"preciseIdentifier":"s:14CoreFoundation7CGFloatV","text":"CGFloat","kind":"typeIdentifier"},{"text":") -> ","kind":"text"},{"text":"some","kind":"keyword"},{"text":" ","kind":"text"},{"preciseIdentifier":"s:15OpenSwiftUICore4ViewP","text":"View","kind":"typeIdentifier"}],"title":"offset(x:y:)","kind":"symbol","abstract":[{"text":"Offset this view by the specified horizontal and vertical distances.","type":"text"}],"role":"symbol","url":"\/documentation\/openswiftui\/ellipse\/offset(x:y:)","identifier":"doc:\/\/OpenSwiftUI\/documentation\/OpenSwiftUI\/Ellipse\/offset(x:y:)","type":"topic"},"doc://OpenSwiftUI/documentation/OpenSwiftUI/Ellipse/onChange(of:perform:)":{"abstract":[{"text":"Performs an action when a specified value changes.","type":"text"}],"deprecated":true,"fragments":[{"kind":"keyword","text":"func"},{"kind":"text","text":" "},{"kind":"identifier","text":"onChange"},{"kind":"text","text":"<"},{"kind":"genericParameter","text":"V"},{"kind":"text","text":">("},{"kind":"externalParam","text":"of"},{"kind":"text","text":": "},{"kind":"typeIdentifier","text":"V"},{"kind":"text","text":", "},{"kind":"externalParam","text":"perform"},{"kind":"text","text":": ("},{"kind":"typeIdentifier","text":"V"},{"kind":"text","text":") -> "},{"kind":"typeIdentifier","text":"Void","preciseIdentifier":"s:s4Voida"},{"kind":"text","text":") -> "},{"kind":"keyword","text":"some"},{"kind":"text","text":" "},{"kind":"typeIdentifier","text":"View","preciseIdentifier":"s:15OpenSwiftUICore4ViewP"}],"identifier":"doc:\/\/OpenSwiftUI\/documentation\/OpenSwiftUI\/Ellipse\/onChange(of:perform:)","url":"\/documentation\/openswiftui\/ellipse\/onchange(of:perform:)","role":"symbol","title":"onChange(of:perform:)","kind":"symbol","type":"topic"},"doc://OpenSwiftUI/documentation/OpenSwiftUI/Ellipse/padding(_:)-7p0vd":{"fragments":[{"text":"func","kind":"keyword"},{"text":" ","kind":"text"},{"text":"padding","kind":"identifier"},{"text":"(","kind":"text"},{"preciseIdentifier":"s:14CoreFoundation7CGFloatV","text":"CGFloat","kind":"typeIdentifier"},{"text":") -> ","kind":"text"},{"text":"some","kind":"keyword"},{"text":" ","kind":"text"},{"preciseIdentifier":"s:15OpenSwiftUICore4ViewP","text":"View","kind":"typeIdentifier"}],"type":"topic","identifier":"doc:\/\/OpenSwiftUI\/documentation\/OpenSwiftUI\/Ellipse\/padding(_:)-7p0vd","url":"\/documentation\/openswiftui\/ellipse\/padding(_:)-7p0vd","title":"padding(_:)","abstract":[{"type":"text","text":"Adds a specific padding amount to each edge of this view."}],"kind":"symbol","role":"symbol"},"doc://OpenSwiftUI/documentation/OpenSwiftUI/Ellipse/transaction(_:)":{"abstract":[{"type":"text","text":"Applies the given transaction mutation function to all animations used"},{"type":"text","text":" "},{"type":"text","text":"within the view."}],"identifier":"doc:\/\/OpenSwiftUI\/documentation\/OpenSwiftUI\/Ellipse\/transaction(_:)","kind":"symbol","url":"\/documentation\/openswiftui\/ellipse\/transaction(_:)","type":"topic","fragments":[{"kind":"keyword","text":"func"},{"kind":"text","text":" "},{"kind":"identifier","text":"transaction"},{"kind":"text","text":"(("},{"kind":"keyword","text":"inout"},{"kind":"text","text":" "},{"kind":"typeIdentifier","preciseIdentifier":"s:15OpenSwiftUICore11TransactionV","text":"Transaction"},{"kind":"text","text":") -> "},{"kind":"typeIdentifier","preciseIdentifier":"s:s4Voida","text":"Void"},{"kind":"text","text":") -> "},{"kind":"keyword","text":"some"},{"kind":"text","text":" "},{"kind":"typeIdentifier","preciseIdentifier":"s:15OpenSwiftUICore4ViewP","text":"View"}],"title":"transaction(_:)","role":"symbol"},"doc://OpenSwiftUI/documentation/OpenSwiftUI/Ellipse/controlSize(_:)":{"fragments":[{"kind":"keyword","text":"func"},{"kind":"text","text":" "},{"kind":"identifier","text":"controlSize"},{"kind":"text","text":"("},{"kind":"typeIdentifier","text":"ControlSize","preciseIdentifier":"s:11OpenSwiftUI11ControlSizeO"},{"kind":"text","text":") -> "},{"kind":"keyword","text":"some"},{"kind":"text","text":" "},{"kind":"typeIdentifier","text":"View","preciseIdentifier":"s:15OpenSwiftUICore4ViewP"}],"type":"topic","title":"controlSize(_:)","role":"symbol","kind":"symbol","abstract":[{"text":"Sets the size for controls within this view.","type":"text"}],"identifier":"doc:\/\/OpenSwiftUI\/documentation\/OpenSwiftUI\/Ellipse\/controlSize(_:)","url":"\/documentation\/openswiftui\/ellipse\/controlsize(_:)"},"doc://OpenSwiftUI/documentation/OpenSwiftUI/Ellipse/foregroundStyle(_:_:_:)":{"title":"foregroundStyle(_:_:_:)","type":"topic","abstract":[{"type":"text","text":"Sets the primary, secondary, and tertiary levels of"},{"type":"text","text":" "},{"type":"text","text":"the foreground style."}],"identifier":"doc:\/\/OpenSwiftUI\/documentation\/OpenSwiftUI\/Ellipse\/foregroundStyle(_:_:_:)","kind":"symbol","role":"symbol","fragments":[{"text":"func","kind":"keyword"},{"text":" ","kind":"text"},{"text":"foregroundStyle","kind":"identifier"},{"text":"<","kind":"text"},{"text":"S1","kind":"genericParameter"},{"text":", ","kind":"text"},{"text":"S2","kind":"genericParameter"},{"text":", ","kind":"text"},{"text":"S3","kind":"genericParameter"},{"text":">(","kind":"text"},{"text":"S1","kind":"typeIdentifier"},{"text":", ","kind":"text"},{"text":"S2","kind":"typeIdentifier"},{"text":", ","kind":"text"},{"text":"S3","kind":"typeIdentifier"},{"text":") -> ","kind":"text"},{"text":"some","kind":"keyword"},{"text":" ","kind":"text"},{"text":"View","kind":"typeIdentifier","preciseIdentifier":"s:15OpenSwiftUICore4ViewP"}],"url":"\/documentation\/openswiftui\/ellipse\/foregroundstyle(_:_:_:)"},"doc://OpenSwiftUI/documentation/OpenSwiftUI/Ellipse/toggleStyle(_:)":{"abstract":[{"text":"Sets the style for toggles in a view hierarchy.","type":"text"}],"fragments":[{"kind":"keyword","text":"func"},{"kind":"text","text":" "},{"kind":"identifier","text":"toggleStyle"},{"kind":"text","text":"<"},{"kind":"genericParameter","text":"S"},{"kind":"text","text":">("},{"preciseIdentifier":"s:15OpenSwiftUICore4ViewP0aB2UIE11toggleStyleyQrqd__AD06ToggleG0Rd__lFQO1Sqd__mfp","kind":"typeIdentifier","text":"S"},{"kind":"text","text":") -> "},{"kind":"keyword","text":"some"},{"kind":"text","text":" "},{"preciseIdentifier":"s:15OpenSwiftUICore4ViewP","kind":"typeIdentifier","text":"View"}],"kind":"symbol","title":"toggleStyle(_:)","type":"topic","identifier":"doc:\/\/OpenSwiftUI\/documentation\/OpenSwiftUI\/Ellipse\/toggleStyle(_:)","role":"symbol","url":"\/documentation\/openswiftui\/ellipse\/togglestyle(_:)"},"doc://OpenSwiftUI/documentation/OpenSwiftUI/Ellipse/modifier(_:)":{"url":"\/documentation\/openswiftui\/ellipse\/modifier(_:)","kind":"symbol","abstract":[{"text":"Applies a modifier to a view and returns a new view.","type":"text"}],"type":"topic","fragments":[{"text":"func","kind":"keyword"},{"text":" ","kind":"text"},{"text":"modifier","kind":"identifier"},{"text":"<","kind":"text"},{"text":"T","kind":"genericParameter"},{"text":">(","kind":"text"},{"text":"T","kind":"typeIdentifier"},{"text":") -> ","kind":"text"},{"text":"ModifiedContent","kind":"typeIdentifier","preciseIdentifier":"s:15OpenSwiftUICore15ModifiedContentV"},{"text":"<","kind":"text"},{"text":"Self","kind":"typeIdentifier"},{"text":", ","kind":"text"},{"text":"T","kind":"typeIdentifier"},{"text":">","kind":"text"}],"role":"symbol","title":"modifier(_:)","identifier":"doc:\/\/OpenSwiftUI\/documentation\/OpenSwiftUI\/Ellipse\/modifier(_:)"},"doc://OpenSwiftUI/documentation/OpenSwiftUI/Ellipse/aspectRatio(_:contentMode:)-2er13":{"fragments":[{"kind":"keyword","text":"func"},{"kind":"text","text":" "},{"kind":"identifier","text":"aspectRatio"},{"kind":"text","text":"("},{"kind":"typeIdentifier","preciseIdentifier":"c:@S@CGSize","text":"CGSize"},{"kind":"text","text":", "},{"kind":"externalParam","text":"contentMode"},{"kind":"text","text":": "},{"kind":"typeIdentifier","preciseIdentifier":"s:15OpenSwiftUICore11ContentModeO","text":"ContentMode"},{"kind":"text","text":") -> "},{"kind":"keyword","text":"some"},{"kind":"text","text":" "},{"text":"View","kind":"typeIdentifier","preciseIdentifier":"s:15OpenSwiftUICore4ViewP"}],"type":"topic","identifier":"doc:\/\/OpenSwiftUI\/documentation\/OpenSwiftUI\/Ellipse\/aspectRatio(_:contentMode:)-2er13","role":"symbol","title":"aspectRatio(_:contentMode:)","kind":"symbol","url":"\/documentation\/openswiftui\/ellipse\/aspectratio(_:contentmode:)-2er13","abstract":[{"text":"Constrains this view’s dimensions to the aspect ratio of the given size.","type":"text"}]},"doc://OpenSwiftUI/documentation/OpenSwiftUI/Ellipse/font(_:)":{"fragments":[{"text":"func","kind":"keyword"},{"text":" ","kind":"text"},{"text":"font","kind":"identifier"},{"text":"(","kind":"text"},{"preciseIdentifier":"s:15OpenSwiftUICore4FontV","text":"Font","kind":"typeIdentifier"},{"text":"?) -> ","kind":"text"},{"text":"some","kind":"keyword"},{"text":" ","kind":"text"},{"preciseIdentifier":"s:15OpenSwiftUICore4ViewP","text":"View","kind":"typeIdentifier"}],"type":"topic","identifier":"doc:\/\/OpenSwiftUI\/documentation\/OpenSwiftUI\/Ellipse\/font(_:)","role":"symbol","abstract":[],"kind":"symbol","url":"\/documentation\/openswiftui\/ellipse\/font(_:)","title":"font(_:)"},"doc://OpenSwiftUI/documentation/OpenSwiftUI/Ellipse/ignoresSafeArea(_:edges:)":{"fragments":[{"kind":"keyword","text":"func"},{"kind":"text","text":" "},{"kind":"identifier","text":"ignoresSafeArea"},{"kind":"text","text":"("},{"preciseIdentifier":"s:15OpenSwiftUICore15SafeAreaRegionsV","kind":"typeIdentifier","text":"SafeAreaRegions"},{"kind":"text","text":", "},{"kind":"externalParam","text":"edges"},{"kind":"text","text":": "},{"preciseIdentifier":"s:15OpenSwiftUICore4EdgeO","kind":"typeIdentifier","text":"Edge"},{"kind":"text","text":"."},{"preciseIdentifier":"s:15OpenSwiftUICore4EdgeO3SetV","kind":"typeIdentifier","text":"Set"},{"kind":"text","text":") -> "},{"text":"some","kind":"keyword"},{"text":" ","kind":"text"},{"text":"View","kind":"typeIdentifier","preciseIdentifier":"s:15OpenSwiftUICore4ViewP"}],"type":"topic","identifier":"doc:\/\/OpenSwiftUI\/documentation\/OpenSwiftUI\/Ellipse\/ignoresSafeArea(_:edges:)","role":"symbol","kind":"symbol","abstract":[{"text":"Expands the safe area of a view.","type":"text"}],"title":"ignoresSafeArea(_:edges:)","url":"\/documentation\/openswiftui\/ellipse\/ignoressafearea(_:edges:)"},"doc://OpenSwiftUI/documentation/OpenSwiftUI/Ellipse/background(_:alignment:)":{"deprecated":true,"fragments":[{"kind":"keyword","text":"func"},{"kind":"text","text":" "},{"kind":"identifier","text":"background"},{"kind":"text","text":"<"},{"kind":"genericParameter","text":"Background"},{"kind":"text","text":">("},{"kind":"typeIdentifier","text":"Background"},{"kind":"text","text":", "},{"kind":"externalParam","text":"alignment"},{"kind":"text","text":": "},{"kind":"typeIdentifier","text":"Alignment","preciseIdentifier":"s:15OpenSwiftUICore9AlignmentV"},{"kind":"text","text":") -> "},{"text":"some","kind":"keyword"},{"text":" ","kind":"text"},{"text":"View","kind":"typeIdentifier","preciseIdentifier":"s:15OpenSwiftUICore4ViewP"}],"type":"topic","identifier":"doc:\/\/OpenSwiftUI\/documentation\/OpenSwiftUI\/Ellipse\/background(_:alignment:)","role":"symbol","title":"background(_:alignment:)","url":"\/documentation\/openswiftui\/ellipse\/background(_:alignment:)","kind":"symbol","abstract":[{"type":"text","text":"Layers the given view behind this view."}]},"doc://OpenSwiftUI/documentation/OpenSwiftUI/Ellipse/animation(_:value:)":{"url":"\/documentation\/openswiftui\/ellipse\/animation(_:value:)","role":"symbol","kind":"symbol","type":"topic","title":"animation(_:value:)","identifier":"doc:\/\/OpenSwiftUI\/documentation\/OpenSwiftUI\/Ellipse\/animation(_:value:)","fragments":[{"text":"func","kind":"keyword"},{"text":" ","kind":"text"},{"text":"animation","kind":"identifier"},{"text":"<","kind":"text"},{"text":"V","kind":"genericParameter"},{"text":">(","kind":"text"},{"preciseIdentifier":"s:15OpenSwiftUICore9AnimationV","text":"Animation","kind":"typeIdentifier"},{"text":"?, ","kind":"text"},{"text":"value","kind":"externalParam"},{"text":": ","kind":"text"},{"text":"V","kind":"typeIdentifier"},{"text":") -> ","kind":"text"},{"text":"some","kind":"keyword"},{"text":" ","kind":"text"},{"preciseIdentifier":"s:15OpenSwiftUICore4ViewP","text":"View","kind":"typeIdentifier"}],"abstract":[]},"doc://OpenSwiftUI/documentation/OpenSwiftUI/Ellipse/onDisappear(perform:)":{"title":"onDisappear(perform:)","kind":"symbol","identifier":"doc:\/\/OpenSwiftUI\/documentation\/OpenSwiftUI\/Ellipse\/onDisappear(perform:)","url":"\/documentation\/openswiftui\/ellipse\/ondisappear(perform:)","role":"symbol","type":"topic","fragments":[{"kind":"keyword","text":"func"},{"kind":"text","text":" "},{"kind":"identifier","text":"onDisappear"},{"kind":"text","text":"("},{"kind":"externalParam","text":"perform"},{"kind":"text","text":": (() -> "},{"kind":"typeIdentifier","text":"Void","preciseIdentifier":"s:s4Voida"},{"kind":"text","text":")?) -> "},{"kind":"keyword","text":"some"},{"kind":"text","text":" "},{"kind":"typeIdentifier","text":"View","preciseIdentifier":"s:15OpenSwiftUICore4ViewP"}],"abstract":[{"text":"Adds an action to perform after this view disappears.","type":"text"}]},"doc://OpenSwiftUI/documentation/OpenSwiftUI/Ellipse/fixedSize()":{"identifier":"doc:\/\/OpenSwiftUI\/documentation\/OpenSwiftUI\/Ellipse\/fixedSize()","abstract":[{"type":"text","text":"Fixes this view at its ideal size."}],"title":"fixedSize()","role":"symbol","kind":"symbol","type":"topic","fragments":[{"kind":"keyword","text":"func"},{"kind":"text","text":" "},{"kind":"identifier","text":"fixedSize"},{"kind":"text","text":"() -> "},{"kind":"keyword","text":"some"},{"kind":"text","text":" "},{"kind":"typeIdentifier","preciseIdentifier":"s:15OpenSwiftUICore4ViewP","text":"View"}],"url":"\/documentation\/openswiftui\/ellipse\/fixedsize()"},"doc://OpenSwiftUI/documentation/OpenSwiftUI/Ellipse/animation(_:)":{"identifier":"doc:\/\/OpenSwiftUI\/documentation\/OpenSwiftUI\/Ellipse\/animation(_:)","abstract":[{"text":"Applies the given animation to all animatable values within this view.","type":"text"}],"title":"animation(_:)","role":"symbol","kind":"symbol","type":"topic","deprecated":true,"fragments":[{"text":"func","kind":"keyword"},{"text":" ","kind":"text"},{"text":"animation","kind":"identifier"},{"text":"(","kind":"text"},{"preciseIdentifier":"s:15OpenSwiftUICore9AnimationV","text":"Animation","kind":"typeIdentifier"},{"text":"?) -> ","kind":"text"},{"text":"some","kind":"keyword"},{"text":" ","kind":"text"},{"preciseIdentifier":"s:15OpenSwiftUICore4ViewP","text":"View","kind":"typeIdentifier"}],"url":"\/documentation\/openswiftui\/ellipse\/animation(_:)"},"doc://OpenSwiftUI/documentation/OpenSwiftUI/Ellipse/transformEnvironment(_:transform:)":{"identifier":"doc:\/\/OpenSwiftUI\/documentation\/OpenSwiftUI\/Ellipse\/transformEnvironment(_:transform:)","role":"symbol","fragments":[{"kind":"keyword","text":"func"},{"kind":"text","text":" "},{"kind":"identifier","text":"transformEnvironment"},{"kind":"text","text":"<"},{"kind":"genericParameter","text":"V"},{"kind":"text","text":">("},{"preciseIdentifier":"s:s15WritableKeyPathC","kind":"typeIdentifier","text":"WritableKeyPath"},{"kind":"text","text":"<"},{"preciseIdentifier":"s:15OpenSwiftUICore17EnvironmentValuesV","kind":"typeIdentifier","text":"EnvironmentValues"},{"kind":"text","text":", "},{"kind":"typeIdentifier","text":"V"},{"kind":"text","text":">, "},{"kind":"externalParam","text":"transform"},{"kind":"text","text":": ("},{"kind":"keyword","text":"inout"},{"kind":"text","text":" "},{"kind":"typeIdentifier","text":"V"},{"kind":"text","text":") -> "},{"preciseIdentifier":"s:s4Voida","kind":"typeIdentifier","text":"Void"},{"kind":"text","text":") -> "},{"kind":"keyword","text":"some"},{"kind":"text","text":" "},{"preciseIdentifier":"s:15OpenSwiftUICore4ViewP","kind":"typeIdentifier","text":"View"}],"abstract":[{"text":"Transforms the environment value of the specified key path with the","type":"text"},{"text":" ","type":"text"},{"text":"given function.","type":"text"}],"kind":"symbol","type":"topic","title":"transformEnvironment(_:transform:)","url":"\/documentation\/openswiftui\/ellipse\/transformenvironment(_:transform:)"},"doc://OpenSwiftUI/documentation/OpenSwiftUI/Ellipse/overlay(_:alignment:)":{"identifier":"doc:\/\/OpenSwiftUI\/documentation\/OpenSwiftUI\/Ellipse\/overlay(_:alignment:)","abstract":[{"text":"Layers a secondary view in front of this view.","type":"text"}],"title":"overlay(_:alignment:)","role":"symbol","kind":"symbol","type":"topic","deprecated":true,"fragments":[{"kind":"keyword","text":"func"},{"kind":"text","text":" "},{"kind":"identifier","text":"overlay"},{"kind":"text","text":"<"},{"kind":"genericParameter","text":"Overlay"},{"kind":"text","text":">("},{"kind":"typeIdentifier","text":"Overlay"},{"kind":"text","text":", "},{"kind":"externalParam","text":"alignment"},{"kind":"text","text":": "},{"preciseIdentifier":"s:15OpenSwiftUICore9AlignmentV","kind":"typeIdentifier","text":"Alignment"},{"kind":"text","text":") -> "},{"kind":"keyword","text":"some"},{"kind":"text","text":" "},{"preciseIdentifier":"s:15OpenSwiftUICore4ViewP","kind":"typeIdentifier","text":"View"}],"url":"\/documentation\/openswiftui\/ellipse\/overlay(_:alignment:)"},"doc://OpenSwiftUI/documentation/OpenSwiftUI/Ellipse/rotation3DEffect(_:axis:anchor:anchorZ:perspective:)":{"type":"topic","kind":"symbol","identifier":"doc:\/\/OpenSwiftUI\/documentation\/OpenSwiftUI\/Ellipse\/rotation3DEffect(_:axis:anchor:anchorZ:perspective:)","url":"\/documentation\/openswiftui\/ellipse\/rotation3deffect(_:axis:anchor:anchorz:perspective:)","title":"rotation3DEffect(_:axis:anchor:anchorZ:perspective:)","abstract":[{"text":"Renders a view’s content as if it’s rotated in three dimensions around","type":"text"},{"text":" ","type":"text"},{"text":"the specified axis.","type":"text"}],"fragments":[{"kind":"keyword","text":"func"},{"kind":"text","text":" "},{"kind":"identifier","text":"rotation3DEffect"},{"kind":"text","text":"("},{"kind":"typeIdentifier","text":"Angle","preciseIdentifier":"s:15OpenSwiftUICore5AngleV"},{"kind":"text","text":", "},{"kind":"externalParam","text":"axis"},{"kind":"text","text":": (x"},{"kind":"text","text":": "},{"kind":"typeIdentifier","text":"CGFloat","preciseIdentifier":"s:14CoreFoundation7CGFloatV"},{"kind":"text","text":", y"},{"kind":"text","text":": "},{"kind":"typeIdentifier","text":"CGFloat","preciseIdentifier":"s:14CoreFoundation7CGFloatV"},{"text":", z","kind":"text"},{"text":": ","kind":"text"},{"text":"CGFloat","preciseIdentifier":"s:14CoreFoundation7CGFloatV","kind":"typeIdentifier"},{"text":"), ","kind":"text"},{"text":"anchor","kind":"externalParam"},{"text":": ","kind":"text"},{"text":"UnitPoint","preciseIdentifier":"s:15OpenSwiftUICore9UnitPointV","kind":"typeIdentifier"},{"text":", ","kind":"text"},{"text":"anchorZ","kind":"externalParam"},{"text":": ","kind":"text"},{"text":"CGFloat","preciseIdentifier":"s:14CoreFoundation7CGFloatV","kind":"typeIdentifier"},{"text":", ","kind":"text"},{"text":"perspective","kind":"externalParam"},{"text":": ","kind":"text"},{"text":"CGFloat","preciseIdentifier":"s:14CoreFoundation7CGFloatV","kind":"typeIdentifier"},{"text":") -> ","kind":"text"},{"text":"some","kind":"keyword"},{"text":" ","kind":"text"},{"text":"View","preciseIdentifier":"s:15OpenSwiftUICore4ViewP","kind":"typeIdentifier"}],"role":"symbol"},"doc://OpenSwiftUI/documentation/OpenSwiftUI/Ellipse/frame()":{"title":"frame()","url":"\/documentation\/openswiftui\/ellipse\/frame()","type":"topic","kind":"symbol","role":"symbol","fragments":[{"text":"func","kind":"keyword"},{"text":" ","kind":"text"},{"text":"frame","kind":"identifier"},{"text":"() -> ","kind":"text"},{"text":"some","kind":"keyword"},{"text":" ","kind":"text"},{"preciseIdentifier":"s:15OpenSwiftUICore4ViewP","text":"View","kind":"typeIdentifier"}],"identifier":"doc:\/\/OpenSwiftUI\/documentation\/OpenSwiftUI\/Ellipse\/frame()","abstract":[{"text":"Positions this view within an invisible frame.","type":"text"}],"deprecated":true},"doc://OpenSwiftUI/documentation/OpenSwiftUI/Ellipse":{"abstract":[{"text":"An ellipse aligned inside the frame of the view containing it.","type":"text"}],"navigatorTitle":[{"kind":"identifier","text":"Ellipse"}],"type":"topic","identifier":"doc:\/\/OpenSwiftUI\/documentation\/OpenSwiftUI\/Ellipse","fragments":[{"kind":"keyword","text":"struct"},{"kind":"text","text":" "},{"kind":"identifier","text":"Ellipse"}],"role":"symbol","kind":"symbol","title":"Ellipse","url":"\/documentation\/openswiftui\/ellipse"},"doc://OpenSwiftUI/documentation/OpenSwiftUI/Ellipse/safeAreaInset(edge:alignment:spacing:content:)-58523":{"identifier":"doc:\/\/OpenSwiftUI\/documentation\/OpenSwiftUI\/Ellipse\/safeAreaInset(edge:alignment:spacing:content:)-58523","fragments":[{"kind":"keyword","text":"func"},{"kind":"text","text":" "},{"kind":"identifier","text":"safeAreaInset"},{"kind":"text","text":"<"},{"kind":"genericParameter","text":"V"},{"kind":"text","text":">("},{"kind":"externalParam","text":"edge"},{"kind":"text","text":": "},{"preciseIdentifier":"s:15OpenSwiftUICore12VerticalEdgeO","kind":"typeIdentifier","text":"VerticalEdge"},{"kind":"text","text":", "},{"kind":"externalParam","text":"alignment"},{"kind":"text","text":": "},{"preciseIdentifier":"s:15OpenSwiftUICore19HorizontalAlignmentV","kind":"typeIdentifier","text":"HorizontalAlignment"},{"kind":"text","text":", "},{"kind":"externalParam","text":"spacing"},{"kind":"text","text":": "},{"preciseIdentifier":"s:14CoreFoundation7CGFloatV","kind":"typeIdentifier","text":"CGFloat"},{"kind":"text","text":"?, "},{"kind":"externalParam","text":"content"},{"kind":"text","text":": () -> "},{"kind":"typeIdentifier","text":"V"},{"kind":"text","text":") -> "},{"kind":"keyword","text":"some"},{"kind":"text","text":" "},{"preciseIdentifier":"s:15OpenSwiftUICore4ViewP","kind":"typeIdentifier","text":"View"}],"type":"topic","title":"safeAreaInset(edge:alignment:spacing:content:)","url":"\/documentation\/openswiftui\/ellipse\/safeareainset(edge:alignment:spacing:content:)-58523","role":"symbol","abstract":[{"text":"Shows the specified content above or below the modified view.","type":"text"}],"kind":"symbol"},"doc://OpenSwiftUI/documentation/OpenSwiftUI/Ellipse/offset(_:)":{"identifier":"doc:\/\/OpenSwiftUI\/documentation\/OpenSwiftUI\/Ellipse\/offset(_:)","abstract":[{"text":"Offset this view by the horizontal and vertical amount specified in the","type":"text"},{"text":" ","type":"text"},{"text":"offset parameter.","type":"text"}],"title":"offset(_:)","role":"symbol","type":"topic","kind":"symbol","fragments":[{"kind":"keyword","text":"func"},{"kind":"text","text":" "},{"kind":"identifier","text":"offset"},{"kind":"text","text":"("},{"kind":"typeIdentifier","text":"CGSize","preciseIdentifier":"c:@S@CGSize"},{"kind":"text","text":") -> "},{"kind":"keyword","text":"some"},{"kind":"text","text":" "},{"kind":"typeIdentifier","text":"View","preciseIdentifier":"s:15OpenSwiftUICore4ViewP"}],"url":"\/documentation\/openswiftui\/ellipse\/offset(_:)"},"doc://OpenSwiftUI/documentation/OpenSwiftUI/Ellipse/preference(key:value:)":{"identifier":"doc:\/\/OpenSwiftUI\/documentation\/OpenSwiftUI\/Ellipse\/preference(key:value:)","fragments":[{"text":"func","kind":"keyword"},{"text":" ","kind":"text"},{"text":"preference","kind":"identifier"},{"text":"<","kind":"text"},{"text":"K","kind":"genericParameter"},{"text":">(","kind":"text"},{"text":"key","kind":"externalParam"},{"text":": ","kind":"text"},{"text":"K","kind":"typeIdentifier"},{"text":".Type, ","kind":"text"},{"text":"value","kind":"externalParam"},{"text":": ","kind":"text"},{"text":"K","kind":"typeIdentifier"},{"text":".","kind":"text"},{"preciseIdentifier":"s:15OpenSwiftUICore13PreferenceKeyP5ValueQa","text":"Value","kind":"typeIdentifier"},{"text":") -> ","kind":"text"},{"text":"some","kind":"keyword"},{"text":" ","kind":"text"},{"preciseIdentifier":"s:15OpenSwiftUICore4ViewP","text":"View","kind":"typeIdentifier"}],"url":"\/documentation\/openswiftui\/ellipse\/preference(key:value:)","title":"preference(key:value:)","role":"symbol","type":"topic","kind":"symbol","abstract":[{"type":"text","text":"Sets a value for the given preference."}]},"doc://OpenSwiftUI/documentation/OpenSwiftUI/Ellipse/environmentObject(_:)":{"identifier":"doc:\/\/OpenSwiftUI\/documentation\/OpenSwiftUI\/Ellipse\/environmentObject(_:)","fragments":[{"kind":"keyword","text":"func"},{"kind":"text","text":" "},{"kind":"identifier","text":"environmentObject"},{"kind":"text","text":"<"},{"kind":"genericParameter","text":"T"},{"kind":"text","text":">("},{"kind":"typeIdentifier","text":"T"},{"kind":"text","text":") -> "},{"kind":"keyword","text":"some"},{"kind":"text","text":" "},{"kind":"typeIdentifier","preciseIdentifier":"s:15OpenSwiftUICore4ViewP","text":"View"}],"type":"topic","title":"environmentObject(_:)","url":"\/documentation\/openswiftui\/ellipse\/environmentobject(_:)","role":"symbol","abstract":[{"type":"text","text":"Supplies an observable object to a view’s hierarchy."}],"kind":"symbol"},"doc://OpenSwiftUI/documentation/OpenSwiftUI/Ellipse/geometryGroup()":{"url":"\/documentation\/openswiftui\/ellipse\/geometrygroup()","role":"symbol","identifier":"doc:\/\/OpenSwiftUI\/documentation\/OpenSwiftUI\/Ellipse\/geometryGroup()","type":"topic","title":"geometryGroup()","kind":"symbol","abstract":[{"type":"text","text":"Isolates the geometry (e.g. position and size) of the view"},{"text":" ","type":"text"},{"text":"from its parent view.","type":"text"}],"fragments":[{"kind":"keyword","text":"func"},{"kind":"text","text":" "},{"kind":"identifier","text":"geometryGroup"},{"kind":"text","text":"() -> "},{"kind":"keyword","text":"some"},{"kind":"text","text":" "},{"kind":"typeIdentifier","text":"View","preciseIdentifier":"s:15OpenSwiftUICore4ViewP"}]},"doc://OpenSwiftUI/documentation/OpenSwiftUI/Ellipse/environment(_:)":{"abstract":[{"type":"text","text":"Places an observable object in the view’s environment."}],"type":"topic","url":"\/documentation\/openswiftui\/ellipse\/environment(_:)","identifier":"doc:\/\/OpenSwiftUI\/documentation\/OpenSwiftUI\/Ellipse\/environment(_:)","title":"environment(_:)","kind":"symbol","role":"symbol","fragments":[{"kind":"keyword","text":"func"},{"kind":"text","text":" "},{"kind":"identifier","text":"environment"},{"kind":"text","text":"<"},{"kind":"genericParameter","text":"T"},{"kind":"text","text":">("},{"kind":"typeIdentifier","text":"T"},{"kind":"text","text":"?) -> "},{"kind":"keyword","text":"some"},{"kind":"text","text":" "},{"kind":"typeIdentifier","text":"View","preciseIdentifier":"s:15OpenSwiftUICore4ViewP"}]},"doc://OpenSwiftUI/documentation/OpenSwiftUI/Ellipse/frame(minWidth:idealWidth:maxWidth:minHeight:idealHeight:maxHeight:alignment:)":{"role":"symbol","title":"frame(minWidth:idealWidth:maxWidth:minHeight:idealHeight:maxHeight:alignment:)","fragments":[{"text":"func","kind":"keyword"},{"text":" ","kind":"text"},{"text":"frame","kind":"identifier"},{"text":"(","kind":"text"},{"text":"minWidth","kind":"externalParam"},{"text":": ","kind":"text"},{"preciseIdentifier":"s:14CoreFoundation7CGFloatV","text":"CGFloat","kind":"typeIdentifier"},{"text":"?, ","kind":"text"},{"text":"idealWidth","kind":"externalParam"},{"text":": ","kind":"text"},{"preciseIdentifier":"s:14CoreFoundation7CGFloatV","text":"CGFloat","kind":"typeIdentifier"},{"text":"?, ","kind":"text"},{"text":"maxWidth","kind":"externalParam"},{"text":": ","kind":"text"},{"preciseIdentifier":"s:14CoreFoundation7CGFloatV","text":"CGFloat","kind":"typeIdentifier"},{"text":"?, ","kind":"text"},{"text":"minHeight","kind":"externalParam"},{"text":": ","kind":"text"},{"preciseIdentifier":"s:14CoreFoundation7CGFloatV","text":"CGFloat","kind":"typeIdentifier"},{"text":"?, ","kind":"text"},{"text":"idealHeight","kind":"externalParam"},{"text":": ","kind":"text"},{"preciseIdentifier":"s:14CoreFoundation7CGFloatV","text":"CGFloat","kind":"typeIdentifier"},{"text":"?, ","kind":"text"},{"text":"maxHeight","kind":"externalParam"},{"text":": ","kind":"text"},{"preciseIdentifier":"s:14CoreFoundation7CGFloatV","text":"CGFloat","kind":"typeIdentifier"},{"text":"?, ","kind":"text"},{"text":"alignment","kind":"externalParam"},{"text":": ","kind":"text"},{"preciseIdentifier":"s:15OpenSwiftUICore9AlignmentV","text":"Alignment","kind":"typeIdentifier"},{"text":") -> ","kind":"text"},{"text":"some","kind":"keyword"},{"text":" ","kind":"text"},{"preciseIdentifier":"s:15OpenSwiftUICore4ViewP","text":"View","kind":"typeIdentifier"}],"identifier":"doc:\/\/OpenSwiftUI\/documentation\/OpenSwiftUI\/Ellipse\/frame(minWidth:idealWidth:maxWidth:minHeight:idealHeight:maxHeight:alignment:)","abstract":[{"type":"text","text":"Positions this view within an invisible frame having the specified size"},{"type":"text","text":" "},{"type":"text","text":"constraints."}],"url":"\/documentation\/openswiftui\/ellipse\/frame(minwidth:idealwidth:maxwidth:minheight:idealheight:maxheight:alignment:)","type":"topic","kind":"symbol"},"doc://OpenSwiftUI/documentation/OpenSwiftUI/Ellipse/cornerRadius(_:antialiased:)":{"type":"topic","title":"cornerRadius(_:antialiased:)","deprecated":true,"abstract":[{"text":"Clips this view to its bounding frame, with the specified corner radius.","type":"text"}],"kind":"symbol","identifier":"doc:\/\/OpenSwiftUI\/documentation\/OpenSwiftUI\/Ellipse\/cornerRadius(_:antialiased:)","role":"symbol","url":"\/documentation\/openswiftui\/ellipse\/cornerradius(_:antialiased:)","fragments":[{"text":"func","kind":"keyword"},{"text":" ","kind":"text"},{"text":"cornerRadius","kind":"identifier"},{"text":"(","kind":"text"},{"preciseIdentifier":"s:14CoreFoundation7CGFloatV","text":"CGFloat","kind":"typeIdentifier"},{"text":", ","kind":"text"},{"text":"antialiased","kind":"externalParam"},{"text":": ","kind":"text"},{"preciseIdentifier":"s:Sb","text":"Bool","kind":"typeIdentifier"},{"text":") -> ","kind":"text"},{"text":"some","kind":"keyword"},{"text":" ","kind":"text"},{"preciseIdentifier":"s:15OpenSwiftUICore4ViewP","text":"View","kind":"typeIdentifier"}]},"doc://OpenSwiftUI/documentation/OpenSwiftUI/Ellipse/zIndex(_:)":{"type":"topic","title":"zIndex(_:)","abstract":[{"text":"Controls the display order of overlapping views.","type":"text"}],"kind":"symbol","identifier":"doc:\/\/OpenSwiftUI\/documentation\/OpenSwiftUI\/Ellipse\/zIndex(_:)","role":"symbol","url":"\/documentation\/openswiftui\/ellipse\/zindex(_:)","fragments":[{"kind":"keyword","text":"func"},{"kind":"text","text":" "},{"kind":"identifier","text":"zIndex"},{"kind":"text","text":"("},{"preciseIdentifier":"s:Sd","kind":"typeIdentifier","text":"Double"},{"kind":"text","text":") -> "},{"kind":"keyword","text":"some"},{"kind":"text","text":" "},{"preciseIdentifier":"s:15OpenSwiftUICore4ViewP","kind":"typeIdentifier","text":"View"}]},"doc://OpenSwiftUI/documentation/OpenSwiftUI/Ellipse/animation(_:body:)":{"title":"animation(_:body:)","kind":"symbol","type":"topic","fragments":[{"text":"func","kind":"keyword"},{"text":" ","kind":"text"},{"text":"animation","kind":"identifier"},{"text":"<","kind":"text"},{"text":"V","kind":"genericParameter"},{"text":">(","kind":"text"},{"text":"Animation","kind":"typeIdentifier","preciseIdentifier":"s:15OpenSwiftUICore9AnimationV"},{"text":"?, ","kind":"text"},{"text":"body","kind":"externalParam"},{"text":": (","kind":"text"},{"text":"PlaceholderContentView","kind":"typeIdentifier","preciseIdentifier":"s:15OpenSwiftUICore22PlaceholderContentViewV"},{"text":"<","kind":"text"},{"text":"Self","kind":"typeIdentifier"},{"text":">) -> ","kind":"text"},{"text":"V","kind":"typeIdentifier"},{"text":") -> ","kind":"text"},{"text":"some","kind":"keyword"},{"text":" ","kind":"text"},{"text":"View","kind":"typeIdentifier","preciseIdentifier":"s:15OpenSwiftUICore4ViewP"}],"identifier":"doc:\/\/OpenSwiftUI\/documentation\/OpenSwiftUI\/Ellipse\/animation(_:body:)","role":"symbol","url":"\/documentation\/openswiftui\/ellipse\/animation(_:body:)","abstract":[{"type":"text","text":"Applies the given animation to all animatable values within the "},{"type":"codeVoice","code":"body"},{"type":"text","text":" "},{"type":"text","text":"closure."}]},"doc://OpenSwiftUI/documentation/OpenSwiftUI":{"kind":"symbol","identifier":"doc:\/\/OpenSwiftUI\/documentation\/OpenSwiftUI","abstract":[{"type":"text","text":"Declare the user interface and behavior for your app on every platform."}],"url":"\/documentation\/openswiftui","type":"topic","title":"OpenSwiftUI","role":"collection"},"doc://OpenSwiftUI/documentation/OpenSwiftUI/Ellipse/disabled(_:)-4hz7c":{"abstract":[{"text":"Adds a condition that controls whether users can interact with this","type":"text"},{"text":" ","type":"text"},{"text":"view.","type":"text"}],"type":"topic","url":"\/documentation\/openswiftui\/ellipse\/disabled(_:)-4hz7c","identifier":"doc:\/\/OpenSwiftUI\/documentation\/OpenSwiftUI\/Ellipse\/disabled(_:)-4hz7c","title":"disabled(_:)","kind":"symbol","role":"symbol","fragments":[{"kind":"keyword","text":"func"},{"kind":"text","text":" "},{"kind":"identifier","text":"disabled"},{"kind":"text","text":"("},{"kind":"typeIdentifier","preciseIdentifier":"s:Sb","text":"Bool"},{"kind":"text","text":") -> "},{"kind":"keyword","text":"some"},{"kind":"text","text":" "},{"kind":"typeIdentifier","preciseIdentifier":"s:15OpenSwiftUICore4ViewP","text":"View"}]},"doc://OpenSwiftUI/documentation/OpenSwiftUI/Ellipse/transformPreference(_:_:)":{"type":"topic","title":"transformPreference(_:_:)","url":"\/documentation\/openswiftui\/ellipse\/transformpreference(_:_:)","abstract":[],"kind":"symbol","role":"symbol","fragments":[{"text":"func","kind":"keyword"},{"text":" ","kind":"text"},{"text":"transformPreference","kind":"identifier"},{"text":"<","kind":"text"},{"text":"K","kind":"genericParameter"},{"text":">(","kind":"text"},{"text":"K","kind":"typeIdentifier"},{"text":".Type, (","kind":"text"},{"text":"inout","kind":"keyword"},{"text":" ","kind":"text"},{"text":"K","kind":"typeIdentifier"},{"text":".","kind":"text"},{"preciseIdentifier":"s:15OpenSwiftUICore13PreferenceKeyP5ValueQa","text":"Value","kind":"typeIdentifier"},{"text":") -> ","kind":"text"},{"preciseIdentifier":"s:s4Voida","text":"Void","kind":"typeIdentifier"},{"text":") -> ","kind":"text"},{"text":"some","kind":"keyword"},{"text":" ","kind":"text"},{"preciseIdentifier":"s:15OpenSwiftUICore4ViewP","text":"View","kind":"typeIdentifier"}],"identifier":"doc:\/\/OpenSwiftUI\/documentation\/OpenSwiftUI\/Ellipse\/transformPreference(_:_:)"},"doc://OpenSwiftUI/documentation/OpenSwiftUI/Ellipse/layoutValue(key:value:)":{"abstract":[{"type":"text","text":"Associates a value with a custom layout property."}],"kind":"symbol","title":"layoutValue(key:value:)","url":"\/documentation\/openswiftui\/ellipse\/layoutvalue(key:value:)","identifier":"doc:\/\/OpenSwiftUI\/documentation\/OpenSwiftUI\/Ellipse\/layoutValue(key:value:)","role":"symbol","type":"topic","fragments":[{"kind":"keyword","text":"func"},{"kind":"text","text":" "},{"kind":"identifier","text":"layoutValue"},{"kind":"text","text":"<"},{"kind":"genericParameter","text":"K"},{"kind":"text","text":">("},{"kind":"externalParam","text":"key"},{"kind":"text","text":": "},{"kind":"typeIdentifier","text":"K"},{"kind":"text","text":".Type, "},{"kind":"externalParam","text":"value"},{"kind":"text","text":": "},{"kind":"typeIdentifier","text":"K"},{"text":".","kind":"text"},{"text":"Value","preciseIdentifier":"s:15OpenSwiftUICore14LayoutValueKeyP0E0Qa","kind":"typeIdentifier"},{"text":") -> ","kind":"text"},{"text":"some","kind":"keyword"},{"text":" ","kind":"text"},{"text":"View","preciseIdentifier":"s:15OpenSwiftUICore4ViewP","kind":"typeIdentifier"}]},"doc://OpenSwiftUI/documentation/OpenSwiftUI/Ellipse/overlay(alignment:content:)":{"kind":"symbol","type":"topic","identifier":"doc:\/\/OpenSwiftUI\/documentation\/OpenSwiftUI\/Ellipse\/overlay(alignment:content:)","url":"\/documentation\/openswiftui\/ellipse\/overlay(alignment:content:)","title":"overlay(alignment:content:)","abstract":[{"type":"text","text":"Layers the views that you specify in front of this view."}],"fragments":[{"text":"func","kind":"keyword"},{"text":" ","kind":"text"},{"text":"overlay","kind":"identifier"},{"text":"<","kind":"text"},{"text":"V","kind":"genericParameter"},{"text":">(","kind":"text"},{"text":"alignment","kind":"externalParam"},{"text":": ","kind":"text"},{"preciseIdentifier":"s:15OpenSwiftUICore9AlignmentV","text":"Alignment","kind":"typeIdentifier"},{"text":", ","kind":"text"},{"text":"content","kind":"externalParam"},{"text":": () -> ","kind":"text"},{"text":"V","kind":"typeIdentifier"},{"text":") -> ","kind":"text"},{"text":"some","kind":"keyword"},{"text":" ","kind":"text"},{"preciseIdentifier":"s:15OpenSwiftUICore4ViewP","text":"View","kind":"typeIdentifier"}],"role":"symbol"},"doc://OpenSwiftUI/documentation/OpenSwiftUI/Ellipse/fixedSize(horizontal:vertical:)":{"abstract":[{"type":"text","text":"Fixes this view at its ideal size in the specified dimensions."}],"kind":"symbol","title":"fixedSize(horizontal:vertical:)","url":"\/documentation\/openswiftui\/ellipse\/fixedsize(horizontal:vertical:)","identifier":"doc:\/\/OpenSwiftUI\/documentation\/OpenSwiftUI\/Ellipse\/fixedSize(horizontal:vertical:)","role":"symbol","type":"topic","fragments":[{"kind":"keyword","text":"func"},{"kind":"text","text":" "},{"kind":"identifier","text":"fixedSize"},{"kind":"text","text":"("},{"kind":"externalParam","text":"horizontal"},{"kind":"text","text":": "},{"kind":"typeIdentifier","text":"Bool","preciseIdentifier":"s:Sb"},{"kind":"text","text":", "},{"kind":"externalParam","text":"vertical"},{"kind":"text","text":": "},{"kind":"typeIdentifier","text":"Bool","preciseIdentifier":"s:Sb"},{"kind":"text","text":") -> "},{"kind":"keyword","text":"some"},{"text":" ","kind":"text"},{"text":"View","preciseIdentifier":"s:15OpenSwiftUICore4ViewP","kind":"typeIdentifier"}]},"doc://OpenSwiftUI/documentation/OpenSwiftUI/Ellipse/task(id:priority:_:)":{"title":"task(id:priority:_:)","url":"\/documentation\/openswiftui\/ellipse\/task(id:priority:_:)","abstract":[{"text":"Adds a task to perform before this view appears or when a specified","type":"text"},{"text":" ","type":"text"},{"text":"value changes.","type":"text"}],"kind":"symbol","type":"topic","fragments":[{"text":"func","kind":"keyword"},{"text":" ","kind":"text"},{"text":"task","kind":"identifier"},{"text":"<","kind":"text"},{"text":"T","kind":"genericParameter"},{"text":">(","kind":"text"},{"text":"id","kind":"externalParam"},{"text":": ","kind":"text"},{"text":"T","preciseIdentifier":"s:15OpenSwiftUICore4ViewP0aB2UIE4task2id8priority_Qrqd___ScPyyYaYbctSQRd__lFQO1Tqd__mfp","kind":"typeIdentifier"},{"text":", ","kind":"text"},{"text":"priority","kind":"externalParam"},{"text":": ","kind":"text"},{"text":"TaskPriority","preciseIdentifier":"s:ScP","kind":"typeIdentifier"},{"text":", () ","kind":"text"},{"text":"async","kind":"keyword"},{"text":" -> ","kind":"text"},{"text":"Void","preciseIdentifier":"s:s4Voida","kind":"typeIdentifier"},{"text":") -> ","kind":"text"},{"text":"some","kind":"keyword"},{"text":" ","kind":"text"},{"text":"View","preciseIdentifier":"s:15OpenSwiftUICore4ViewP","kind":"typeIdentifier"}],"role":"symbol","identifier":"doc:\/\/OpenSwiftUI\/documentation\/OpenSwiftUI\/Ellipse\/task(id:priority:_:)"},"doc://OpenSwiftUI/documentation/OpenSwiftUI/Ellipse/onChange(of:initial:_:)-8yyep":{"title":"onChange(of:initial:_:)","url":"\/documentation\/openswiftui\/ellipse\/onchange(of:initial:_:)-8yyep","kind":"symbol","role":"symbol","fragments":[{"text":"func","kind":"keyword"},{"text":" ","kind":"text"},{"text":"onChange","kind":"identifier"},{"text":"<","kind":"text"},{"text":"V","kind":"genericParameter"},{"text":">(","kind":"text"},{"text":"of","kind":"externalParam"},{"text":": ","kind":"text"},{"text":"V","kind":"typeIdentifier"},{"text":", ","kind":"text"},{"text":"initial","kind":"externalParam"},{"text":": ","kind":"text"},{"text":"Bool","kind":"typeIdentifier","preciseIdentifier":"s:Sb"},{"text":", (","kind":"text"},{"text":"V","kind":"typeIdentifier"},{"text":", ","kind":"text"},{"text":"V","kind":"typeIdentifier"},{"text":") -> ","kind":"text"},{"text":"Void","kind":"typeIdentifier","preciseIdentifier":"s:s4Voida"},{"text":") -> ","kind":"text"},{"text":"some","kind":"keyword"},{"text":" ","kind":"text"},{"text":"View","kind":"typeIdentifier","preciseIdentifier":"s:15OpenSwiftUICore4ViewP"}],"identifier":"doc:\/\/OpenSwiftUI\/documentation\/OpenSwiftUI\/Ellipse\/onChange(of:initial:_:)-8yyep","abstract":[{"text":"Adds a modifier for this view that fires an action when a specific","type":"text"},{"text":" ","type":"text"},{"text":"value changes.","type":"text"}],"type":"topic"},"doc://OpenSwiftUI/documentation/OpenSwiftUI/Ellipse/frame(width:height:alignment:)":{"url":"\/documentation\/openswiftui\/ellipse\/frame(width:height:alignment:)","title":"frame(width:height:alignment:)","role":"symbol","fragments":[{"text":"func","kind":"keyword"},{"text":" ","kind":"text"},{"text":"frame","kind":"identifier"},{"text":"(","kind":"text"},{"text":"width","kind":"externalParam"},{"text":": ","kind":"text"},{"preciseIdentifier":"s:14CoreFoundation7CGFloatV","text":"CGFloat","kind":"typeIdentifier"},{"text":"?, ","kind":"text"},{"text":"height","kind":"externalParam"},{"text":": ","kind":"text"},{"preciseIdentifier":"s:14CoreFoundation7CGFloatV","text":"CGFloat","kind":"typeIdentifier"},{"text":"?, ","kind":"text"},{"text":"alignment","kind":"externalParam"},{"text":": ","kind":"text"},{"preciseIdentifier":"s:15OpenSwiftUICore9AlignmentV","text":"Alignment","kind":"typeIdentifier"},{"text":") -> ","kind":"text"},{"text":"some","kind":"keyword"},{"text":" ","kind":"text"},{"preciseIdentifier":"s:15OpenSwiftUICore4ViewP","text":"View","kind":"typeIdentifier"}],"identifier":"doc:\/\/OpenSwiftUI\/documentation\/OpenSwiftUI\/Ellipse\/frame(width:height:alignment:)","type":"topic","kind":"symbol","abstract":[{"type":"text","text":"Positions this view within an invisible frame with the specified size."}]},"doc://OpenSwiftUI/documentation/OpenSwiftUI/Ellipse/onChange(of:initial:_:)-6gyuv":{"url":"\/documentation\/openswiftui\/ellipse\/onchange(of:initial:_:)-6gyuv","title":"onChange(of:initial:_:)","role":"symbol","fragments":[{"kind":"keyword","text":"func"},{"kind":"text","text":" "},{"kind":"identifier","text":"onChange"},{"kind":"text","text":"<"},{"kind":"genericParameter","text":"V"},{"kind":"text","text":">("},{"kind":"externalParam","text":"of"},{"kind":"text","text":": "},{"kind":"typeIdentifier","text":"V"},{"kind":"text","text":", "},{"kind":"externalParam","text":"initial"},{"kind":"text","text":": "},{"kind":"typeIdentifier","text":"Bool","preciseIdentifier":"s:Sb"},{"kind":"text","text":", () -> "},{"kind":"typeIdentifier","preciseIdentifier":"s:s4Voida","text":"Void"},{"kind":"text","text":") -> "},{"kind":"keyword","text":"some"},{"kind":"text","text":" "},{"kind":"typeIdentifier","preciseIdentifier":"s:15OpenSwiftUICore4ViewP","text":"View"}],"identifier":"doc:\/\/OpenSwiftUI\/documentation\/OpenSwiftUI\/Ellipse\/onChange(of:initial:_:)-6gyuv","type":"topic","kind":"symbol","abstract":[{"type":"text","text":"Adds a modifier for this view that fires an action when a specific"},{"type":"text","text":" "},{"type":"text","text":"value changes."}]},"doc://OpenSwiftUI/documentation/OpenSwiftUI/Ellipse/clipShape(_:style:)":{"url":"\/documentation\/openswiftui\/ellipse\/clipshape(_:style:)","title":"clipShape(_:style:)","role":"symbol","fragments":[{"kind":"keyword","text":"func"},{"kind":"text","text":" "},{"kind":"identifier","text":"clipShape"},{"kind":"text","text":"<"},{"kind":"genericParameter","text":"S"},{"kind":"text","text":">("},{"kind":"typeIdentifier","text":"S"},{"kind":"text","text":", "},{"kind":"externalParam","text":"style"},{"kind":"text","text":": "},{"kind":"typeIdentifier","preciseIdentifier":"s:15OpenSwiftUICore9FillStyleV","text":"FillStyle"},{"kind":"text","text":") -> "},{"kind":"keyword","text":"some"},{"kind":"text","text":" "},{"kind":"typeIdentifier","preciseIdentifier":"s:15OpenSwiftUICore4ViewP","text":"View"}],"identifier":"doc:\/\/OpenSwiftUI\/documentation\/OpenSwiftUI\/Ellipse\/clipShape(_:style:)","type":"topic","kind":"symbol","abstract":[{"text":"Sets a clipping shape for this view.","type":"text"}]},"doc://OpenSwiftUI/documentation/OpenSwiftUI/Ellipse/task(priority:_:)":{"role":"symbol","identifier":"doc:\/\/OpenSwiftUI\/documentation\/OpenSwiftUI\/Ellipse\/task(priority:_:)","type":"topic","abstract":[{"text":"Adds an asynchronous task to perform before this view appears.","type":"text"}],"fragments":[{"text":"func","kind":"keyword"},{"text":" ","kind":"text"},{"text":"task","kind":"identifier"},{"text":"(","kind":"text"},{"text":"priority","kind":"externalParam"},{"text":": ","kind":"text"},{"preciseIdentifier":"s:ScP","text":"TaskPriority","kind":"typeIdentifier"},{"text":", () ","kind":"text"},{"text":"async","kind":"keyword"},{"text":" -> ","kind":"text"},{"preciseIdentifier":"s:s4Voida","text":"Void","kind":"typeIdentifier"},{"text":") -> ","kind":"text"},{"text":"some","kind":"keyword"},{"kind":"text","text":" "},{"kind":"typeIdentifier","preciseIdentifier":"s:15OpenSwiftUICore4ViewP","text":"View"}],"kind":"symbol","url":"\/documentation\/openswiftui\/ellipse\/task(priority:_:)","title":"task(priority:_:)"},"doc://OpenSwiftUI/documentation/OpenSwiftUI/Ellipse/padding(_:)-2db3t":{"role":"symbol","identifier":"doc:\/\/OpenSwiftUI\/documentation\/OpenSwiftUI\/Ellipse\/padding(_:)-2db3t","type":"topic","abstract":[{"type":"text","text":"Adds a different padding amount to each edge of this view."}],"fragments":[{"text":"func","kind":"keyword"},{"text":" ","kind":"text"},{"text":"padding","kind":"identifier"},{"text":"(","kind":"text"},{"text":"EdgeInsets","preciseIdentifier":"s:15OpenSwiftUICore10EdgeInsetsV","kind":"typeIdentifier"},{"text":") -> ","kind":"text"},{"text":"some","kind":"keyword"},{"text":" ","kind":"text"},{"text":"View","preciseIdentifier":"s:15OpenSwiftUICore4ViewP","kind":"typeIdentifier"}],"kind":"symbol","url":"\/documentation\/openswiftui\/ellipse\/padding(_:)-2db3t","title":"padding(_:)"},"doc://OpenSwiftUI/documentation/OpenSwiftUI/Ellipse/disabled(_:)-6fkwb":{"title":"disabled(_:)","url":"\/documentation\/openswiftui\/ellipse\/disabled(_:)-6fkwb","identifier":"doc:\/\/OpenSwiftUI\/documentation\/OpenSwiftUI\/Ellipse\/disabled(_:)-6fkwb","fragments":[{"text":"func","kind":"keyword"},{"text":" ","kind":"text"},{"text":"disabled","kind":"identifier"},{"text":"(","kind":"text"},{"text":"Bool","kind":"typeIdentifier","preciseIdentifier":"s:Sb"},{"text":") -> ","kind":"text"},{"text":"some","kind":"keyword"},{"text":" ","kind":"text"},{"text":"View","kind":"typeIdentifier","preciseIdentifier":"s:15OpenSwiftUICore4ViewP"}],"kind":"symbol","role":"symbol","abstract":[{"type":"text","text":"Adds a condition that controls whether users can interact with this"},{"type":"text","text":" "},{"type":"text","text":"view."}],"type":"topic"},"doc://OpenSwiftUI/documentation/OpenSwiftUI/Ellipse/id(_:)":{"role":"symbol","identifier":"doc:\/\/OpenSwiftUI\/documentation\/OpenSwiftUI\/Ellipse\/id(_:)","type":"topic","abstract":[{"text":"Binds a view’s identity to the given proxy value.","type":"text"}],"fragments":[{"text":"func","kind":"keyword"},{"text":" ","kind":"text"},{"text":"id","kind":"identifier"},{"text":"<","kind":"text"},{"text":"ID","kind":"genericParameter"},{"text":">(","kind":"text"},{"text":"ID","kind":"typeIdentifier"},{"text":") -> ","kind":"text"},{"text":"some","kind":"keyword"},{"text":" ","kind":"text"},{"text":"View","preciseIdentifier":"s:15OpenSwiftUICore4ViewP","kind":"typeIdentifier"}],"kind":"symbol","url":"\/documentation\/openswiftui\/ellipse\/id(_:)","title":"id(_:)"},"doc://OpenSwiftUI/documentation/OpenSwiftUI/Ellipse/safeAreaPadding(_:)-5nk70":{"kind":"symbol","type":"topic","url":"\/documentation\/openswiftui\/ellipse\/safeareapadding(_:)-5nk70","identifier":"doc:\/\/OpenSwiftUI\/documentation\/OpenSwiftUI\/Ellipse\/safeAreaPadding(_:)-5nk70","title":"safeAreaPadding(_:)","abstract":[{"text":"Adds the provided insets into the safe area of this view.","type":"text"}],"fragments":[{"text":"func","kind":"keyword"},{"text":" ","kind":"text"},{"text":"safeAreaPadding","kind":"identifier"},{"text":"(","kind":"text"},{"text":"EdgeInsets","preciseIdentifier":"s:15OpenSwiftUICore10EdgeInsetsV","kind":"typeIdentifier"},{"text":") -> ","kind":"text"},{"text":"some","kind":"keyword"},{"text":" ","kind":"text"},{"text":"View","preciseIdentifier":"s:15OpenSwiftUICore4ViewP","kind":"typeIdentifier"}],"role":"symbol"},"doc://OpenSwiftUI/documentation/OpenSwiftUI/Ellipse/transaction(value:_:)":{"role":"symbol","url":"\/documentation\/openswiftui\/ellipse\/transaction(value:_:)","type":"topic","abstract":[{"text":"Applies the given transaction mutation function to all animations used","type":"text"},{"text":" ","type":"text"},{"text":"within the view.","type":"text"}],"title":"transaction(value:_:)","kind":"symbol","identifier":"doc:\/\/OpenSwiftUI\/documentation\/OpenSwiftUI\/Ellipse\/transaction(value:_:)","fragments":[{"text":"func","kind":"keyword"},{"text":" ","kind":"text"},{"text":"transaction","kind":"identifier"},{"text":"(","kind":"text"},{"text":"value","kind":"externalParam"},{"text":": ","kind":"text"},{"text":"some","kind":"keyword"},{"text":" ","kind":"text"},{"text":"Equatable","preciseIdentifier":"s:SQ","kind":"typeIdentifier"},{"text":", (","kind":"text"},{"text":"inout","kind":"keyword"},{"text":" ","kind":"text"},{"text":"Transaction","preciseIdentifier":"s:15OpenSwiftUICore11TransactionV","kind":"typeIdentifier"},{"text":") -> ","kind":"text"},{"text":"Void","preciseIdentifier":"s:s4Voida","kind":"typeIdentifier"},{"text":") -> ","kind":"text"},{"text":"some","kind":"keyword"},{"text":" ","kind":"text"},{"text":"View","preciseIdentifier":"s:15OpenSwiftUICore4ViewP","kind":"typeIdentifier"}]},"doc://OpenSwiftUI/documentation/OpenSwiftUI/Ellipse/clipped(antialiased:)":{"role":"symbol","url":"\/documentation\/openswiftui\/ellipse\/clipped(antialiased:)","type":"topic","abstract":[{"type":"text","text":"Clips this view to its bounding rectangular frame."}],"title":"clipped(antialiased:)","kind":"symbol","identifier":"doc:\/\/OpenSwiftUI\/documentation\/OpenSwiftUI\/Ellipse\/clipped(antialiased:)","fragments":[{"text":"func","kind":"keyword"},{"text":" ","kind":"text"},{"text":"clipped","kind":"identifier"},{"text":"(","kind":"text"},{"text":"antialiased","kind":"externalParam"},{"text":": ","kind":"text"},{"text":"Bool","preciseIdentifier":"s:Sb","kind":"typeIdentifier"},{"text":") -> ","kind":"text"},{"text":"some","kind":"keyword"},{"text":" ","kind":"text"},{"text":"View","preciseIdentifier":"s:15OpenSwiftUICore4ViewP","kind":"typeIdentifier"}]},"doc://OpenSwiftUI/documentation/OpenSwiftUI/Ellipse/environment(_:_:)":{"identifier":"doc:\/\/OpenSwiftUI\/documentation\/OpenSwiftUI\/Ellipse\/environment(_:_:)","role":"symbol","url":"\/documentation\/openswiftui\/ellipse\/environment(_:_:)","fragments":[{"text":"func","kind":"keyword"},{"text":" ","kind":"text"},{"text":"environment","kind":"identifier"},{"text":"<","kind":"text"},{"text":"V","kind":"genericParameter"},{"text":">(","kind":"text"},{"text":"WritableKeyPath","preciseIdentifier":"s:s15WritableKeyPathC","kind":"typeIdentifier"},{"text":"<","kind":"text"},{"text":"EnvironmentValues","preciseIdentifier":"s:15OpenSwiftUICore17EnvironmentValuesV","kind":"typeIdentifier"},{"text":", ","kind":"text"},{"text":"V","kind":"typeIdentifier"},{"text":">, ","kind":"text"},{"text":"V","kind":"typeIdentifier"},{"text":") -> ","kind":"text"},{"text":"some","kind":"keyword"},{"text":" ","kind":"text"},{"text":"View","preciseIdentifier":"s:15OpenSwiftUICore4ViewP","kind":"typeIdentifier"}],"title":"environment(_:_:)","abstract":[{"text":"Sets the environment value of the specified key path to the given value.","type":"text"}],"kind":"symbol","type":"topic"},"doc://OpenSwiftUI/documentation/OpenSwiftUI/Ellipse/tint(_:)":{"identifier":"doc:\/\/OpenSwiftUI\/documentation\/OpenSwiftUI\/Ellipse\/tint(_:)","role":"symbol","url":"\/documentation\/openswiftui\/ellipse\/tint(_:)","fragments":[{"text":"func","kind":"keyword"},{"text":" ","kind":"text"},{"text":"tint","kind":"identifier"},{"text":"(","kind":"text"},{"text":"Color","preciseIdentifier":"s:15OpenSwiftUICore5ColorV","kind":"typeIdentifier"},{"text":"?) -> ","kind":"text"},{"text":"some","kind":"keyword"},{"text":" ","kind":"text"},{"text":"View","preciseIdentifier":"s:15OpenSwiftUICore4ViewP","kind":"typeIdentifier"}],"title":"tint(_:)","abstract":[{"text":"Sets the tint color within this view.","type":"text"}],"kind":"symbol","type":"topic"},"doc://OpenSwiftUI/documentation/OpenSwiftUI/Ellipse/scaledToFit()":{"title":"scaledToFit()","role":"symbol","type":"topic","abstract":[{"text":"Scales this view to fit its parent.","type":"text"}],"kind":"symbol","fragments":[{"text":"func","kind":"keyword"},{"text":" ","kind":"text"},{"text":"scaledToFit","kind":"identifier"},{"text":"() -> ","kind":"text"},{"text":"some","kind":"keyword"},{"text":" ","kind":"text"},{"text":"View","preciseIdentifier":"s:15OpenSwiftUICore4ViewP","kind":"typeIdentifier"}],"identifier":"doc:\/\/OpenSwiftUI\/documentation\/OpenSwiftUI\/Ellipse\/scaledToFit()","url":"\/documentation\/openswiftui\/ellipse\/scaledtofit()"},"doc://OpenSwiftUI/documentation/OpenSwiftUI/Ellipse/onAppear(perform:)":{"kind":"symbol","title":"onAppear(perform:)","role":"symbol","abstract":[{"type":"text","text":"Adds an action to perform before this view appears."}],"identifier":"doc:\/\/OpenSwiftUI\/documentation\/OpenSwiftUI\/Ellipse\/onAppear(perform:)","fragments":[{"text":"func","kind":"keyword"},{"text":" ","kind":"text"},{"text":"onAppear","kind":"identifier"},{"text":"(","kind":"text"},{"text":"perform","kind":"externalParam"},{"text":": (() -> ","kind":"text"},{"text":"Void","preciseIdentifier":"s:s4Voida","kind":"typeIdentifier"},{"text":")?) -> ","kind":"text"},{"text":"some","kind":"keyword"},{"text":" ","kind":"text"},{"text":"View","preciseIdentifier":"s:15OpenSwiftUICore4ViewP","kind":"typeIdentifier"}],"type":"topic","url":"\/documentation\/openswiftui\/ellipse\/onappear(perform:)"},"doc://OpenSwiftUI/documentation/OpenSwiftUI/Ellipse/scaledToFill()":{"fragments":[{"text":"func","kind":"keyword"},{"text":" ","kind":"text"},{"text":"scaledToFill","kind":"identifier"},{"text":"() -> ","kind":"text"},{"text":"some","kind":"keyword"},{"text":" ","kind":"text"},{"text":"View","preciseIdentifier":"s:15OpenSwiftUICore4ViewP","kind":"typeIdentifier"}],"url":"\/documentation\/openswiftui\/ellipse\/scaledtofill()","kind":"symbol","abstract":[{"text":"Scales this view to fill its parent.","type":"text"}],"identifier":"doc:\/\/OpenSwiftUI\/documentation\/OpenSwiftUI\/Ellipse\/scaledToFill()","role":"symbol","type":"topic","title":"scaledToFill()"},"doc://OpenSwiftUI/documentation/OpenSwiftUI/Ellipse/colorScheme(_:)":{"url":"\/documentation\/openswiftui\/ellipse\/colorscheme(_:)","kind":"symbol","identifier":"doc:\/\/OpenSwiftUI\/documentation\/OpenSwiftUI\/Ellipse\/colorScheme(_:)","role":"symbol","abstract":[{"text":"Sets this view’s color scheme.","type":"text"}],"fragments":[{"text":"func","kind":"keyword"},{"text":" ","kind":"text"},{"text":"colorScheme","kind":"identifier"},{"text":"(","kind":"text"},{"text":"ColorScheme","preciseIdentifier":"s:15OpenSwiftUICore11ColorSchemeO","kind":"typeIdentifier"},{"text":") -> ","kind":"text"},{"text":"some","kind":"keyword"},{"text":" ","kind":"text"},{"text":"View","preciseIdentifier":"s:15OpenSwiftUICore4ViewP","kind":"typeIdentifier"}],"type":"topic","title":"colorScheme(_:)"},"doc://OpenSwiftUI/documentation/OpenSwiftUI/Ellipse/padding(_:_:)":{"kind":"symbol","title":"padding(_:_:)","type":"topic","url":"\/documentation\/openswiftui\/ellipse\/padding(_:_:)","fragments":[{"text":"func","kind":"keyword"},{"text":" ","kind":"text"},{"text":"padding","kind":"identifier"},{"text":"(","kind":"text"},{"text":"Edge","preciseIdentifier":"s:15OpenSwiftUICore4EdgeO","kind":"typeIdentifier"},{"text":".","kind":"text"},{"text":"Set","preciseIdentifier":"s:15OpenSwiftUICore4EdgeO3SetV","kind":"typeIdentifier"},{"text":", ","kind":"text"},{"text":"CGFloat","preciseIdentifier":"s:14CoreFoundation7CGFloatV","kind":"typeIdentifier"},{"text":"?) -> ","kind":"text"},{"text":"some","kind":"keyword"},{"text":" ","kind":"text"},{"text":"View","preciseIdentifier":"s:15OpenSwiftUICore4ViewP","kind":"typeIdentifier"}],"abstract":[{"type":"text","text":"Adds an equal padding amount to specific edges of this view."}],"role":"symbol","identifier":"doc:\/\/OpenSwiftUI\/documentation\/OpenSwiftUI\/Ellipse\/padding(_:_:)"},"doc://OpenSwiftUI/documentation/OpenSwiftUI/Ellipse/dynamicTypeSize(_:)":{"identifier":"doc:\/\/OpenSwiftUI\/documentation\/OpenSwiftUI\/Ellipse\/dynamicTypeSize(_:)","url":"\/documentation\/openswiftui\/ellipse\/dynamictypesize(_:)","title":"dynamicTypeSize(_:)","type":"topic","abstract":[{"text":"Sets the Dynamic Type size within the view to the given value.","type":"text"}],"fragments":[{"text":"func","kind":"keyword"},{"text":" ","kind":"text"},{"text":"dynamicTypeSize","kind":"identifier"},{"text":"(","kind":"text"},{"text":"DynamicTypeSize","preciseIdentifier":"s:15OpenSwiftUICore15DynamicTypeSizeO","kind":"typeIdentifier"},{"text":") -> ","kind":"text"},{"text":"some","kind":"keyword"},{"text":" ","kind":"text"},{"text":"View","preciseIdentifier":"s:15OpenSwiftUICore4ViewP","kind":"typeIdentifier"}],"role":"symbol","kind":"symbol"},"doc://OpenSwiftUI/documentation/OpenSwiftUI/Ellipse/layoutPriority(_:)":{"abstract":[{"text":"Sets the priority by which a parent layout should apportion space to","type":"text"},{"text":" ","type":"text"},{"text":"this child.","type":"text"}],"identifier":"doc:\/\/OpenSwiftUI\/documentation\/OpenSwiftUI\/Ellipse\/layoutPriority(_:)","type":"topic","role":"symbol","title":"layoutPriority(_:)","kind":"symbol","url":"\/documentation\/openswiftui\/ellipse\/layoutpriority(_:)","fragments":[{"text":"func","kind":"keyword"},{"text":" ","kind":"text"},{"text":"layoutPriority","kind":"identifier"},{"text":"(","kind":"text"},{"text":"Double","preciseIdentifier":"s:Sd","kind":"typeIdentifier"},{"text":") -> ","kind":"text"},{"text":"some","kind":"keyword"},{"text":" ","kind":"text"},{"text":"View","preciseIdentifier":"s:15OpenSwiftUICore4ViewP","kind":"typeIdentifier"}]},"doc://OpenSwiftUI/documentation/OpenSwiftUI/Ellipse/transaction(_:body:)":{"fragments":[{"text":"func","kind":"keyword"},{"text":" ","kind":"text"},{"text":"transaction","kind":"identifier"},{"text":"<","kind":"text"},{"text":"V","kind":"genericParameter"},{"text":">((","kind":"text"},{"text":"inout","kind":"keyword"},{"text":" ","kind":"text"},{"text":"Transaction","kind":"typeIdentifier","preciseIdentifier":"s:15OpenSwiftUICore11TransactionV"},{"text":") -> ","kind":"text"},{"text":"Void","kind":"typeIdentifier","preciseIdentifier":"s:s4Voida"},{"text":", ","kind":"text"},{"text":"body","kind":"externalParam"},{"text":": (","kind":"text"},{"text":"PlaceholderContentView","kind":"typeIdentifier","preciseIdentifier":"s:15OpenSwiftUICore22PlaceholderContentViewV"},{"text":"<","kind":"text"},{"text":"Self","kind":"typeIdentifier"},{"text":">) -> ","kind":"text"},{"text":"V","kind":"typeIdentifier"},{"text":") -> ","kind":"text"},{"text":"some","kind":"keyword"},{"text":" ","kind":"text"},{"text":"View","kind":"typeIdentifier","preciseIdentifier":"s:15OpenSwiftUICore4ViewP"}],"kind":"symbol","type":"topic","title":"transaction(_:body:)","identifier":"doc:\/\/OpenSwiftUI\/documentation\/OpenSwiftUI\/Ellipse\/transaction(_:body:)","abstract":[{"type":"text","text":"Applies the given transaction mutation function to all animations used"},{"type":"text","text":" "},{"text":"within the ","type":"text"},{"type":"codeVoice","code":"body"},{"text":" closure.","type":"text"}],"role":"symbol","url":"\/documentation\/openswiftui\/ellipse\/transaction(_:body:)"},"doc://OpenSwiftUI/documentation/OpenSwiftUI/Ellipse/rotationEffect(_:anchor:)":{"url":"\/documentation\/openswiftui\/ellipse\/rotationeffect(_:anchor:)","fragments":[{"text":"func","kind":"keyword"},{"text":" ","kind":"text"},{"text":"rotationEffect","kind":"identifier"},{"text":"(","kind":"text"},{"text":"Angle","kind":"typeIdentifier","preciseIdentifier":"s:15OpenSwiftUICore5AngleV"},{"text":", ","kind":"text"},{"text":"anchor","kind":"externalParam"},{"text":": ","kind":"text"},{"text":"UnitPoint","kind":"typeIdentifier","preciseIdentifier":"s:15OpenSwiftUICore9UnitPointV"},{"text":") -> ","kind":"text"},{"text":"some","kind":"keyword"},{"text":" ","kind":"text"},{"text":"View","kind":"typeIdentifier","preciseIdentifier":"s:15OpenSwiftUICore4ViewP"}],"abstract":[{"text":"Rotates a view’s rendered output in two dimensions around the specified","type":"text"},{"text":" ","type":"text"},{"text":"point.","type":"text"}],"kind":"symbol","identifier":"doc:\/\/OpenSwiftUI\/documentation\/OpenSwiftUI\/Ellipse\/rotationEffect(_:anchor:)","type":"topic","role":"symbol","title":"rotationEffect(_:anchor:)"},"doc://OpenSwiftUI/documentation/OpenSwiftUI/Ellipse/safeAreaInset(edge:alignment:spacing:content:)-5nnzo":{"fragments":[{"text":"func","kind":"keyword"},{"text":" ","kind":"text"},{"text":"safeAreaInset","kind":"identifier"},{"text":"<","kind":"text"},{"text":"V","kind":"genericParameter"},{"text":">(","kind":"text"},{"text":"edge","kind":"externalParam"},{"text":": ","kind":"text"},{"preciseIdentifier":"s:15OpenSwiftUICore14HorizontalEdgeO","text":"HorizontalEdge","kind":"typeIdentifier"},{"text":", ","kind":"text"},{"text":"alignment","kind":"externalParam"},{"text":": ","kind":"text"},{"preciseIdentifier":"s:15OpenSwiftUICore17VerticalAlignmentV","text":"VerticalAlignment","kind":"typeIdentifier"},{"text":", ","kind":"text"},{"text":"spacing","kind":"externalParam"},{"text":": ","kind":"text"},{"preciseIdentifier":"s:14CoreFoundation7CGFloatV","text":"CGFloat","kind":"typeIdentifier"},{"text":"?, ","kind":"text"},{"text":"content","kind":"externalParam"},{"text":": () -> ","kind":"text"},{"text":"V","kind":"typeIdentifier"},{"text":") -> ","kind":"text"},{"text":"some","kind":"keyword"},{"text":" ","kind":"text"},{"preciseIdentifier":"s:15OpenSwiftUICore4ViewP","text":"View","kind":"typeIdentifier"}],"kind":"symbol","role":"symbol","type":"topic","abstract":[{"text":"Shows the specified content beside the modified view.","type":"text"}],"url":"\/documentation\/openswiftui\/ellipse\/safeareainset(edge:alignment:spacing:content:)-5nnzo","title":"safeAreaInset(edge:alignment:spacing:content:)","identifier":"doc:\/\/OpenSwiftUI\/documentation\/OpenSwiftUI\/Ellipse\/safeAreaInset(edge:alignment:spacing:content:)-5nnzo"},"doc://OpenSwiftUI/documentation/OpenSwiftUI/Ellipse/foregroundStyle(_:_:)":{"fragments":[{"text":"func","kind":"keyword"},{"text":" ","kind":"text"},{"text":"foregroundStyle","kind":"identifier"},{"text":"<","kind":"text"},{"text":"S1","kind":"genericParameter"},{"text":", ","kind":"text"},{"text":"S2","kind":"genericParameter"},{"text":">(","kind":"text"},{"text":"S1","kind":"typeIdentifier"},{"text":", ","kind":"text"},{"text":"S2","kind":"typeIdentifier"},{"text":") -> ","kind":"text"},{"text":"some","kind":"keyword"},{"text":" ","kind":"text"},{"preciseIdentifier":"s:15OpenSwiftUICore4ViewP","text":"View","kind":"typeIdentifier"}],"kind":"symbol","type":"topic","title":"foregroundStyle(_:_:)","identifier":"doc:\/\/OpenSwiftUI\/documentation\/OpenSwiftUI\/Ellipse\/foregroundStyle(_:_:)","abstract":[{"type":"text","text":"Sets the primary and secondary levels of the foreground"},{"type":"text","text":" "},{"type":"text","text":"style in the child view."}],"role":"symbol","url":"\/documentation\/openswiftui\/ellipse\/foregroundstyle(_:_:)"},"doc://OpenSwiftUI/documentation/OpenSwiftUI/Ellipse/background(alignment:content:)":{"url":"\/documentation\/openswiftui\/ellipse\/background(alignment:content:)","abstract":[{"text":"Layers the views that you specify behind this view.","type":"text"}],"type":"topic","title":"background(alignment:content:)","role":"symbol","identifier":"doc:\/\/OpenSwiftUI\/documentation\/OpenSwiftUI\/Ellipse\/background(alignment:content:)","fragments":[{"kind":"keyword","text":"func"},{"kind":"text","text":" "},{"kind":"identifier","text":"background"},{"kind":"text","text":"<"},{"kind":"genericParameter","text":"V"},{"kind":"text","text":">("},{"kind":"externalParam","text":"alignment"},{"kind":"text","text":": "},{"kind":"typeIdentifier","text":"Alignment","preciseIdentifier":"s:15OpenSwiftUICore9AlignmentV"},{"kind":"text","text":", "},{"kind":"externalParam","text":"content"},{"kind":"text","text":": () -> "},{"kind":"typeIdentifier","text":"V"},{"kind":"text","text":") -> "},{"kind":"keyword","text":"some"},{"kind":"text","text":" "},{"kind":"typeIdentifier","text":"View","preciseIdentifier":"s:15OpenSwiftUICore4ViewP"}],"kind":"symbol"}}}