{"sections":[],"primaryContentSections":[{"declarations":[{"platforms":["macOS"],"tokens":[{"kind":"keyword","text":"func"},{"kind":"text","text":" "},{"kind":"identifier","text":"sizeThatFits"},{"kind":"text","text":"("},{"kind":"externalParam","text":"proposal"},{"kind":"text","text":": "},{"preciseIdentifier":"s:15OpenSwiftUICore16ProposedViewSizeV","kind":"typeIdentifier","text":"ProposedViewSize","identifier":"doc:\/\/OpenSwiftUI\/documentation\/OpenSwiftUI\/ProposedViewSize"},{"kind":"text","text":", "},{"kind":"externalParam","text":"subviews"},{"kind":"text","text":": "},{"preciseIdentifier":"s:15OpenSwiftUICore9AnyLayoutV","kind":"typeIdentifier","text":"AnyLayout","identifier":"doc:\/\/OpenSwiftUI\/documentation\/OpenSwiftUI\/AnyLayout"},{"kind":"text","text":"."},{"preciseIdentifier":"s:15OpenSwiftUICore6LayoutP8Subviewsa","kind":"typeIdentifier","text":"Subviews","identifier":"doc:\/\/OpenSwiftUI\/documentation\/OpenSwiftUI\/Layout\/Subviews"},{"kind":"text","text":", "},{"kind":"externalParam","text":"cache"},{"kind":"text","text":": "},{"kind":"keyword","text":"inout"},{"kind":"text","text":" "},{"preciseIdentifier":"s:15OpenSwiftUICore9AnyLayoutV","kind":"typeIdentifier","text":"AnyLayout","identifier":"doc:\/\/OpenSwiftUI\/documentation\/OpenSwiftUI\/AnyLayout"},{"kind":"text","text":"."},{"preciseIdentifier":"s:15OpenSwiftUICore9AnyLayoutV5CacheV","kind":"typeIdentifier","text":"Cache","identifier":"doc:\/\/OpenSwiftUI\/documentation\/OpenSwiftUI\/AnyLayout\/Cache"},{"kind":"text","text":") -> "},{"preciseIdentifier":"c:@S@CGSize","kind":"typeIdentifier","text":"CGSize"}],"languages":["swift"]}],"kind":"declarations"},{"parameters":[{"name":"proposal","content":[{"type":"paragraph","inlineContent":[{"type":"text","text":"A size proposal for the container. The container’s parent"},{"type":"text","text":" "},{"type":"text","text":"view that calls this method might call the method more than once"},{"type":"text","text":" "},{"type":"text","text":"with different proposals to learn more about the container’s"},{"type":"text","text":" "},{"type":"text","text":"flexibility before deciding which proposal to use for placement."}]}]},{"name":"subviews","content":[{"type":"paragraph","inlineContent":[{"text":"A collection of proxies that represent the","type":"text"},{"text":" ","type":"text"},{"text":"views that the container arranges. You can use the proxies in the","type":"text"},{"text":" ","type":"text"},{"text":"collection to get information about the subviews as you determine","type":"text"},{"text":" ","type":"text"},{"text":"how much space the container needs to display them.","type":"text"}]}]},{"name":"cache","content":[{"inlineContent":[{"type":"text","text":"Optional storage for calculated data that you can share among"},{"type":"text","text":" "},{"type":"text","text":"the methods of your custom layout container. See"},{"type":"text","text":" "},{"isActive":true,"type":"reference","identifier":"doc:\/\/OpenSwiftUI\/documentation\/OpenSwiftUI\/AnyLayout\/makeCache(subviews:)"},{"type":"text","text":" for details."}],"type":"paragraph"}]}],"kind":"parameters"},{"content":[{"anchor":"return-value","type":"heading","level":2,"text":"Return Value"},{"inlineContent":[{"text":"A size that indicates how much space the container","type":"text"},{"text":" ","type":"text"},{"text":"needs to arrange its subviews.","type":"text"}],"type":"paragraph"}],"kind":"content"},{"content":[{"type":"heading","level":2,"text":"Discussion","anchor":"discussion"},{"type":"paragraph","inlineContent":[{"text":"Implement this method to tell your custom layout container’s parent","type":"text"},{"text":" ","type":"text"},{"text":"view how much space the container needs for a set of subviews, given","type":"text"},{"text":" ","type":"text"},{"text":"a size proposal. The parent might call this method more than once","type":"text"},{"text":" ","type":"text"},{"text":"during a layout pass with different proposed sizes to test the","type":"text"},{"text":" ","type":"text"},{"text":"flexibility of the container, using proposals like:","type":"text"}]},{"items":[{"content":[{"inlineContent":[{"type":"text","text":"The "},{"type":"reference","identifier":"doc:\/\/OpenSwiftUI\/documentation\/OpenSwiftUI\/ProposedViewSize\/zero","isActive":true},{"type":"text","text":" proposal; respond with the"},{"type":"text","text":" "},{"type":"text","text":"layout’s minimum size."}],"type":"paragraph"}]},{"content":[{"inlineContent":[{"type":"text","text":"The "},{"type":"reference","identifier":"doc:\/\/OpenSwiftUI\/documentation\/OpenSwiftUI\/ProposedViewSize\/infinity","isActive":true},{"type":"text","text":" proposal; respond with the"},{"type":"text","text":" "},{"type":"text","text":"layout’s maximum size."}],"type":"paragraph"}]},{"content":[{"type":"paragraph","inlineContent":[{"text":"The ","type":"text"},{"identifier":"doc:\/\/OpenSwiftUI\/documentation\/OpenSwiftUI\/ProposedViewSize\/unspecified","isActive":true,"type":"reference"},{"text":" proposal; respond with the","type":"text"},{"text":" ","type":"text"},{"text":"layout’s ideal size.","type":"text"}]}]}],"type":"unorderedList"},{"type":"paragraph","inlineContent":[{"text":"The parent might also choose to test flexibility in one dimension at a","type":"text"},{"text":" ","type":"text"},{"text":"time. For example, a horizontal stack might propose a fixed height and","type":"text"},{"text":" ","type":"text"},{"text":"an infinite width, and then the same height with a zero width.","type":"text"}]},{"type":"paragraph","inlineContent":[{"text":"The following example calculates the size for a basic vertical stack","type":"text"},{"text":" ","type":"text"},{"text":"that places views in a column, with no spacing between the views:","type":"text"}]},{"type":"codeListing","code":["private struct BasicVStack: Layout {","    func sizeThatFits(","        proposal: ProposedViewSize,","        subviews: Subviews,","        cache: inout ()","    ) -> CGSize {","        subviews.reduce(CGSize.zero) { result, subview in","            let size = subview.sizeThatFits(.unspecified)","            return CGSize(","                width: max(result.width, size.width),","                height: result.height + size.height)","        }","    }","","    \/\/ This layout also needs a placeSubviews() implementation.","}"],"syntax":"swift"},{"type":"paragraph","inlineContent":[{"type":"text","text":"The implementation asks each subview for its ideal size by calling the"},{"type":"text","text":" "},{"type":"reference","isActive":true,"identifier":"doc:\/\/OpenSwiftUI\/documentation\/OpenSwiftUI\/LayoutSubview\/sizeThatFits(_:)"},{"type":"text","text":" method with an"},{"type":"text","text":" "},{"type":"reference","isActive":true,"identifier":"doc:\/\/OpenSwiftUI\/documentation\/OpenSwiftUI\/ProposedViewSize\/unspecified"},{"type":"text","text":" proposed size."},{"type":"text","text":" "},{"type":"text","text":"It then reduces these values into a single size that represents"},{"type":"text","text":" "},{"type":"text","text":"the maximum subview width and the sum of subview heights."},{"type":"text","text":" "},{"type":"text","text":"Because this example isn’t flexible, it ignores its size proposal"},{"type":"text","text":" "},{"type":"text","text":"input and always returns the same value for a given set of subviews."}]},{"type":"paragraph","inlineContent":[{"type":"text","text":"OpenSwiftUI views choose their own size, so the layout engine always"},{"type":"text","text":" "},{"type":"text","text":"uses a value that you return from this method as the actual size of the"},{"type":"text","text":" "},{"type":"text","text":"composite view. That size factors into the construction of the "},{"type":"codeVoice","code":"bounds"},{"type":"text","text":" "},{"type":"text","text":"input to the "},{"type":"reference","identifier":"doc:\/\/OpenSwiftUI\/documentation\/OpenSwiftUI\/AnyLayout\/placeSubviews(in:proposal:subviews:cache:)","isActive":true},{"type":"text","text":" method."}]}],"kind":"content"}],"kind":"symbol","metadata":{"role":"symbol","modules":[{"name":"OpenSwiftUI"}],"externalID":"s:15OpenSwiftUICore9AnyLayoutV12sizeThatFits8proposal8subviews5cacheSo6CGSizeVAA16ProposedViewSizeV_AA0E8SubviewsVAC5CacheVztF","symbolKind":"method","fragments":[{"text":"func","kind":"keyword"},{"text":" ","kind":"text"},{"text":"sizeThatFits","kind":"identifier"},{"text":"(","kind":"text"},{"text":"proposal","kind":"externalParam"},{"text":": ","kind":"text"},{"text":"ProposedViewSize","kind":"typeIdentifier","preciseIdentifier":"s:15OpenSwiftUICore16ProposedViewSizeV"},{"text":", ","kind":"text"},{"text":"subviews","kind":"externalParam"},{"text":": ","kind":"text"},{"text":"AnyLayout","kind":"typeIdentifier","preciseIdentifier":"s:15OpenSwiftUICore9AnyLayoutV"},{"text":".","kind":"text"},{"text":"Subviews","kind":"typeIdentifier","preciseIdentifier":"s:15OpenSwiftUICore6LayoutP8Subviewsa"},{"text":", ","kind":"text"},{"text":"cache","kind":"externalParam"},{"text":": ","kind":"text"},{"text":"inout","kind":"keyword"},{"text":" ","kind":"text"},{"text":"AnyLayout","kind":"typeIdentifier","preciseIdentifier":"s:15OpenSwiftUICore9AnyLayoutV"},{"text":".","kind":"text"},{"text":"Cache","kind":"typeIdentifier","preciseIdentifier":"s:15OpenSwiftUICore9AnyLayoutV5CacheV"},{"text":") -> ","kind":"text"},{"text":"CGSize","kind":"typeIdentifier","preciseIdentifier":"c:@S@CGSize"}],"roleHeading":"Instance Method","title":"sizeThatFits(proposal:subviews:cache:)","remoteSource":{"url":"https:\/\/github.com\/OpenSwiftUIProject\/OpenSwiftUI\/blob\/main\/Sources\/OpenSwiftUICore\/Layout\/AnyLayout.swift#L277","fileName":"AnyLayout.swift"}},"schemaVersion":{"major":0,"minor":3,"patch":0},"identifier":{"url":"doc:\/\/OpenSwiftUI\/documentation\/OpenSwiftUI\/AnyLayout\/sizeThatFits(proposal:subviews:cache:)","interfaceLanguage":"swift"},"hierarchy":{"paths":[["doc:\/\/OpenSwiftUI\/documentation\/OpenSwiftUI","doc:\/\/OpenSwiftUI\/documentation\/OpenSwiftUI\/AnyLayout"]]},"abstract":[{"text":"Returns the size of the composite view, given a proposed size","type":"text"},{"text":" ","type":"text"},{"text":"and the view’s subviews.","type":"text"}],"variants":[{"traits":[{"interfaceLanguage":"swift"}],"paths":["\/documentation\/openswiftui\/anylayout\/sizethatfits(proposal:subviews:cache:)"]}],"references":{"doc://OpenSwiftUI/documentation/OpenSwiftUI/ProposedViewSize/zero":{"type":"topic","role":"symbol","url":"\/documentation\/openswiftui\/proposedviewsize\/zero","kind":"symbol","fragments":[{"text":"static","kind":"keyword"},{"text":" ","kind":"text"},{"text":"let","kind":"keyword"},{"text":" ","kind":"text"},{"text":"zero","kind":"identifier"},{"text":": ","kind":"text"},{"preciseIdentifier":"s:15OpenSwiftUICore16ProposedViewSizeV","text":"ProposedViewSize","kind":"typeIdentifier"}],"identifier":"doc:\/\/OpenSwiftUI\/documentation\/OpenSwiftUI\/ProposedViewSize\/zero","title":"zero","abstract":[{"type":"text","text":"A size proposal that contains zero in both dimensions."}]},"doc://OpenSwiftUI/documentation/OpenSwiftUI/AnyLayout/makeCache(subviews:)":{"type":"topic","role":"symbol","url":"\/documentation\/openswiftui\/anylayout\/makecache(subviews:)","kind":"symbol","fragments":[{"text":"func","kind":"keyword"},{"text":" ","kind":"text"},{"text":"makeCache","kind":"identifier"},{"text":"(","kind":"text"},{"text":"subviews","kind":"externalParam"},{"text":": ","kind":"text"},{"preciseIdentifier":"s:15OpenSwiftUICore9AnyLayoutV","text":"AnyLayout","kind":"typeIdentifier"},{"text":".","kind":"text"},{"preciseIdentifier":"s:15OpenSwiftUICore6LayoutP8Subviewsa","text":"Subviews","kind":"typeIdentifier"},{"text":") -> ","kind":"text"},{"preciseIdentifier":"s:15OpenSwiftUICore9AnyLayoutV","text":"AnyLayout","kind":"typeIdentifier"},{"text":".","kind":"text"},{"preciseIdentifier":"s:15OpenSwiftUICore9AnyLayoutV5CacheV","text":"Cache","kind":"typeIdentifier"}],"identifier":"doc:\/\/OpenSwiftUI\/documentation\/OpenSwiftUI\/AnyLayout\/makeCache(subviews:)","title":"makeCache(subviews:)","abstract":[{"text":"Creates and initializes a cache for a layout instance.","type":"text"}]},"doc://OpenSwiftUI/documentation/OpenSwiftUI/AnyLayout/Cache":{"type":"topic","role":"symbol","navigatorTitle":[{"text":"Cache","kind":"identifier"}],"url":"\/documentation\/openswiftui\/anylayout\/cache","kind":"symbol","fragments":[{"text":"struct","kind":"keyword"},{"text":" ","kind":"text"},{"text":"Cache","kind":"identifier"}],"identifier":"doc:\/\/OpenSwiftUI\/documentation\/OpenSwiftUI\/AnyLayout\/Cache","title":"AnyLayout.Cache","abstract":[{"type":"text","text":"Cached values associated with the layout instance."}]},"doc://OpenSwiftUI/documentation/OpenSwiftUI":{"identifier":"doc:\/\/OpenSwiftUI\/documentation\/OpenSwiftUI","url":"\/documentation\/openswiftui","role":"collection","type":"topic","kind":"symbol","abstract":[{"type":"text","text":"Declare the user interface and behavior for your app on every platform."}],"title":"OpenSwiftUI"},"doc://OpenSwiftUI/documentation/OpenSwiftUI/ProposedViewSize":{"fragments":[{"kind":"keyword","text":"struct"},{"kind":"text","text":" "},{"kind":"identifier","text":"ProposedViewSize"}],"navigatorTitle":[{"kind":"identifier","text":"ProposedViewSize"}],"url":"\/documentation\/openswiftui\/proposedviewsize","kind":"symbol","type":"topic","identifier":"doc:\/\/OpenSwiftUI\/documentation\/OpenSwiftUI\/ProposedViewSize","title":"ProposedViewSize","abstract":[{"type":"text","text":"A proposal for the size of a view."}],"role":"symbol"},"doc://OpenSwiftUI/documentation/OpenSwiftUI/AnyLayout/sizeThatFits(proposal:subviews:cache:)":{"type":"topic","role":"symbol","url":"\/documentation\/openswiftui\/anylayout\/sizethatfits(proposal:subviews:cache:)","kind":"symbol","fragments":[{"text":"func","kind":"keyword"},{"text":" ","kind":"text"},{"text":"sizeThatFits","kind":"identifier"},{"text":"(","kind":"text"},{"text":"proposal","kind":"externalParam"},{"text":": ","kind":"text"},{"preciseIdentifier":"s:15OpenSwiftUICore16ProposedViewSizeV","text":"ProposedViewSize","kind":"typeIdentifier"},{"text":", ","kind":"text"},{"text":"subviews","kind":"externalParam"},{"text":": ","kind":"text"},{"preciseIdentifier":"s:15OpenSwiftUICore9AnyLayoutV","text":"AnyLayout","kind":"typeIdentifier"},{"text":".","kind":"text"},{"preciseIdentifier":"s:15OpenSwiftUICore6LayoutP8Subviewsa","text":"Subviews","kind":"typeIdentifier"},{"text":", ","kind":"text"},{"text":"cache","kind":"externalParam"},{"text":": ","kind":"text"},{"text":"inout","kind":"keyword"},{"text":" ","kind":"text"},{"preciseIdentifier":"s:15OpenSwiftUICore9AnyLayoutV","text":"AnyLayout","kind":"typeIdentifier"},{"text":".","kind":"text"},{"preciseIdentifier":"s:15OpenSwiftUICore9AnyLayoutV5CacheV","text":"Cache","kind":"typeIdentifier"},{"text":") -> ","kind":"text"},{"preciseIdentifier":"c:@S@CGSize","text":"CGSize","kind":"typeIdentifier"}],"identifier":"doc:\/\/OpenSwiftUI\/documentation\/OpenSwiftUI\/AnyLayout\/sizeThatFits(proposal:subviews:cache:)","title":"sizeThatFits(proposal:subviews:cache:)","abstract":[{"type":"text","text":"Returns the size of the composite view, given a proposed size"},{"type":"text","text":" "},{"type":"text","text":"and the view’s subviews."}]},"doc://OpenSwiftUI/documentation/OpenSwiftUI/AnyLayout":{"url":"\/documentation\/openswiftui\/anylayout","abstract":[{"text":"A type-erased instance of the layout protocol.","type":"text"}],"identifier":"doc:\/\/OpenSwiftUI\/documentation\/OpenSwiftUI\/AnyLayout","navigatorTitle":[{"text":"AnyLayout","kind":"identifier"}],"fragments":[{"text":"struct","kind":"keyword"},{"text":" ","kind":"text"},{"text":"AnyLayout","kind":"identifier"}],"role":"symbol","kind":"symbol","type":"topic","title":"AnyLayout"},"doc://OpenSwiftUI/documentation/OpenSwiftUI/ProposedViewSize/unspecified":{"type":"topic","url":"\/documentation\/openswiftui\/proposedviewsize\/unspecified","identifier":"doc:\/\/OpenSwiftUI\/documentation\/OpenSwiftUI\/ProposedViewSize\/unspecified","kind":"symbol","role":"symbol","title":"unspecified","fragments":[{"text":"static","kind":"keyword"},{"text":" ","kind":"text"},{"text":"let","kind":"keyword"},{"text":" ","kind":"text"},{"text":"unspecified","kind":"identifier"},{"text":": ","kind":"text"},{"text":"ProposedViewSize","preciseIdentifier":"s:15OpenSwiftUICore16ProposedViewSizeV","kind":"typeIdentifier"}],"abstract":[{"text":"The proposed size with both dimensions left unspecified.","type":"text"}]},"doc://OpenSwiftUI/documentation/OpenSwiftUI/AnyLayout/placeSubviews(in:proposal:subviews:cache:)":{"type":"topic","role":"symbol","url":"\/documentation\/openswiftui\/anylayout\/placesubviews(in:proposal:subviews:cache:)","kind":"symbol","fragments":[{"text":"func","kind":"keyword"},{"text":" ","kind":"text"},{"text":"placeSubviews","kind":"identifier"},{"text":"(","kind":"text"},{"text":"in","kind":"externalParam"},{"text":": ","kind":"text"},{"preciseIdentifier":"c:@S@CGRect","text":"CGRect","kind":"typeIdentifier"},{"text":", ","kind":"text"},{"text":"proposal","kind":"externalParam"},{"text":": ","kind":"text"},{"preciseIdentifier":"s:15OpenSwiftUICore16ProposedViewSizeV","text":"ProposedViewSize","kind":"typeIdentifier"},{"text":", ","kind":"text"},{"text":"subviews","kind":"externalParam"},{"text":": ","kind":"text"},{"preciseIdentifier":"s:15OpenSwiftUICore9AnyLayoutV","text":"AnyLayout","kind":"typeIdentifier"},{"text":".","kind":"text"},{"preciseIdentifier":"s:15OpenSwiftUICore6LayoutP8Subviewsa","text":"Subviews","kind":"typeIdentifier"},{"text":", ","kind":"text"},{"text":"cache","kind":"externalParam"},{"text":": ","kind":"text"},{"text":"inout","kind":"keyword"},{"text":" ","kind":"text"},{"preciseIdentifier":"s:15OpenSwiftUICore9AnyLayoutV","text":"AnyLayout","kind":"typeIdentifier"},{"text":".","kind":"text"},{"preciseIdentifier":"s:15OpenSwiftUICore9AnyLayoutV5CacheV","text":"Cache","kind":"typeIdentifier"},{"text":")","kind":"text"}],"identifier":"doc:\/\/OpenSwiftUI\/documentation\/OpenSwiftUI\/AnyLayout\/placeSubviews(in:proposal:subviews:cache:)","title":"placeSubviews(in:proposal:subviews:cache:)","abstract":[{"type":"text","text":"Assigns positions to each of the layout’s subviews."}]},"doc://OpenSwiftUI/documentation/OpenSwiftUI/LayoutSubview/sizeThatFits(_:)":{"type":"topic","role":"symbol","url":"\/documentation\/openswiftui\/layoutsubview\/sizethatfits(_:)","kind":"symbol","fragments":[{"text":"func","kind":"keyword"},{"text":" ","kind":"text"},{"text":"sizeThatFits","kind":"identifier"},{"text":"(","kind":"text"},{"preciseIdentifier":"s:15OpenSwiftUICore16ProposedViewSizeV","text":"ProposedViewSize","kind":"typeIdentifier"},{"text":") -> ","kind":"text"},{"preciseIdentifier":"c:@S@CGSize","text":"CGSize","kind":"typeIdentifier"}],"identifier":"doc:\/\/OpenSwiftUI\/documentation\/OpenSwiftUI\/LayoutSubview\/sizeThatFits(_:)","title":"sizeThatFits(_:)","abstract":[{"type":"text","text":"Asks the subview for its size."}]},"doc://OpenSwiftUI/documentation/OpenSwiftUI/Layout/Subviews":{"fragments":[{"kind":"keyword","text":"typealias"},{"kind":"text","text":" "},{"kind":"identifier","text":"Subviews"}],"navigatorTitle":[{"kind":"identifier","text":"Subviews"}],"url":"\/documentation\/openswiftui\/layout\/subviews","kind":"symbol","type":"topic","identifier":"doc:\/\/OpenSwiftUI\/documentation\/OpenSwiftUI\/Layout\/Subviews","title":"Layout.Subviews","abstract":[{"text":"A collection of proxies for the subviews of a layout view.","type":"text"}],"role":"symbol"},"doc://OpenSwiftUI/documentation/OpenSwiftUI/ProposedViewSize/infinity":{"identifier":"doc:\/\/OpenSwiftUI\/documentation\/OpenSwiftUI\/ProposedViewSize\/infinity","type":"topic","url":"\/documentation\/openswiftui\/proposedviewsize\/infinity","fragments":[{"text":"static","kind":"keyword"},{"text":" ","kind":"text"},{"text":"let","kind":"keyword"},{"text":" ","kind":"text"},{"text":"infinity","kind":"identifier"},{"text":": ","kind":"text"},{"preciseIdentifier":"s:15OpenSwiftUICore16ProposedViewSizeV","text":"ProposedViewSize","kind":"typeIdentifier"}],"kind":"symbol","title":"infinity","abstract":[{"text":"A size proposal that contains infinity in both dimensions.","type":"text"}],"role":"symbol"}}}